Workbook
Name LIST_INDUSTRY: OFFSET('维度字典'!$A$2,0,0,COUNTA('维度字典'!$A$2:$A$200),1)
Name LIST_SALESPERSON: OFFSET('维度字典'!$C$2,0,0,COUNTA('维度字典'!$C$2:$C$200),1)
Name LIST_PRODUCT: OFFSET('维度字典'!$E$2,0,0,COUNTA('维度字典'!$E$2:$E$200),1)
Name LIST_REGION: OFFSET('维度字典'!$G$2,0,0,COUNTA('维度字典'!$G$2:$G$200),1)
Name LIST_METRIC_TARGET: OFFSET('维度字典'!$I$2,0,0,COUNTA('维度字典'!$I$2:$I$200),1)
Name LIST_METRIC_SYS: OFFSET('维度字典'!$M$2,0,0,COUNTA('维度字典'!$M$2:$M$200),1)
Name LIST_MONTH: '维度字典'!$U$2:$U$13

Sheet 填报指引
B2: 目标填报模板（SBU行业管理·按产品/行业/月份）v10
B3: 三层职责分离：目标填报（业务员唯一填报入口：年初设目标 + 月末填管道实际值）→ 系统实绩导入（管理员粘贴BI数据）→ 达成看板（全自动计算）
B5: 一、模板结构
B6: 「维度字典」维护行业/业务员/产品(钎焊、可拆)/区域/指标/参数，所有下拉自动联动。其中「目标填报指标」登记业务员可填报的全部 7 项指标及全年汇总方式；「实绩指标目录」只登记 BI 系统计算的指标（业务人员不填），是看板口径的权威清单。金额单位为万元。
B7: 「目标填报」业务员唯一填报表：每行 = 业务员×行业×产品×指标。①年初设定 5 类目标（销售目标额/毛利目标/毛利率目标/在手订单目标/目标客户机会目标），全年可修改，修改后所有达成率自动重算，并在「目标修订记录」列登记修改说明；②每月末在「在手订单」「目标客户机会」两行更新当月末最新实际值。
B8: 「系统实绩导入」BI 系统数据落地区：指标仅实绩销售额/实绩毛利，数据管理员每月从系统报表导出后粘贴当月列；业务人员不得修改。
B9: 「达成看板」全公式自动计算，无需填写：当期达成（本月销售额/毛利/毛利率/目标/达成率）、全年累计达成（累计/毛利率/年度目标/达成率/与目标差距）、管道充裕度（在手订单及目标与达成率、目标客户机会及目标与达成率）、下期预测（预测合计/剩余目标/预测达成率/预测与目标差距）；顶部可切换统计月份；组合行由维度字典自动展开，字典增删自动增减。
B10: 「经营汇总」产品×行业、业务员×产品、产品×月份、行业×月份 四块矩阵，公式自动。
B11: 「行业经营分析表」「业务员目标管理表」Word 样式汇报表，选月份/业务员后数字全自动。
B13: 二、填报规则（重点）
B14: 1. 一行 = 一个「业务员+行业+产品+指标」组合；同一组合同一指标只填一行，勿重复。
B15: 2. 目标填报：选好四个维度后，把 12 个月的值横向填入。目标类指标（销售/毛利/毛利率/在手订单目标/目标客户机会目标）年初设定、全年可改；「在手订单」「目标客户机会」为时点实际值，每月末只更新当月列。
... B42: 阈值在「维度字典」参数区维护（默认 黄线≥60%、绿线≥80%），改参数即全局生效，无需改任何公式。

Sheet 维度字典
A1: 行业维度（可增删） | C1: 业务员（可增删） | E1: 产品（钎焊/可拆，可扩展） | G1: 区域（预留） | I1: 目标填报指标 | J1: 汇总方式 | K1: 实绩指标目录（BI计算） | L1: 计算方式 | M1: 系统实绩指标 | N1: 汇总方式 | R1: 参数名 | S1: 参数值 | U1: 月份（固定1-12）
A2: 空调制冷 | C2: 张三 | E2: 钎焊 | G2: 华东 | I2: 销售目标额 | J2: 求和 | K2: 本月销售额 | L2: 系统计算 | M2: 实绩销售额 | N2: 求和 | R2: 目标年度（默认） | S2: 2027 | U2: 1
A3: 工业制冷 | C3: 李四 | E3: 可拆 | G3: 华南 | I3: 毛利目标 | J3: 求和 | K3: 本月毛利 | L3: 系统计算 | M3: 实绩毛利 | N3: 求和 | R3: 达成率·黄线（≥） | S3: 0.6 | U3: 2
A4: 船舶行业 | C4: 王五 | G4: 华北 | I4: 毛利率目标 | J4: 手工录入 | K4: 本月毛利率 | L4: 系统计算 | R4: 达成率·绿线（≥） | S4: 0.8 | U4: 3
A5: 储能行业 | I5: 在手订单目标 | J5: 最新值 | K5: 本月目标达成率 | L5: 系统计算 | R5: 金额单位 | S5: 万元 | U5: 4
A6: 数据中心 | I6: 目标客户机会目标 | J6: 最新值 | K6: 累计销售额 | L6: 系统计算 | U6: 5
I7: 在手订单 | J7: 最新值 | K7: 累计毛利 | L7: 系统计算 | U7: 6
I8: 目标客户机会 | J8: 最新值 | K8: 累计毛利率 | L8: 系统计算 | U8: 7
K9: 累计达成率 | L9: 系统计算 | U9: 8
K10: 与目标差距 | L10: 系统计算 | U10: 9
K11: 在手订单达成率 | L11: 系统计算 | U11: 10
K12: 目标客户机会达成率 | L12: 系统计算 | U12: 11
K13: 预测合计 | L13: 系统计算 | U13: 12
K14: 剩余目标 | L14: 系统计算
K15: 预测达成率 | L15: 系统计算
K16: 预测与目标差距 | L16: 系统计算

Sheet 目标填报
A1: 目标填报（按月）—— 业务员唯一填报入口：①年初设定5类目标（销售/毛利/毛利率/在手订单目标/目标客户机会目标，全年可改）；②每月末更新「在手订单」「目标客户机会」实际值
B2: 填报维度（下拉选择） | G2: 月度填报（万元）—— 当月填当列 | S2: 全年 | T2: 备注
A3: 序号 | B3: 业务员* | C3: 应用行业* | D3: 产品*(钎焊/可拆) | E3: 区域(预留) | F3: 填报指标* | G3: 1 | H3: 2 | I3: 3 | J3: 4 | K3: 5 | L3: 6 | M3: 7 | N3: 8 | O3: 9 | P3: 10 | Q3: 11 | R3: 12 | S3: 全年汇总 (自动/录入) | T3: 差异分析/备注 | U3: 目标修订记录
A4: =IF($B4="","",ROW()-3) | B4: 张三 | C4: 空调制冷 | D4: 钎焊 | E4: 华东 | F4: 销售目标额 | G4: 62 | H4: 53 | I4: 71 | J4: 79 | K4: 79 | L4: 88 | M4: 88 | N4: 79 | O4: 79 | P4: 79 | Q4: 71 | R4: 53 | S4: =IF($F4="","",IF(IFERROR(VLOOKUP($F4,'维度字典'!$I$2:$J$50,2,0),"求和")="手工录入","",IF(IFERROR(VLOOKUP($F4,'维度字典'!$I$2:$J$50,2,0),"求和")="最新值",IFERROR(LOOKUP(9.99E+307,G4:R4),""),SUM(G4:R4)))) | U4: 3月经营会调增：数据中心钎焊 +20
A5: =IF($B5="","",ROW()-3) | B5: 张三 | C5: 空调制冷 | D5: 钎焊 | E5: 华东 | F5: 毛利目标 | G5: 9.3 | H5: 7.9 | I5: 10.6 | J5: 11.9 | K5: 11.9 | L5: 13.2 | M5: 13.2 | N5: 11.9 | O5: 11.9 | P5: 11.9 | Q5: 10.6 | R5: 7.9 | S5: =IF($F5="","",IF(IFERROR(VLOOKUP($F5,'维度字典'!$I$2:$J$50,2,0),"求和")="手工录入","",IF(IFERROR(VLOOKUP($F5,'维度字典'!$I$2:$J$50,2,0),"求和")="最新值",IFERROR(LOOKUP(9.99E+307,G5:R5),""),SUM(G5:R5))))
A6: =IF($B6="","",ROW()-3) | B6: 张三 | C6: 空调制冷 | D6: 钎焊 | E6: 华东 | F6: 毛利率目标 | G6: 0.144 | H6: 0.1452 | I6: 0.1464 | J6: 0.1476 | K6: 0.1488 | L6: 0.15 | M6: 0.1512 | N6: 0.1524 | O6: 0.1536 | P6: 0.1548 | Q6: 0.156 | R6: 0.1572 | S6: 0.15
A7: =IF($B7="","",ROW()-3) | B7: 张三 | C7: 空调制冷 | D7: 钎焊 | E7: 华东 | F7: 在手订单目标 | G7: 104 | H7: 106 | I7: 107 | J7: 109 | K7: 110 | L7: 112 | M7: 113 | N7: 115 | O7: 116 | P7: 118 | Q7: 119 | R7: 121 | S7: =IF($F7="","",IF(IFERROR(VLOOKUP($F7,'维度字典'!$I$2:$J$50,2,0),"求和")="手工录入","",IF(IFERROR(VLOOKUP($F7,'维度字典'!$I$2:$J$50,2,0),"求和")="最新值",IFERROR(LOOKUP(9.99E+307,G7:R7),""),SUM(G7:R7)))) | U7: 6月调整：客户A项目延期，7-9月各 -10
A8: =IF($B8="","",ROW()-3) | B8: 张三 | C8: 空调制冷 | D8: 钎焊 | E8: 华东 | F8: 目标客户机会目标 | G8: 75 | H8: 76 | I8: 78 | J8: 79 | K8: 81 | L8: 82 | M8: 84 | N8: 85 | O8: 87 | P8: 88 | Q8: 90 | R8: 91 | S8: =IF($F8="","",IF(IFERROR(VLOOKUP($F8,'维度字典'!$I$2:$J$50,2,0),"求和")="手工录入","",IF(IFERROR(VLOOKUP($F8,'维度字典'!$I$2:$J$50,2,0),"求和")="最新值",IFERROR(LOOKUP(9.99E+307,G8:R8),""),SUM(G8:R8))))
A9: =IF($B9="","",ROW()-3) | B9: 张三 | C9: 空调制冷 | D9: 钎焊 | E9: 华东 | F9: 在手订单 | G9: 104 | H9: 106 | I9: 107 | J9: 109 | K9: 110 | L9: 112 | M9: 113 | N9: 115 | O9: 116 | P9: 118 | Q9: 119 | R9: 121 | S9: =IF($F9="","",IF(IFERROR(VLOOKUP($F9,'维度字典'!$I$2:$J$50,2,0),"求和")="手工录入","",IF(IFERROR(VLOOKUP($F9,'维度字典'!$I$2:$J$50,2,0),"求和")="最新值",IFERROR(LOOKUP(9.99E+307,G9:R9),""),SUM(G9:R9)))) | T9: 管道充足：大客户在手订单集中，交付节奏稳定
A10: =IF($B10="","",ROW()-3) | B10: 张三 | C10: 空调制冷 | D10: 钎焊 | E10: 华东 | F10: 目标客户机会 | G10: 64 | H10: 65 | I10: 66 | J10: 67 | K10: 69 | L10: 70 | M10: 71 | N10: 72 | O10: 74 | P10: 75 | Q10: 77 | R10: 77 | S10: =IF($F10="","",IF(IFERROR(VLOOKUP($F10,'维度字典'!$I$2:$J$50,2,0),"求和")="手工录入","",IF(IFERROR(VLOOKUP($F10,'维度字典'!$I$2:$J$50,2,0),"求和")="最新值",IFERROR(LOOKUP(9.99E+307,G10:R10),""),SUM(G10:R10))))
A11: =IF($B11="","",ROW()-3) | B11: 张三 | C11: 空调制冷 | D11: 可拆 | E11: 华东 | F11: 销售目标额 | G11: 26 | H11: 23 | I11: 30 | J11: 34 | K11: 34 | L11: 38 | M11: 38 | N11: 34 | O11: 34 | P11: 34 | Q11: 30 | R11: 23 | S11: =IF($F11="","",IF(IFERROR(VLOOKUP($F11,'维度字典'!$I$2:$J$50,2,0),"求和")="手工录入","",IF(IFERROR(VLOOKUP($F11,'维度字典'!$I$2:$J$50,2,0),"求和")="最新值",IFERROR(LOOKUP(9.99E+307,G11:R11),""),SUM(G11:R11))))
A12: =IF($B12="","",ROW()-3) | B12: 张三 | C12: 空调制冷 | D12: 可拆 | E12: 华东 | F12: 毛利目标 | G12: 4 | H12: 3.4 | I12: 4.5 | J12: 5.1 | K12: 5.1 | L12: 5.7 | M12: 5.7 | N12: 5.1 | O12: 5.1 | P12: 5.1 | Q12: 4.5 | R12: 3.4 | S12: =IF($F12="","",IF(IFERROR(VLOOKUP($F12,'维度字典'!$I$2:$J$50,2,0),"求和")="手工录入","",IF(IFERROR(VLOOKUP($F12,'维度字典'!$I$2:$J$50,2,0),"求和")="最新值",IFERROR(LOOKUP(9.99E+307,G12:R12),""),SUM(G12:R12))))
A13: =IF($B13="","",ROW()-3) | B13: 张三 | C13: 空调制冷 | D13: 可拆 | E13: 华东 | F13: 毛利率目标 | G13: 0.144 | H13: 0.1452 | I13: 0.1464 | J13: 0.1476 | K13: 0.1488 | L13: 0.15 | M13: 0.1512 | N13: 0.1524 | O13: 0.1536 | P13: 0.1548 | Q13: 0.156 | R13: 0.1572 | S13: 0.15
A14: =IF($B14="","",ROW()-3) | B14: 张三 | C14: 空调制冷 | D14: 可拆 | E14: 华东 | F14: 在手订单目标 | G14: 45 | H14: 45 | I14: 46 | J14: 47 | K14: 47 | L14: 48 | M14: 49 | N14: 49 | O14: 50 | P14: 50 | Q14: 51 | R14: 52 | S14: =IF($F14="","",IF(IFERROR(VLOOKUP($F14,'维度字典'!$I$2:$J$50,2,0),"求和")="手工录入","",IF(IFERROR(VLOOKUP($F14,'维度字典'!$I$2:$J$50,2,0),"求和")="最新值",IFERROR(LOOKUP(9.99E+307,G14:R14),""),SUM(G14:R14))))
A15: =IF($B15="","",ROW()-3) | B15: 张三 | C15: 空调制冷 | D15: 可拆 | E15: 华东 | F15: 目标客户机会目标 | G15: 32 | H15: 33 | I15: 33 | J15: 34 | K15: 35 | L15: 35 | M15: 36 | N15: 37 | O15: 37 | P15: 38 | Q15: 38 | R15: 39 | S15: =IF($F15="","",IF(IFERROR(VLOOKUP($F15,'维度字典'!$I$2:$J$50,2,0),"求和")="手工录入","",IF(IFERROR(VLOOKUP($F15,'维度字典'!$I$2:$J$50,2,0),"求和")="最新值",IFERROR(LOOKUP(9.99E+307,G15:R15),""),SUM(G15:R15))))
A16: =IF($B16="","",ROW()-3) | B16: 张三 | C16: 空调制冷 | D16: 可拆 | E16: 华东 | F16: 在手订单 | G16: 45 | H16: 45 | I16: 46 | J16: 47 | K16: 47 | L16: 48 | M16: 49 | N16: 49 | O16: 50 | P16: 50 | Q16: 51 | R16: 52 | S16: =IF($F16="","",IF(IFERROR(VLOOKUP($F16,'维度字典'!$I$2:$J$50,2,0),"求和")="手工录入","",IF(IFERROR(VLOOKUP($F16,'维度字典'!$I$2:$J$50,2,0),"求和")="最新值",IFERROR(LOOKUP(9.99E+307,G16:R16),""),SUM(G16:R16)))) | T16: 管道良好：新客户导入顺利，机会转化符合预期 | U16: 7月追加在手订单目标：空调制冷钎焊 +5
A17: =IF($B17="","",ROW()-3) | B17: 张三 | C17: 空调制冷 | D17: 可拆 | E17: 华东 | F17: 目标客户机会 | G17: 27 | H17: 28 | I17: 28 | J17: 29 | K17: 29 | L17: 29 | M17: 30 | N17: 31 | O17: 31 | P17: 32 | Q17: 32 | R17: 33 | S17: =IF($F17="","",IF(IFERROR(VLOOKUP($F17,'维度字典'!$I$2:$J$50,2,0),"求和")="手工录入","",IF(IFERROR(VLOOKUP($F17,'维度字典'!$I$2:$J$50,2,0),"求和")="最新值",IFERROR(LOOKUP(9.99E+307,G17:R17),""),SUM(G17:R17))))
A18: =IF($B18="","",ROW()-3) | B18: 张三 | C18: 工业制冷 | D18: 钎焊 | E18: 华东 | F18: 销售目标额 | G18: 37 | H18: 32 | I18: 42 | J18: 47 | K18: 47 | L18: 52 | M18: 52 | N18: 47 | O18: 47 | P18: 47 | Q18: 42 | R18: 32 | S18: =IF($F18="","",IF(IFERROR(VLOOKUP($F18,'维度字典'!$I$2:$J$50,2,0),"求和")="手工录入","",IF(IFERROR(VLOOKUP($F18,'维度字典'!$I$2:$J$50,2,0),"求和")="最新值",IFERROR(LOOKUP(9.99E+307,G18:R18),""),SUM(G18:R18))))
A19: =IF($B19="","",ROW()-3) | B19: 张三 | C19: 工业制冷 | D19: 钎焊 | E19: 华东 | F19: 毛利目标 | G19: 5.9 | H19: 5 | I19: 6.7 | J19: 7.6 | K19: 7.6 | L19: 8.4 | M19: 8.4 | N19: 7.6 | O19: 7.6 | P19: 7.6 | Q19: 6.7 | R19: 5 | S19: =IF($F19="","",IF(IFERROR(VLOOKUP($F19,'维度字典'!$I$2:$J$50,2,0),"求和")="手工录入","",IF(IFERROR(VLOOKUP($F19,'维度字典'!$I$2:$J$50,2,0),"求和")="最新值",IFERROR(LOOKUP(9.99E+307,G19:R19),""),SUM(G19:R19))))
A20: =IF($B20="","",ROW()-3) | B20: 张三 | C20: 工业制冷 | D20: 钎焊 | E20: 华东 | F20: 毛利率目标 | G20: 0.1536 | H20: 0.1549 | I20: 0.1562 | J20: 0.1574 | K20: 0.1587 | L20: 0.16 | M20: 0.1613 | N20: 0.1626 | O20: 0.1638 | P20: 0.1651 | Q20: 0.1664 | R20: 0.1677 | S20: 0.16
A21: =IF($B21="","",ROW()-3) | B21: 张三 | C21: 工业制冷 | D21: 钎焊 | E21: 华东 | F21: 在手订单目标 | G21: 62 | H21: 63 | I21: 64 | J21: 65 | K21: 66 | L21: 66 | M21: 67 | N21: 68 | O21: 69 | P21: 70 | Q21: 71 | R21: 72 | S21: =IF($F21="","",IF(IFERROR(VLOOKUP($F21,'维度字典'!$I$2:$J$50,2,0),"求和")="手工录入","",IF(IFERROR(VLOOKUP($F21,'维度字典'!$I$2:$J$50,2,0),"求和")="最新值",IFERROR(LOOKUP(9.99E+307,G21:R21),""),SUM(G21:R21))))
A22: =IF($B22="","",ROW()-3) | B22: 张三 | C22: 工业制冷 | D22: 钎焊 | E22: 华东 | F22: 目标客户机会目标 | G22: 45 | H22: 46 | I22: 46 | J22: 47 | K22: 48 | L22: 49 | M22: 50 | N22: 51 | O22: 52 | P22: 52 | Q22: 53 | R22: 54 | S22: =IF($F22="","",IF(IFERROR(VLOOKUP($F22,'维度字典'!$I$2:$J$50,2,0),"求和")="手工录入","",IF(IFERROR(VLOOKUP($F22,'维度字典'!$I$2:$J$50,2,0),"求和")="最新值",IFERROR(LOOKUP(9.99E+307,G22:R22),""),SUM(G22:R22))))
A23: =IF($B23="","",ROW()-3) | B23: 张三 | C23: 工业制冷 | D23: 钎焊 | E23: 华东 | F23: 在手订单 | G23: 62 | H23: 63 | I23: 64 | J23: 65 | K23: 66 | L23: 66 | M23: 67 | N23: 68 | O23: 69 | P23: 70 | Q23: 71 | R23: 72 | S23: =IF($F23="","",IF(IFERROR(VLOOKUP($F23,'维度字典'!$I$2:$J$50,2,0),"求和")="手工录入","",IF(IFERROR(VLOOKUP($F23,'维度字典'!$I$2:$J$50,2,0),"求和")="最新值",IFERROR(LOOKUP(9.99E+307,G23:R23),""),SUM(G23:R23)))) | T23: 管道充足：大客户在手订单集中，交付节奏稳定
A24: =IF($B24="","",ROW()-3) | B24: 张三 | C24: 工业制冷 | D24: 钎焊 | E24: 华东 | F24: 目标客户机会 | G24: 38 | H24: 39 | I24: 39 | J24: 40 | K24: 41 | L24: 42 | M24: 43 | N24: 43 | O24: 44 | P24: 44 | Q24: 45 | R24: 46 | S24: =IF($F24="","",IF(IFERROR(VLOOKUP($F24,'维度字典'!$I$2:$J$50,2,0),"求和")="手工录入","",IF(IFERROR(VLOOKUP($F24,'维度字典'!$I$2:$J$50,2,0),"求和")="最新值",IFERROR(LOOKUP(9.99E+307,G24:R24),""),SUM(G24:R24))))
A25: =IF($B25="","",ROW()-3) | B25: 张三 | C25: 工业制冷 | D25: 可拆 | E25: 华东 | F25: 销售目标额 | G25: 37 | H25: 32 | I25: 42 | J25: 47 | K25: 47 | L25: 52 | M25: 52 | N25: 47 | O25: 47 | P25: 47 | Q25: 42 | R25: 32 | S25: =IF($F25="","",IF(IFERROR(VLOOKUP($F25,'维度字典'!$I$2:$J$50,2,0),"求和")="手工录入","",IF(IFERROR(VLOOKUP($F25,'维度字典'!$I$2:$J$50,2,0),"求和")="最新值",IFERROR(LOOKUP(9.99E+307,G25:R25),""),SUM(G25:R25))))
A26: =IF($B26="","",ROW()-3) | B26: 张三 | C26: 工业制冷 | D26: 可拆 | E26: 华东 | F26: 毛利目标 | G26: 5.9 | H26: 5 | I26: 6.7 | J26: 7.6 | K26: 7.6 | L26: 8.4 | M26: 8.4 | N26: 7.6 | O26: 7.6 | P26: 7.6 | Q26: 6.7 | R26: 5 | S26: =IF($F26="","",IF(IFERROR(VLOOKUP($F26,'维度字典'!$I$2:$J$50,2,0),"求和")="手工录入","",IF(IFERROR(VLOOKUP($F26,'维度字典'!$I$2:$J$50,2,0),"求和")="最新值",IFERROR(LOOKUP(9.99E+307,G26:R26),""),SUM(G26:R26))))
A27: =IF($B27="","",ROW()-3) | B27: 张三 | C27: 工业制冷 | D27: 可拆 | E27: 华东 | F27: 毛利率目标 | G27: 0.1536 | H27: 0.1549 | I27: 0.1562 | J27: 0.1574 | K27: 0.1587 | L27: 0.16 | M27: 0.1613 | N27: 0.1626 | O27: 0.1638 | P27: 0.1651 | Q27: 0.1664 | R27: 0.1677 | S27: 0.16
A28: =IF($B28="","",ROW()-3) | B28: 张三 | C28: 工业制冷 | D28: 可拆 | E28: 华东 | F28: 在手订单目标 | G28: 62 | H28: 63 | I28: 64 | J28: 65 | K28: 66 | L28: 66 | M28: 67 | N28: 68 | O28: 69 | P28: 70 | Q28: 71 | R28: 72 | S28: =IF($F28="","",IF(IFERROR(VLOOKUP($F28,'维度字典'!$I$2:$J$50,2,0),"求和")="手工录入","",IF(IFERROR(VLOOKUP($F28,'维度字典'!$I$2:$J$50,2,0),"求和")="最新值",IFERROR(LOOKUP(9.99E+307,G28:R28),""),SUM(G28:R28))))
A29: =IF($B29="","",ROW()-3) | B29: 张三 | C29: 工业制冷 | D29: 可拆 | E29: 华东 | F29: 目标客户机会目标 | G29: 45 | H29: 46 | I29: 46 | J29: 47 | K29: 48 | L29: 49 | M29: 50 | N29: 51 | O29: 52 | P29: 52 | Q29: 53 | R29: 54 | S29: =IF($F29="","",IF(IFERROR(VLOOKUP($F29,'维度字典'!$I$2:$J$50,2,0),"求和")="手工录入","",IF(IFERROR(VLOOKUP($F29,'维度字典'!$I$2:$J$50,2,0),"求和")="最新值",IFERROR(LOOKUP(9.99E+307,G29:R29),""),SUM(G29:R29))))
A30: =IF($B30="","",ROW()-3) | B30: 张三 | C30: 工业制冷 | D30: 可拆 | E30: 华东 | F30: 在手订单 | G30: 62 | H30: 63 | I30: 64 | J30: 65 | K30: 66 | L30: 66 | M30: 67 | N30: 68 | O30: 69 | P30: 70 | Q30: 71 | R30: 72 | S30: =IF($F30="","",IF(IFERROR(VLOOKUP($F30,'维度字典'!$I$2:$J$50,2,0),"求和")="手工录入","",IF(IFERROR(VLOOKUP($F30,'维度字典'!$I$2:$J$50,2,0),"求和")="最新值",IFERROR(LOOKUP(9.99E+307,G30:R30),""),SUM(G30:R30)))) | T30: 管道充足：大客户在手订单集中，交付节奏稳定
A31: =IF($B31="","",ROW()-3) | B31: 张三 | C31: 工业制冷 | D31: 可拆 | E31: 华东 | F31: 目标客户机会 | G31: 38 | H31: 39 | I31: 39 | J31: 40 | K31: 41 | L31: 42 | M31: 43 | N31: 43 | O31: 44 | P31: 44 | Q31: 45 | R31: 46 | S31: =IF($F31="","",IF(IFERROR(VLOOKUP($F31,'维度字典'!$I$2:$J$50,2,0),"求和")="手工录入","",IF(IFERROR(VLOOKUP($F31,'维度字典'!$I$2:$J$50,2,0),"求和")="最新值",IFERROR(LOOKUP(9.99E+307,G31:R31),""),SUM(G31:R31))))
A32: =IF($B32="","",ROW()-3) | B32: 张三 | C32: 船舶行业 | D32: 钎焊 | E32: 华东 | F32: 销售目标额 | G32: 9 | H32: 8 | I32: 11 | J32: 12 | K32: 12 | L32: 13 | M32: 13 | N32: 12 | O32: 12 | P32: 12 | Q32: 11 | R32: 8 | S32: =IF($F32="","",IF(IFERROR(VLOOKUP($F32,'维度字典'!$I$2:$J$50,2,0),"求和")="手工录入","",IF(IFERROR(VLOOKUP($F32,'维度字典'!$I$2:$J$50,2,0),"求和")="最新值",IFERROR(LOOKUP(9.99E+307,G32:R32),""),SUM(G32:R32))))
A33: =IF($B33="","",ROW()-3) | B33: 张三 | C33: 船舶行业 | D33: 钎焊 | E33: 华东 | F33: 毛利目标 | G33: 1.9 | H33: 1.6 | I33: 2.1 | J33: 2.4 | K33: 2.4 | L33: 2.7 | M33: 2.7 | N33: 2.4 | O33: 2.4 | P33: 2.4 | Q33: 2.1 | R33: 1.6 | S33: =IF($F33="","",IF(IFERROR(VLOOKUP($F33,'维度字典'!$I$2:$J$50,2,0),"求和")="手工录入","",IF(IFERROR(VLOOKUP($F33,'维度字典'!$I$2:$J$50,2,0),"求和")="最新值",IFERROR(LOOKUP(9.99E+307,G33:R33),""),SUM(G33:R33))))
A34: =IF($B34="","",ROW()-3) | B34: 张三 | C34: 船舶行业 | D34: 钎焊 | E34: 华东 | F34: 毛利率目标 | G34: 0.192 | H34: 0.1936 | I34: 0.1952 | J34: 0.1968 | K34: 0.1984 | L34: 0.2 | M34: 0.2016 | N34: 0.2032 | O34: 0.2048 | P34: 0.2064 | Q34: 0.208 | R34: 0.2096 | S34: 0.2
A35: =IF($B35="","",ROW()-3) | B35: 张三 | C35: 船舶行业 | D35: 钎焊 | E35: 华东 | F35: 在手订单目标 | G35: 16 | H35: 16 | I35: 16 | J35: 17 | K35: 17 | L35: 17 | M35: 17 | N35: 17 | O35: 18 | P35: 18 | Q35: 18 | R35: 18 | S35: =IF($F35="","",IF(IFERROR(VLOOKUP($F35,'维度字典'!$I$2:$J$50,2,0),"求和")="手工录入","",IF(IFERROR(VLOOKUP($F35,'维度字典'!$I$2:$J$50,2,0),"求和")="最新值",IFERROR(LOOKUP(9.99E+307,G35:R35),""),SUM(G35:R35))))
A36: =IF($B36="","",ROW()-3) | B36: 张三 | C36: 船舶行业 | D36: 钎焊 | E36: 华东 | F36: 目标客户机会目标 | G36: 11 | H36: 12 | I36: 12 | J36: 12 | K36: 12 | L36: 13 | M36: 13 | N36: 13 | O36: 13 | P36: 13 | Q36: 14 | R36: 14 | S36: =IF($F36="","",IF(IFERROR(VLOOKUP($F36,'维度字典'!$I$2:$J$50,2,0),"求和")="手工录入","",IF(IFERROR(VLOOKUP($F36,'维度字典'!$I$2:$J$50,2,0),"求和")="最新值",IFERROR(LOOKUP(9.99E+307,G36:R36),""),SUM(G36:R36))))
A37: =IF($B37="","",ROW()-3) | B37: 张三 | C37: 船舶行业 | D37: 钎焊 | E37: 华东 | F37: 在手订单 | G37: 16 | H37: 16 | I37: 16 | J37: 17 | K37: 17 | L37: 17 | M37: 17 | N37: 17 | O37: 18 | P37: 18 | Q37: 18 | R37: 18 | S37: =IF($F37="","",IF(IFERROR(VLOOKUP($F37,'维度字典'!$I$2:$J$50,2,0),"求和")="手工录入","",IF(IFERROR(VLOOKUP($F37,'维度字典'!$I$2:$J$50,2,0),"求和")="最新值",IFERROR(LOOKUP(9.99E+307,G37:R37),""),SUM(G37:R37)))) | T37: 管道良好：新客户导入顺利，机会转化符合预期
A38: =IF($B38="","",ROW()-3) | B38: 张三 | C38: 船舶行业 | D38: 钎焊 | E38: 华东 | F38: 目标客户机会 | G38: 9 | H38: 10 | I38: 10 | J38: 10 | K38: 10 | L38: 11 | M38: 11 | N38: 11 | O38: 11 | P38: 11 | Q38: 12 | R38: 12 | S38: =IF($F38="","",IF(IFERROR(VLOOKUP($F38,'维度字典'!$I$2:$J$50,2,0),"求和")="手工录入","",IF(IFERROR(VLOOKUP($F38,'维度字典'!$I$2:$J$50,2,0),"求和")="最新值",IFERROR(LOOKUP(9.99E+307,G38:R38),""),SUM(G38:R38))))
A39: =IF($B39="","",ROW()-3) | B39: 张三 | C39: 船舶行业 | D39: 可拆 | E39: 华东 | F39: 销售目标额 | G39: 14 | H39: 12 | I39: 16 | J39: 18 | K39: 18 | L39: 20 | M39: 20 | N39: 18 | O39: 18 | P39: 18 | Q39: 16 | R39: 12 | S39: =IF($F39="","",IF(IFERROR(VLOOKUP($F39,'维度字典'!$I$2:$J$50,2,0),"求和")="手工录入","",IF(IFERROR(VLOOKUP($F39,'维度字典'!$I$2:$J$50,2,0),"求和")="最新值",IFERROR(LOOKUP(9.99E+307,G39:R39),""),SUM(G39:R39))))
A40: =IF($B40="","",ROW()-3) | B40: 张三 | C40: 船舶行业 | D40: 可拆 | E40: 华东 | F40: 毛利目标 | G40: 2.8 | H40: 2.4 | I40: 3.2 | J40: 3.6 | K40: 3.6 | L40: 4 | M40: 4 | N40: 3.6 | O40: 3.6 | P40: 3.6 | Q40: 3.2 | R40: 2.4 | S40: =IF($F40="","",IF(IFERROR(VLOOKUP($F40,'维度字典'!$I$2:$J$50,2,0),"求和")="手工录入","",IF(IFERROR(VLOOKUP($F40,'维度字典'!$I$2:$J$50,2,0),"求和")="最新值",IFERROR(LOOKUP(9.99E+307,G40:R40),""),SUM(G40:R40))))
A41: =IF($B41="","",ROW()-3) | B41: 张三 | C41: 船舶行业 | D41: 可拆 | E41: 华东 | F41: 毛利率目标 | G41: 0.192 | H41: 0.1936 | I41: 0.1952 | J41: 0.1968 | K41: 0.1984 | L41: 0.2 | M41: 0.2016 | N41: 0.2032 | O41: 0.2048 | P41: 0.2064 | Q41: 0.208 | R41: 0.2096 | S41: 0.2
A42: =IF($B42="","",ROW()-3) | B42: 张三 | C42: 船舶行业 | D42: 可拆 | E42: 华东 | F42: 在手订单目标 | G42: 24 | H42: 24 | I42: 25 | J42: 25 | K42: 25 | L42: 26 | M42: 26 | N42: 26 | O42: 27 | P42: 27 | Q42: 27 | R42: 28 | S42: =IF($F42="","",IF(IFERROR(VLOOKUP($F42,'维度字典'!$I$2:$J$50,2,0),"求和")="手工录入","",IF(IFERROR(VLOOKUP($F42,'维度字典'!$I$2:$J$50,2,0),"求和")="最新值",IFERROR(LOOKUP(9.99E+307,G42:R42),""),SUM(G42:R42))))
A43: =IF($B43="","",ROW()-3) | B43: 张三 | C43: 船舶行业 | D43: 可拆 | E43: 华东 | F43: 目标客户机会目标 | G43: 17 | H43: 18 | I43: 18 | J43: 18 | K43: 19 | L43: 19 | M43: 19 | N43: 20 | O43: 20 | P43: 20 | Q43: 21 | R43: 21 | S43: =IF($F43="","",IF(IFERROR(VLOOKUP($F43,'维度字典'!$I$2:$J$50,2,0),"求和")="手工录入","",IF(IFERROR(VLOOKUP($F43,'维度字典'!$I$2:$J$50,2,0),"求和")="最新值",IFERROR(LOOKUP(9.99E+307,G43:R43),""),SUM(G43:R43))))
A44: =IF($B44="","",ROW()-3) | B44: 张三 | C44: 船舶行业 | D44: 可拆 | E44: 华东 | F44: 在手订单 | G44: 23 | H44: 23 | I44: 24 | J44: 24 | K44: 24 | L44: 25 | M44: 25 | N44: 25 | O44: 26 | P44: 26 | Q44: 26 | R44: 27 | S44: =IF($F44="","",IF(IFERROR(VLOOKUP($F44,'维度字典'!$I$2:$J$50,2,0),"求和")="手工录入","",IF(IFERROR(VLOOKUP($F44,'维度字典'!$I$2:$J$50,2,0),"求和")="最新值",IFERROR(LOOKUP(9.99E+307,G44:R44),""),SUM(G44:R44)))) | T44: 管道良好：新客户导入顺利，机会转化符合预期
A45: =IF($B45="","",ROW()-3) | B45: 张三 | C45: 船舶行业 | D45: 可拆 | E45: 华东 | F45: 目标客户机会 | G45: 14 | H45: 15 | I45: 15 | J45: 15 | K45: 16 | L45: 16 | M45: 16 | N45: 16 | O45: 16 | P45: 16 | Q45: 17 | R45: 17 | S45: =IF($F45="","",IF(IFERROR(VLOOKUP($F45,'维度字典'!$I$2:$J$50,2,0),"求和")="手工录入","",IF(IFERROR(VLOOKUP($F45,'维度字典'!$I$2:$J$50,2,0),"求和")="最新值",IFERROR(LOOKUP(9.99E+307,G45:R45),""),SUM(G45:R45))))
A46: =IF($B46="","",ROW()-3) | B46: 张三 | C46: 储能行业 | D46: 钎焊 | E46: 华东 | F46: 销售目标额 | G46: 5 | H46: 5 | I46: 6 | J46: 7 | K46: 7 | L46: 8 | M46: 8 | N46: 7 | O46: 7 | P46: 7 | Q46: 6 | R46: 5 | S46: =IF($F46="","",IF(IFERROR(VLOOKUP($F46,'维度字典'!$I$2:$J$50,2,0),"求和")="手工录入","",IF(IFERROR(VLOOKUP($F46,'维度字典'!$I$2:$J$50,2,0),"求和")="最新值",IFERROR(LOOKUP(9.99E+307,G46:R46),""),SUM(G46:R46))))
A47: =IF($B47="","",ROW()-3) | B47: 张三 | C47: 储能行业 | D47: 钎焊 | E47: 华东 | F47: 毛利目标 | G47: 1.1 | H47: 0.9 | I47: 1.2 | J47: 1.4 | K47: 1.4 | L47: 1.5 | M47: 1.5 | N47: 1.4 | O47: 1.4 | P47: 1.4 | Q47: 1.2 | R47: 0.9 | S47: =IF($F47="","",IF(IFERROR(VLOOKUP($F47,'维度字典'!$I$2:$J$50,2,0),"求和")="手工录入","",IF(IFERROR(VLOOKUP($F47,'维度字典'!$I$2:$J$50,2,0),"求和")="最新值",IFERROR(LOOKUP(9.99E+307,G47:R47),""),SUM(G47:R47))))
A48: =IF($B48="","",ROW()-3) | B48: 张三 | C48: 储能行业 | D48: 钎焊 | E48: 华东 | F48: 毛利率目标 | G48: 0.192 | H48: 0.1936 | I48: 0.1952 | J48: 0.1968 | K48: 0.1984 | L48: 0.2 | M48: 0.2016 | N48: 0.2032 | O48: 0.2048 | P48: 0.2064 | Q48: 0.208 | R48: 0.2096 | S48: 0.2
A49: =IF($B49="","",ROW()-3) | B49: 张三 | C49: 储能行业 | D49: 钎焊 | E49: 华东 | F49: 在手订单目标 | G49: 9 | H49: 9 | I49: 9 | J49: 9 | K49: 10 | L49: 10 | M49: 10 | N49: 10 | O49: 10 | P49: 10 | Q49: 10 | R49: 10 | S49: =IF($F49="","",IF(IFERROR(VLOOKUP($F49,'维度字典'!$I$2:$J$50,2,0),"求和")="手工录入","",IF(IFERROR(VLOOKUP($F49,'维度字典'!$I$2:$J$50,2,0),"求和")="最新值",IFERROR(LOOKUP(9.99E+307,G49:R49),""),SUM(G49:R49))))
A50: =IF($B50="","",ROW()-3) | B50: 张三 | C50: 储能行业 | D50: 钎焊 | E50: 华东 | F50: 目标客户机会目标 | G50: 6 | H50: 7 | I50: 7 | J50: 7 | K50: 7 | L50: 7 | M50: 7 | N50: 7 | O50: 7 | P50: 8 | Q50: 8 | R50: 8 | S50: =IF($F50="","",IF(IFERROR(VLOOKUP($F50,'维度字典'!$I$2:$J$50,2,0),"求和")="手工录入","",IF(IFERROR(VLOOKUP($F50,'维度字典'!$I$2:$J$50,2,0),"求和")="最新值",IFERROR(LOOKUP(9.99E+307,G50:R50),""),SUM(G50:R50))))
A51: =IF($B51="","",ROW()-3) | B51: 张三 | C51: 储能行业 | D51: 钎焊 | E51: 华东 | F51: 在手订单 | G51: 9 | H51: 9 | I51: 9 | J51: 9 | K51: 10 | L51: 10 | M51: 10 | N51: 10 | O51: 10 | P51: 10 | Q51: 10 | R51: 10 | S51: =IF($F51="","",IF(IFERROR(VLOOKUP($F51,'维度字典'!$I$2:$J$50,2,0),"求和")="手工录入","",IF(IFERROR(VLOOKUP($F51,'维度字典'!$I$2:$J$50,2,0),"求和")="最新值",IFERROR(LOOKUP(9.99E+307,G51:R51),""),SUM(G51:R51)))) | T51: 管道良好：新客户导入顺利，机会转化符合预期
A52: =IF($B52="","",ROW()-3) | B52: 张三 | C52: 储能行业 | D52: 钎焊 | E52: 华东 | F52: 目标客户机会 | G52: 5 | H52: 6 | I52: 6 | J52: 6 | K52: 6 | L52: 6 | M52: 6 | N52: 6 | O52: 6 | P52: 7 | Q52: 7 | R52: 7 | S52: =IF($F52="","",IF(IFERROR(VLOOKUP($F52,'维度字典'!$I$2:$J$50,2,0),"求和")="手工录入","",IF(IFERROR(VLOOKUP($F52,'维度字典'!$I$2:$J$50,2,0),"求和")="最新值",IFERROR(LOOKUP(9.99E+307,G52:R52),""),SUM(G52:R52))))
A53: =IF($B53="","",ROW()-3) | B53: 张三 | C53: 储能行业 | D53: 可拆 | E53: 华东 | F53: 销售目标额 | G53: 12 | H53: 11 | I53: 14 | J53: 16 | K53: 16 | L53: 18 | M53: 18 | N53: 16 | O53: 16 | P53: 16 | Q53: 14 | R53: 11 | S53: =IF($F53="","",IF(IFERROR(VLOOKUP($F53,'维度字典'!$I$2:$J$50,2,0),"求和")="手工录入","",IF(IFERROR(VLOOKUP($F53,'维度字典'!$I$2:$J$50,2,0),"求和")="最新值",IFERROR(LOOKUP(9.99E+307,G53:R53),""),SUM(G53:R53))))
A54: =IF($B54="","",ROW()-3) | B54: 张三 | C54: 储能行业 | D54: 可拆 | E54: 华东 | F54: 毛利目标 | G54: 2.5 | H54: 2.1 | I54: 2.8 | J54: 3.2 | K54: 3.2 | L54: 3.5 | M54: 3.5 | N54: 3.2 | O54: 3.2 | P54: 3.2 | Q54: 2.8 | R54: 2.1 | S54: =IF($F54="","",IF(IFERROR(VLOOKUP($F54,'维度字典'!$I$2:$J$50,2,0),"求和")="手工录入","",IF(IFERROR(VLOOKUP($F54,'维度字典'!$I$2:$J$50,2,0),"求和")="最新值",IFERROR(LOOKUP(9.99E+307,G54:R54),""),SUM(G54:R54))))
A55: =IF($B55="","",ROW()-3) | B55: 张三 | C55: 储能行业 | D55: 可拆 | E55: 华东 | F55: 毛利率目标 | G55: 0.192 | H55: 0.1936 | I55: 0.1952 | J55: 0.1968 | K55: 0.1984 | L55: 0.2 | M55: 0.2016 | N55: 0.2032 | O55: 0.2048 | P55: 0.2064 | Q55: 0.208 | R55: 0.2096 | S55: 0.2
A56: =IF($B56="","",ROW()-3) | B56: 张三 | C56: 储能行业 | D56: 可拆 | E56: 华东 | F56: 在手订单目标 | G56: 21 | H56: 21 | I56: 21 | J56: 22 | K56: 22 | L56: 22 | M56: 23 | N56: 23 | O56: 23 | P56: 23 | Q56: 24 | R56: 24 | S56: =IF($F56="","",IF(IFERROR(VLOOKUP($F56,'维度字典'!$I$2:$J$50,2,0),"求和")="手工录入","",IF(IFERROR(VLOOKUP($F56,'维度字典'!$I$2:$J$50,2,0),"求和")="最新值",IFERROR(LOOKUP(9.99E+307,G56:R56),""),SUM(G56:R56))))
A57: =IF($B57="","",ROW()-3) | B57: 张三 | C57: 储能行业 | D57: 可拆 | E57: 华东 | F57: 目标客户机会目标 | G57: 15 | H57: 15 | I57: 16 | J57: 16 | K57: 16 | L57: 16 | M57: 17 | N57: 17 | O57: 17 | P57: 18 | Q57: 18 | R57: 18 | S57: =IF($F57="","",IF(IFERROR(VLOOKUP($F57,'维度字典'!$I$2:$J$50,2,0),"求和")="手工录入","",IF(IFERROR(VLOOKUP($F57,'维度字典'!$I$2:$J$50,2,0),"求和")="最新值",IFERROR(LOOKUP(9.99E+307,G57:R57),""),SUM(G57:R57))))
A58: =IF($B58="","",ROW()-3) | B58: 张三 | C58: 储能行业 | D58: 可拆 | E58: 华东 | F58: 在手订单 | G58: 20 | H58: 20 | I58: 20 | J58: 21 | K58: 21 | L58: 21 | M58: 22 | N58: 22 | O58: 22 | P58: 22 | Q58: 23 | R58: 23 | S58: =IF($F58="","",IF(IFERROR(VLOOKUP($F58,'维度字典'!$I$2:$J$50,2,0),"求和")="手工录入","",IF(IFERROR(VLOOKUP($F58,'维度字典'!$I$2:$J$50,2,0),"求和")="最新值",IFERROR(LOOKUP(9.99E+307,G58:R58),""),SUM(G58:R58)))) | T58: 管道偏紧：个别客户观望，需加快报价与签约节奏
A59: =IF($B59="","",ROW()-3) | B59: 张三 | C59: 储能行业 | D59: 可拆 | E59: 华东 | F59: 目标客户机会 | G59: 12 | H59: 12 | I59: 13 | J59: 13 | K59: 13 | L59: 13 | M59: 14 | N59: 14 | O59: 14 | P59: 15 | Q59: 15 | R59: 15 | S59: =IF($F59="","",IF(IFERROR(VLOOKUP($F59,'维度字典'!$I$2:$J$50,2,0),"求和")="手工录入","",IF(IFERROR(VLOOKUP($F59,'维度字典'!$I$2:$J$50,2,0),"求和")="最新值",IFERROR(LOOKUP(9.99E+307,G59:R59),""),SUM(G59:R59))))
A60: =IF($B60="","",ROW()-3) | B60: 张三 | C60: 数据中心 | D60: 钎焊 | E60: 华东 | F60: 销售目标额 | G60: 26 | H60: 23 | I60: 30 | J60: 34 | K60: 34 | L60: 38 | M60: 38 | N60: 34 | O60: 34 | P60: 34 | Q60: 30 | R60: 23 | S60: =IF($F60="","",IF(IFERROR(VLOOKUP($F60,'维度字典'!$I$2:$J$50,2,0),"求和")="手工录入","",IF(IFERROR(VLOOKUP($F60,'维度字典'!$I$2:$J$50,2,0),"求和")="最新值",IFERROR(LOOKUP(9.99E+307,G60:R60),""),SUM(G60:R60))))
A61: =IF($B61="","",ROW()-3) | B61: 张三 | C61: 数据中心 | D61: 钎焊 | E61: 华东 | F61: 毛利目标 | G61: 5.8 | H61: 5 | I61: 6.7 | J61: 7.5 | K61: 7.5 | L61: 8.3 | M61: 8.3 | N61: 7.5 | O61: 7.5 | P61: 7.5 | Q61: 6.7 | R61: 5 | S61: =IF($F61="","",IF(IFERROR(VLOOKUP($F61,'维度字典'!$I$2:$J$50,2,0),"求和")="手工录入","",IF(IFERROR(VLOOKUP($F61,'维度字典'!$I$2:$J$50,2,0),"求和")="最新值",IFERROR(LOOKUP(9.99E+307,G61:R61),""),SUM(G61:R61))))
A62: =IF($B62="","",ROW()-3) | B62: 张三 | C62: 数据中心 | D62: 钎焊 | E62: 华东 | F62: 毛利率目标 | G62: 0.2112 | H62: 0.213 | I62: 0.2147 | J62: 0.2165 | K62: 0.2182 | L62: 0.22 | M62: 0.2218 | N62: 0.2235 | O62: 0.2253 | P62: 0.227 | Q62: 0.2288 | R62: 0.2306 | S62: 0.22
A63: =IF($B63="","",ROW()-3) | B63: 张三 | C63: 数据中心 | D63: 钎焊 | E63: 华东 | F63: 在手订单目标 | G63: 45 | H63: 45 | I63: 46 | J63: 47 | K63: 47 | L63: 48 | M63: 49 | N63: 49 | O63: 50 | P63: 50 | Q63: 51 | R63: 52 | S63: =IF($F63="","",IF(IFERROR(VLOOKUP($F63,'维度字典'!$I$2:$J$50,2,0),"求和")="手工录入","",IF(IFERROR(VLOOKUP($F63,'维度字典'!$I$2:$J$50,2,0),"求和")="最新值",IFERROR(LOOKUP(9.99E+307,G63:R63),""),SUM(G63:R63))))
A64: =IF($B64="","",ROW()-3) | B64: 张三 | C64: 数据中心 | D64: 钎焊 | E64: 华东 | F64: 目标客户机会目标 | G64: 32 | H64: 33 | I64: 33 | J64: 34 | K64: 35 | L64: 35 | M64: 36 | N64: 37 | O64: 37 | P64: 38 | Q64: 38 | R64: 39 | S64: =IF($F64="","",IF(IFERROR(VLOOKUP($F64,'维度字典'!$I$2:$J$50,2,0),"求和")="手工录入","",IF(IFERROR(VLOOKUP($F64,'维度字典'!$I$2:$J$50,2,0),"求和")="最新值",IFERROR(LOOKUP(9.99E+307,G64:R64),""),SUM(G64:R64))))
A65: =IF($B65="","",ROW()-3) | B65: 张三 | C65: 数据中心 | D65: 钎焊 | E65: 华东 | F65: 在手订单 | G65: 45 | H65: 45 | I65: 46 | J65: 47 | K65: 47 | L65: 48 | M65: 49 | N65: 49 | O65: 50 | P65: 50 | Q65: 51 | R65: 52 | S65: =IF($F65="","",IF(IFERROR(VLOOKUP($F65,'维度字典'!$I$2:$J$50,2,0),"求和")="手工录入","",IF(IFERROR(VLOOKUP($F65,'维度字典'!$I$2:$J$50,2,0),"求和")="最新值",IFERROR(LOOKUP(9.99E+307,G65:R65),""),SUM(G65:R65)))) | T65: 管道充足：大客户在手订单集中，交付节奏稳定
A66: =IF($B66="","",ROW()-3) | B66: 张三 | C66: 数据中心 | D66: 钎焊 | E66: 华东 | F66: 目标客户机会 | G66: 27 | H66: 28 | I66: 28 | J66: 29 | K66: 30 | L66: 30 | M66: 31 | N66: 31 | O66: 31 | P66: 32 | Q66: 32 | R66: 33 | S66: =IF($F66="","",IF(IFERROR(VLOOKUP($F66,'维度字典'!$I$2:$J$50,2,0),"求和")="手工录入","",IF(IFERROR(VLOOKUP($F66,'维度字典'!$I$2:$J$50,2,0),"求和")="最新值",IFERROR(LOOKUP(9.99E+307,G66:R66),""),SUM(G66:R66))))
A67: =IF($B67="","",ROW()-3) | B67: 张三 | C67: 数据中心 | D67: 可拆 | E67: 华东 | F67: 销售目标额 | G67: 18 | H67: 15 | I67: 20 | J67: 23 | K67: 23 | L67: 25 | M67: 25 | N67: 23 | O67: 23 | P67: 23 | Q67: 20 | R67: 15 | S67: =IF($F67="","",IF(IFERROR(VLOOKUP($F67,'维度字典'!$I$2:$J$50,2,0),"求和")="手工录入","",IF(IFERROR(VLOOKUP($F67,'维度字典'!$I$2:$J$50,2,0),"求和")="最新值",IFERROR(LOOKUP(9.99E+307,G67:R67),""),SUM(G67:R67))))
A68: =IF($B68="","",ROW()-3) | B68: 张三 | C68: 数据中心 | D68: 可拆 | E68: 华东 | F68: 毛利目标 | G68: 3.9 | H68: 3.3 | I68: 4.4 | J68: 5 | K68: 5 | L68: 5.5 | M68: 5.5 | N68: 5 | O68: 5 | P68: 5 | Q68: 4.4 | R68: 3.3 | S68: =IF($F68="","",IF(IFERROR(VLOOKUP($F68,'维度字典'!$I$2:$J$50,2,0),"求和")="手工录入","",IF(IFERROR(VLOOKUP($F68,'维度字典'!$I$2:$J$50,2,0),"求和")="最新值",IFERROR(LOOKUP(9.99E+307,G68:R68),""),SUM(G68:R68))))
A69: =IF($B69="","",ROW()-3) | B69: 张三 | C69: 数据中心 | D69: 可拆 | E69: 华东 | F69: 毛利率目标 | G69: 0.2112 | H69: 0.213 | I69: 0.2147 | J69: 0.2165 | K69: 0.2182 | L69: 0.22 | M69: 0.2218 | N69: 0.2235 | O69: 0.2253 | P69: 0.227 | Q69: 0.2288 | R69: 0.2306 | S69: 0.22
A70: =IF($B70="","",ROW()-3) | B70: 张三 | C70: 数据中心 | D70: 可拆 | E70: 华东 | F70: 在手订单目标 | G70: 30 | H70: 30 | I70: 31 | J70: 31 | K70: 32 | L70: 32 | M70: 32 | N70: 33 | O70: 33 | P70: 34 | Q70: 34 | R70: 34 | S70: =IF($F70="","",IF(IFERROR(VLOOKUP($F70,'维度字典'!$I$2:$J$50,2,0),"求和")="手工录入","",IF(IFERROR(VLOOKUP($F70,'维度字典'!$I$2:$J$50,2,0),"求和")="最新值",IFERROR(LOOKUP(9.99E+307,G70:R70),""),SUM(G70:R70))))
A71: =IF($B71="","",ROW()-3) | B71: 张三 | C71: 数据中心 | D71: 可拆 | E71: 华东 | F71: 目标客户机会目标 | G71: 21 | H71: 22 | I71: 22 | J71: 23 | K71: 23 | L71: 24 | M71: 24 | N71: 24 | O71: 25 | P71: 25 | Q71: 26 | R71: 26 | S71: =IF($F71="","",IF(IFERROR(VLOOKUP($F71,'维度字典'!$I$2:$J$50,2,0),"求和")="手工录入","",IF(IFERROR(VLOOKUP($F71,'维度字典'!$I$2:$J$50,2,0),"求和")="最新值",IFERROR(LOOKUP(9.99E+307,G71:R71),""),SUM(G71:R71))))
A72: =IF($B72="","",ROW()-3) | B72: 张三 | C72: 数据中心 | D72: 可拆 | E72: 华东 | F72: 在手订单 | G72: 30 | H72: 30 | I72: 31 | J72: 31 | K72: 32 | L72: 32 | M72: 32 | N72: 33 | O72: 33 | P72: 34 | Q72: 34 | R72: 34 | S72: =IF($F72="","",IF(IFERROR(VLOOKUP($F72,'维度字典'!$I$2:$J$50,2,0),"求和")="手工录入","",IF(IFERROR(VLOOKUP($F72,'维度字典'!$I$2:$J$50,2,0),"求和")="最新值",IFERROR(LOOKUP(9.99E+307,G72:R72),""),SUM(G72:R72)))) | T72: 管道充足：大客户在手订单集中，交付节奏稳定
A73: =IF($B73="","",ROW()-3) | B73: 张三 | C73: 数据中心 | D73: 可拆 | E73: 华东 | F73: 目标客户机会 | G73: 18 | H73: 19 | I73: 19 | J73: 20 | K73: 20 | L73: 20 | M73: 20 | N73: 20 | O73: 21 | P73: 21 | Q73: 22 | R73: 22 | S73: =IF($F73="","",IF(IFERROR(VLOOKUP($F73,'维度字典'!$I$2:$J$50,2,0),"求和")="手工录入","",IF(IFERROR(VLOOKUP($F73,'维度字典'!$I$2:$J$50,2,0),"求和")="最新值",IFERROR(LOOKUP(9.99E+307,G73:R73),""),SUM(G73:R73))))
A74: =IF($B74="","",ROW()-3) | B74: 李四 | C74: 空调制冷 | D74: 钎焊 | E74: 华南 | F74: 销售目标额 | G74: 51 | H74: 44 | I74: 59 | J74: 66 | K74: 66 | L74: 74 | M74: 74 | N74: 66 | O74: 66 | P74: 66 | Q74: 59 | R74: 44 | S74: =IF($F74="","",IF(IFERROR(VLOOKUP($F74,'维度字典'!$I$2:$J$50,2,0),"求和")="手工录入","",IF(IFERROR(VLOOKUP($F74,'维度字典'!$I$2:$J$50,2,0),"求和")="最新值",IFERROR(LOOKUP(9.99E+307,G74:R74),""),SUM(G74:R74))))
A75: =IF($B75="","",ROW()-3) | B75: 李四 | C75: 空调制冷 | D75: 钎焊 | E75: 华南 | F75: 毛利目标 | G75: 7.7 | H75: 6.6 | I75: 8.8 | J75: 9.9 | K75: 9.9 | L75: 11 | M75: 11 | N75: 9.9 | O75: 9.9 | P75: 9.9 | Q75: 8.8 | R75: 6.6 | S75: =IF($F75="","",IF(IFERROR(VLOOKUP($F75,'维度字典'!$I$2:$J$50,2,0),"求和")="手工录入","",IF(IFERROR(VLOOKUP($F75,'维度字典'!$I$2:$J$50,2,0),"求和")="最新值",IFERROR(LOOKUP(9.99E+307,G75:R75),""),SUM(G75:R75))))
A76: =IF($B76="","",ROW()-3) | B76: 李四 | C76: 空调制冷 | D76: 钎焊 | E76: 华南 | F76: 毛利率目标 | G76: 0.144 | H76: 0.1452 | I76: 0.1464 | J76: 0.1476 | K76: 0.1488 | L76: 0.15 | M76: 0.1512 | N76: 0.1524 | O76: 0.1536 | P76: 0.1548 | Q76: 0.156 | R76: 0.1572 | S76: 0.15
A77: =IF($B77="","",ROW()-3) | B77: 李四 | C77: 空调制冷 | D77: 钎焊 | E77: 华南 | F77: 在手订单目标 | G77: 87 | H77: 88 | I77: 89 | J77: 91 | K77: 92 | L77: 93 | M77: 94 | N77: 96 | O77: 97 | P77: 98 | Q77: 99 | R77: 100 | S77: =IF($F77="","",IF(IFERROR(VLOOKUP($F77,'维度字典'!$I$2:$J$50,2,0),"求和")="手工录入","",IF(IFERROR(VLOOKUP($F77,'维度字典'!$I$2:$J$50,2,0),"求和")="最新值",IFERROR(LOOKUP(9.99E+307,G77:R77),""),SUM(G77:R77))))
A78: =IF($B78="","",ROW()-3) | B78: 李四 | C78: 空调制冷 | D78: 钎焊 | E78: 华南 | F78: 目标客户机会目标 | G78: 62 | H78: 64 | I78: 65 | J78: 66 | K78: 67 | L78: 69 | M78: 70 | N78: 71 | O78: 72 | P78: 74 | Q78: 75 | R78: 76 | S78: =IF($F78="","",IF(IFERROR(VLOOKUP($F78,'维度字典'!$I$2:$J$50,2,0),"求和")="手工录入","",IF(IFERROR(VLOOKUP($F78,'维度字典'!$I$2:$J$50,2,0),"求和")="最新值",IFERROR(LOOKUP(9.99E+307,G78:R78),""),SUM(G78:R78))))
A79: =IF($B79="","",ROW()-3) | B79: 李四 | C79: 空调制冷 | D79: 钎焊 | E79: 华南 | F79: 在手订单 | G79: 85 | H79: 86 | I79: 87 | J79: 89 | K79: 90 | L79: 91 | M79: 92 | N79: 94 | O79: 95 | P79: 96 | Q79: 97 | R79: 98 | S79: =IF($F79="","",IF(IFERROR(VLOOKUP($F79,'维度字典'!$I$2:$J$50,2,0),"求和")="手工录入","",IF(IFERROR(VLOOKUP($F79,'维度字典'!$I$2:$J$50,2,0),"求和")="最新值",IFERROR(LOOKUP(9.99E+307,G79:R79),""),SUM(G79:R79)))) | T79: 管道良好：新客户导入顺利，机会转化符合预期
A80: =IF($B80="","",ROW()-3) | B80: 李四 | C80: 空调制冷 | D80: 钎焊 | E80: 华南 | F80: 目标客户机会 | G80: 52 | H80: 53 | I80: 54 | J80: 55 | K80: 56 | L80: 57 | M80: 58 | N80: 59 | O80: 60 | P80: 62 | Q80: 62 | R80: 63 | S80: =IF($F80="","",IF(IFERROR(VLOOKUP($F80,'维度字典'!$I$2:$J$50,2,0),"求和")="手工录入","",IF(IFERROR(VLOOKUP($F80,'维度字典'!$I$2:$J$50,2,0),"求和")="最新值",IFERROR(LOOKUP(9.99E+307,G80:R80),""),SUM(G80:R80))))
A81: =IF($B81="","",ROW()-3) | B81: 李四 | C81: 空调制冷 | D81: 可拆 | E81: 华南 | F81: 销售目标额 | G81: 22 | H81: 19 | I81: 25 | J81: 28 | K81: 28 | L81: 32 | M81: 32 | N81: 28 | O81: 28 | P81: 28 | Q81: 25 | R81: 19 | S81: =IF($F81="","",IF(IFERROR(VLOOKUP($F81,'维度字典'!$I$2:$J$50,2,0),"求和")="手工录入","",IF(IFERROR(VLOOKUP($F81,'维度字典'!$I$2:$J$50,2,0),"求和")="最新值",IFERROR(LOOKUP(9.99E+307,G81:R81),""),SUM(G81:R81))))
A82: =IF($B82="","",ROW()-3) | B82: 李四 | C82: 空调制冷 | D82: 可拆 | E82: 华南 | F82: 毛利目标 | G82: 3.3 | H82: 2.8 | I82: 3.8 | J82: 4.3 | K82: 4.3 | L82: 4.7 | M82: 4.7 | N82: 4.3 | O82: 4.3 | P82: 4.3 | Q82: 3.8 | R82: 2.8 | S82: =IF($F82="","",IF(IFERROR(VLOOKUP($F82,'维度字典'!$I$2:$J$50,2,0),"求和")="手工录入","",IF(IFERROR(VLOOKUP($F82,'维度字典'!$I$2:$J$50,2,0),"求和")="最新值",IFERROR(LOOKUP(9.99E+307,G82:R82),""),SUM(G82:R82))))
A83: =IF($B83="","",ROW()-3) | B83: 李四 | C83: 空调制冷 | D83: 可拆 | E83: 华南 | F83: 毛利率目标 | G83: 0.144 | H83: 0.1452 | I83: 0.1464 | J83: 0.1476 | K83: 0.1488 | L83: 0.15 | M83: 0.1512 | N83: 0.1524 | O83: 0.1536 | P83: 0.1548 | Q83: 0.156 | R83: 0.1572 | S83: 0.15
A84: =IF($B84="","",ROW()-3) | B84: 李四 | C84: 空调制冷 | D84: 可拆 | E84: 华南 | F84: 在手订单目标 | G84: 37 | H84: 38 | I84: 38 | J84: 39 | K84: 39 | L84: 40 | M84: 40 | N84: 41 | O84: 41 | P84: 42 | Q84: 43 | R84: 43 | S84: =IF($F84="","",IF(IFERROR(VLOOKUP($F84,'维度字典'!$I$2:$J$50,2,0),"求和")="手工录入","",IF(IFERROR(VLOOKUP($F84,'维度字典'!$I$2:$J$50,2,0),"求和")="最新值",IFERROR(LOOKUP(9.99E+307,G84:R84),""),SUM(G84:R84))))
A85: =IF($B85="","",ROW()-3) | B85: 李四 | C85: 空调制冷 | D85: 可拆 | E85: 华南 | F85: 目标客户机会目标 | G85: 27 | H85: 27 | I85: 28 | J85: 28 | K85: 29 | L85: 29 | M85: 30 | N85: 30 | O85: 31 | P85: 32 | Q85: 32 | R85: 33 | S85: =IF($F85="","",IF(IFERROR(VLOOKUP($F85,'维度字典'!$I$2:$J$50,2,0),"求和")="手工录入","",IF(IFERROR(VLOOKUP($F85,'维度字典'!$I$2:$J$50,2,0),"求和")="最新值",IFERROR(LOOKUP(9.99E+307,G85:R85),""),SUM(G85:R85))))
A86: =IF($B86="","",ROW()-3) | B86: 李四 | C86: 空调制冷 | D86: 可拆 | E86: 华南 | F86: 在手订单 | G86: 36 | H86: 37 | I86: 37 | J86: 38 | K86: 38 | L86: 39 | M86: 39 | N86: 40 | O86: 40 | P86: 41 | Q86: 42 | R86: 42 | S86: =IF($F86="","",IF(IFERROR(VLOOKUP($F86,'维度字典'!$I$2:$J$50,2,0),"求和")="手工录入","",IF(IFERROR(VLOOKUP($F86,'维度字典'!$I$2:$J$50,2,0),"求和")="最新值",IFERROR(LOOKUP(9.99E+307,G86:R86),""),SUM(G86:R86)))) | T86: 管道良好：新客户导入顺利，机会转化符合预期
A87: =IF($B87="","",ROW()-3) | B87: 李四 | C87: 空调制冷 | D87: 可拆 | E87: 华南 | F87: 目标客户机会 | G87: 22 | H87: 22 | I87: 23 | J87: 23 | K87: 24 | L87: 24 | M87: 25 | N87: 25 | O87: 25 | P87: 26 | Q87: 26 | R87: 27 | S87: =IF($F87="","",IF(IFERROR(VLOOKUP($F87,'维度字典'!$I$2:$J$50,2,0),"求和")="手工录入","",IF(IFERROR(VLOOKUP($F87,'维度字典'!$I$2:$J$50,2,0),"求和")="最新值",IFERROR(LOOKUP(9.99E+307,G87:R87),""),SUM(G87:R87))))
A88: =IF($B88="","",ROW()-3) | B88: 李四 | C88: 工业制冷 | D88: 钎焊 | E88: 华南 | F88: 销售目标额 | G88: 31 | H88: 26 | I88: 35 | J88: 39 | K88: 39 | L88: 44 | M88: 44 | N88: 39 | O88: 39 | P88: 39 | Q88: 35 | R88: 26 | S88: =IF($F88="","",IF(IFERROR(VLOOKUP($F88,'维度字典'!$I$2:$J$50,2,0),"求和")="手工录入","",IF(IFERROR(VLOOKUP($F88,'维度字典'!$I$2:$J$50,2,0),"求和")="最新值",IFERROR(LOOKUP(9.99E+307,G88:R88),""),SUM(G88:R88))))
A89: =IF($B89="","",ROW()-3) | B89: 李四 | C89: 工业制冷 | D89: 钎焊 | E89: 华南 | F89: 毛利目标 | G89: 4.9 | H89: 4.2 | I89: 5.6 | J89: 6.3 | K89: 6.3 | L89: 7 | M89: 7 | N89: 6.3 | O89: 6.3 | P89: 6.3 | Q89: 5.6 | R89: 4.2 | S89: =IF($F89="","",IF(IFERROR(VLOOKUP($F89,'维度字典'!$I$2:$J$50,2,0),"求和")="手工录入","",IF(IFERROR(VLOOKUP($F89,'维度字典'!$I$2:$J$50,2,0),"求和")="最新值",IFERROR(LOOKUP(9.99E+307,G89:R89),""),SUM(G89:R89))))
A90: =IF($B90="","",ROW()-3) | B90: 李四 | C90: 工业制冷 | D90: 钎焊 | E90: 华南 | F90: 毛利率目标 | G90: 0.1536 | H90: 0.1549 | I90: 0.1562 | J90: 0.1574 | K90: 0.1587 | L90: 0.16 | M90: 0.1613 | N90: 0.1626 | O90: 0.1638 | P90: 0.1651 | Q90: 0.1664 | R90: 0.1677 | S90: 0.16
A91: =IF($B91="","",ROW()-3) | B91: 李四 | C91: 工业制冷 | D91: 钎焊 | E91: 华南 | F91: 在手订单目标 | G91: 52 | H91: 53 | I91: 53 | J91: 54 | K91: 55 | L91: 55 | M91: 56 | N91: 57 | O91: 58 | P91: 58 | Q91: 59 | R91: 60 | S91: =IF($F91="","",IF(IFERROR(VLOOKUP($F91,'维度字典'!$I$2:$J$50,2,0),"求和")="手工录入","",IF(IFERROR(VLOOKUP($F91,'维度字典'!$I$2:$J$50,2,0),"求和")="最新值",IFERROR(LOOKUP(9.99E+307,G91:R91),""),SUM(G91:R91))))
A92: =IF($B92="","",ROW()-3) | B92: 李四 | C92: 工业制冷 | D92: 钎焊 | E92: 华南 | F92: 目标客户机会目标 | G92: 37 | H92: 38 | I92: 39 | J92: 39 | K92: 40 | L92: 41 | M92: 42 | N92: 42 | O92: 43 | P92: 44 | Q92: 45 | R92: 45 | S92: =IF($F92="","",IF(IFERROR(VLOOKUP($F92,'维度字典'!$I$2:$J$50,2,0),"求和")="手工录入","",IF(IFERROR(VLOOKUP($F92,'维度字典'!$I$2:$J$50,2,0),"求和")="最新值",IFERROR(LOOKUP(9.99E+307,G92:R92),""),SUM(G92:R92))))
A93: =IF($B93="","",ROW()-3) | B93: 李四 | C93: 工业制冷 | D93: 钎焊 | E93: 华南 | F93: 在手订单 | G93: 52 | H93: 53 | I93: 53 | J93: 54 | K93: 55 | L93: 55 | M93: 56 | N93: 57 | O93: 58 | P93: 58 | Q93: 59 | R93: 60 | S93: =IF($F93="","",IF(IFERROR(VLOOKUP($F93,'维度字典'!$I$2:$J$50,2,0),"求和")="手工录入","",IF(IFERROR(VLOOKUP($F93,'维度字典'!$I$2:$J$50,2,0),"求和")="最新值",IFERROR(LOOKUP(9.99E+307,G93:R93),""),SUM(G93:R93)))) | T93: 管道良好：新客户导入顺利，机会转化符合预期
A94: =IF($B94="","",ROW()-3) | B94: 李四 | C94: 工业制冷 | D94: 钎焊 | E94: 华南 | F94: 目标客户机会 | G94: 31 | H94: 32 | I94: 33 | J94: 33 | K94: 34 | L94: 35 | M94: 35 | N94: 35 | O94: 36 | P94: 37 | Q94: 38 | R94: 38 | S94: =IF($F94="","",IF(IFERROR(VLOOKUP($F94,'维度字典'!$I$2:$J$50,2,0),"求和")="手工录入","",IF(IFERROR(VLOOKUP($F94,'维度字典'!$I$2:$J$50,2,0),"求和")="最新值",IFERROR(LOOKUP(9.99E+307,G94:R94),""),SUM(G94:R94))))
A95: =IF($B95="","",ROW()-3) | B95: 李四 | C95: 工业制冷 | D95: 可拆 | E95: 华南 | F95: 销售目标额 | G95: 31 | H95: 26 | I95: 35 | J95: 39 | K95: 39 | L95: 44 | M95: 44 | N95: 39 | O95: 39 | P95: 39 | Q95: 35 | R95: 26 | S95: =IF($F95="","",IF(IFERROR(VLOOKUP($F95,'维度字典'!$I$2:$J$50,2,0),"求和")="手工录入","",IF(IFERROR(VLOOKUP($F95,'维度字典'!$I$2:$J$50,2,0),"求和")="最新值",IFERROR(LOOKUP(9.99E+307,G95:R95),""),SUM(G95:R95))))
A96: =IF($B96="","",ROW()-3) | B96: 李四 | C96: 工业制冷 | D96: 可拆 | E96: 华南 | F96: 毛利目标 | G96: 4.9 | H96: 4.2 | I96: 5.6 | J96: 6.3 | K96: 6.3 | L96: 7 | M96: 7 | N96: 6.3 | O96: 6.3 | P96: 6.3 | Q96: 5.6 | R96: 4.2 | S96: =IF($F96="","",IF(IFERROR(VLOOKUP($F96,'维度字典'!$I$2:$J$50,2,0),"求和")="手工录入","",IF(IFERROR(VLOOKUP($F96,'维度字典'!$I$2:$J$50,2,0),"求和")="最新值",IFERROR(LOOKUP(9.99E+307,G96:R96),""),SUM(G96:R96))))
A97: =IF($B97="","",ROW()-3) | B97: 李四 | C97: 工业制冷 | D97: 可拆 | E97: 华南 | F97: 毛利率目标 | G97: 0.1536 | H97: 0.1549 | I97: 0.1562 | J97: 0.1574 | K97: 0.1587 | L97: 0.16 | M97: 0.1613 | N97: 0.1626 | O97: 0.1638 | P97: 0.1651 | Q97: 0.1664 | R97: 0.1677 | S97: 0.16
A98: =IF($B98="","",ROW()-3) | B98: 李四 | C98: 工业制冷 | D98: 可拆 | E98: 华南 | F98: 在手订单目标 | G98: 52 | H98: 52 | I98: 53 | J98: 54 | K98: 55 | L98: 55 | M98: 56 | N98: 57 | O98: 58 | P98: 58 | Q98: 59 | R98: 60 | S98: =IF($F98="","",IF(IFERROR(VLOOKUP($F98,'维度字典'!$I$2:$J$50,2,0),"求和")="手工录入","",IF(IFERROR(VLOOKUP($F98,'维度字典'!$I$2:$J$50,2,0),"求和")="最新值",IFERROR(LOOKUP(9.99E+307,G98:R98),""),SUM(G98:R98))))
A99: =IF($B99="","",ROW()-3) | B99: 李四 | C99: 工业制冷 | D99: 可拆 | E99: 华南 | F99: 目标客户机会目标 | G99: 37 | H99: 38 | I99: 39 | J99: 39 | K99: 40 | L99: 41 | M99: 42 | N99: 42 | O99: 43 | P99: 44 | Q99: 44 | R99: 45 | S99: =IF($F99="","",IF(IFERROR(VLOOKUP($F99,'维度字典'!$I$2:$J$50,2,0),"求和")="手工录入","",IF(IFERROR(VLOOKUP($F99,'维度字典'!$I$2:$J$50,2,0),"求和")="最新值",IFERROR(LOOKUP(9.99E+307,G99:R99),""),SUM(G99:R99))))
A100: =IF($B100="","",ROW()-3) | B100: 李四 | C100: 工业制冷 | D100: 可拆 | E100: 华南 | F100: 在手订单 | G100: 51 | H100: 51 | I100: 52 | J100: 53 | K100: 54 | L100: 54 | M100: 55 | N100: 56 | O100: 57 | P100: 57 | Q100: 58 | R100: 59 | S100: =IF($F100="","",IF(IFERROR(VLOOKUP($F100,'维度字典'!$I$2:$J$50,2,0),"求和")="手工录入","",IF(IFERROR(VLOOKUP($F100,'维度字典'!$I$2:$J$50,2,0),"求和")="最新值",IFERROR(LOOKUP(9.99E+307,G100:R100),""),SUM(G100:R100)))) | T100: 管道良好：新客户导入顺利，机会转化符合预期
...

Sheet 系统实绩导入
A1: 系统实绩导入（按月）—— BI系统数据落地区：数据管理员每月从系统导出后粘贴当月列；业务人员勿改
B2: 填报维度（下拉选择） | G2: 月度填报（万元）—— 当月填当列 | S2: 全年 | T2: 备注
A3: 序号 | B3: 业务员* | C3: 应用行业* | D3: 产品*(钎焊/可拆) | E3: 区域(预留) | F3: 填报指标* | G3: 1 | H3: 2 | I3: 3 | J3: 4 | K3: 5 | L3: 6 | M3: 7 | N3: 8 | O3: 9 | P3: 10 | Q3: 11 | R3: 12 | S3: 全年汇总 (自动/录入) | T3: 差异分析/备注
A4: =IF($B4="","",ROW()-3) | B4: 张三 | C4: 空调制冷 | D4: 钎焊 | E4: 华东 | F4: 实绩销售额 | G4: 62 | H4: 54 | I4: 71 | J4: 80 | K4: 80 | L4: 89 | M4: 89 | N4: 80 | O4: 80 | P4: 80 | Q4: 71 | R4: 54 | S4: =IF($F4="","",IF(IFERROR(VLOOKUP($F4,'维度字典'!$M$2:$N$50,2,0),"求和")="手工录入","",IF(IFERROR(VLOOKUP($F4,'维度字典'!$M$2:$N$50,2,0),"求和")="最新值",IFERROR(LOOKUP(9.99E+307,G4:R4),""),SUM(G4:R4))))
A5: =IF($B5="","",ROW()-3) | B5: 张三 | C5: 空调制冷 | D5: 钎焊 | E5: 华东 | F5: 实绩毛利 | G5: 9.3 | H5: 8.1 | I5: 10.7 | J5: 12 | K5: 12 | L5: 13.3 | M5: 13.3 | N5: 12 | O5: 12 | P5: 12 | Q5: 10.7 | R5: 8.1 | S5: =IF($F5="","",IF(IFERROR(VLOOKUP($F5,'维度字典'!$M$2:$N$50,2,0),"求和")="手工录入","",IF(IFERROR(VLOOKUP($F5,'维度字典'!$M$2:$N$50,2,0),"求和")="最新值",IFERROR(LOOKUP(9.99E+307,G5:R5),""),SUM(G5:R5))))
A6: =IF($B6="","",ROW()-3) | B6: 张三 | C6: 空调制冷 | D6: 可拆 | E6: 华东 | F6: 实绩销售额 | G6: 25 | H6: 22 | I6: 29 | J6: 33 | K6: 33 | L6: 36 | M6: 36 | N6: 33 | O6: 33 | P6: 33 | Q6: 29 | R6: 22 | S6: =IF($F6="","",IF(IFERROR(VLOOKUP($F6,'维度字典'!$M$2:$N$50,2,0),"求和")="手工录入","",IF(IFERROR(VLOOKUP($F6,'维度字典'!$M$2:$N$50,2,0),"求和")="最新值",IFERROR(LOOKUP(9.99E+307,G6:R6),""),SUM(G6:R6))))
A7: =IF($B7="","",ROW()-3) | B7: 张三 | C7: 空调制冷 | D7: 可拆 | E7: 华东 | F7: 实绩毛利 | G7: 3.8 | H7: 3.3 | I7: 4.3 | J7: 5 | K7: 5 | L7: 5.4 | M7: 5.4 | N7: 5 | O7: 5 | P7: 5 | Q7: 4.3 | R7: 3.3 | S7: =IF($F7="","",IF(IFERROR(VLOOKUP($F7,'维度字典'!$M$2:$N$50,2,0),"求和")="手工录入","",IF(IFERROR(VLOOKUP($F7,'维度字典'!$M$2:$N$50,2,0),"求和")="最新值",IFERROR(LOOKUP(9.99E+307,G7:R7),""),SUM(G7:R7))))
A8: =IF($B8="","",ROW()-3) | B8: 张三 | C8: 工业制冷 | D8: 钎焊 | E8: 华东 | F8: 实绩销售额 | G8: 39 | H8: 34 | I8: 45 | J8: 51 | K8: 51 | L8: 56 | M8: 56 | N8: 51 | O8: 51 | P8: 51 | Q8: 45 | R8: 34 | S8: =IF($F8="","",IF(IFERROR(VLOOKUP($F8,'维度字典'!$M$2:$N$50,2,0),"求和")="手工录入","",IF(IFERROR(VLOOKUP($F8,'维度字典'!$M$2:$N$50,2,0),"求和")="最新值",IFERROR(LOOKUP(9.99E+307,G8:R8),""),SUM(G8:R8))))
A9: =IF($B9="","",ROW()-3) | B9: 张三 | C9: 工业制冷 | D9: 钎焊 | E9: 华东 | F9: 实绩毛利 | G9: 6.2 | H9: 5.4 | I9: 7.2 | J9: 8.2 | K9: 8.2 | L9: 9 | M9: 9 | N9: 8.2 | O9: 8.2 | P9: 8.2 | Q9: 7.2 | R9: 5.4 | S9: =IF($F9="","",IF(IFERROR(VLOOKUP($F9,'维度字典'!$M$2:$N$50,2,0),"求和")="手工录入","",IF(IFERROR(VLOOKUP($F9,'维度字典'!$M$2:$N$50,2,0),"求和")="最新值",IFERROR(LOOKUP(9.99E+307,G9:R9),""),SUM(G9:R9))))
A10: =IF($B10="","",ROW()-3) | B10: 张三 | C10: 工业制冷 | D10: 可拆 | E10: 华东 | F10: 实绩销售额 | G10: 37 | H10: 32 | I10: 43 | J10: 48 | K10: 48 | L10: 54 | M10: 54 | N10: 48 | O10: 48 | P10: 48 | Q10: 43 | R10: 32 | S10: =IF($F10="","",IF(IFERROR(VLOOKUP($F10,'维度字典'!$M$2:$N$50,2,0),"求和")="手工录入","",IF(IFERROR(VLOOKUP($F10,'维度字典'!$M$2:$N$50,2,0),"求和")="最新值",IFERROR(LOOKUP(9.99E+307,G10:R10),""),SUM(G10:R10))))
A11: =IF($B11="","",ROW()-3) | B11: 张三 | C11: 工业制冷 | D11: 可拆 | E11: 华东 | F11: 实绩毛利 | G11: 5.9 | H11: 5.1 | I11: 6.9 | J11: 7.7 | K11: 7.7 | L11: 8.6 | M11: 8.6 | N11: 7.7 | O11: 7.7 | P11: 7.7 | Q11: 6.9 | R11: 5.1 | S11: =IF($F11="","",IF(IFERROR(VLOOKUP($F11,'维度字典'!$M$2:$N$50,2,0),"求和")="手工录入","",IF(IFERROR(VLOOKUP($F11,'维度字典'!$M$2:$N$50,2,0),"求和")="最新值",IFERROR(LOOKUP(9.99E+307,G11:R11),""),SUM(G11:R11))))
A12: =IF($B12="","",ROW()-3) | B12: 张三 | C12: 船舶行业 | D12: 钎焊 | E12: 华东 | F12: 实绩销售额 | G12: 9 | H12: 7 | I12: 10 | J12: 11 | K12: 11 | L12: 12 | M12: 12 | N12: 11 | O12: 11 | P12: 11 | Q12: 10 | R12: 7 | S12: =IF($F12="","",IF(IFERROR(VLOOKUP($F12,'维度字典'!$M$2:$N$50,2,0),"求和")="手工录入","",IF(IFERROR(VLOOKUP($F12,'维度字典'!$M$2:$N$50,2,0),"求和")="最新值",IFERROR(LOOKUP(9.99E+307,G12:R12),""),SUM(G12:R12))))
A13: =IF($B13="","",ROW()-3) | B13: 张三 | C13: 船舶行业 | D13: 钎焊 | E13: 华东 | F13: 实绩毛利 | G13: 1.8 | H13: 1.4 | I13: 2 | J13: 2.2 | K13: 2.2 | L13: 2.4 | M13: 2.4 | N13: 2.2 | O13: 2.2 | P13: 2.2 | Q13: 2 | R13: 1.4 | S13: =IF($F13="","",IF(IFERROR(VLOOKUP($F13,'维度字典'!$M$2:$N$50,2,0),"求和")="手工录入","",IF(IFERROR(VLOOKUP($F13,'维度字典'!$M$2:$N$50,2,0),"求和")="最新值",IFERROR(LOOKUP(9.99E+307,G13:R13),""),SUM(G13:R13))))
A14: =IF($B14="","",ROW()-3) | B14: 张三 | C14: 船舶行业 | D14: 可拆 | E14: 华东 | F14: 实绩销售额 | G14: 12 | H14: 10 | I14: 14 | J14: 16 | K14: 16 | L14: 17 | M14: 17 | N14: 16 | O14: 16 | P14: 16 | Q14: 14 | R14: 10 | S14: =IF($F14="","",IF(IFERROR(VLOOKUP($F14,'维度字典'!$M$2:$N$50,2,0),"求和")="手工录入","",IF(IFERROR(VLOOKUP($F14,'维度字典'!$M$2:$N$50,2,0),"求和")="最新值",IFERROR(LOOKUP(9.99E+307,G14:R14),""),SUM(G14:R14))))
A15: =IF($B15="","",ROW()-3) | B15: 张三 | C15: 船舶行业 | D15: 可拆 | E15: 华东 | F15: 实绩毛利 | G15: 2.4 | H15: 2 | I15: 2.8 | J15: 3.2 | K15: 3.2 | L15: 3.4 | M15: 3.4 | N15: 3.2 | O15: 3.2 | P15: 3.2 | Q15: 2.8 | R15: 2 | S15: =IF($F15="","",IF(IFERROR(VLOOKUP($F15,'维度字典'!$M$2:$N$50,2,0),"求和")="手工录入","",IF(IFERROR(VLOOKUP($F15,'维度字典'!$M$2:$N$50,2,0),"求和")="最新值",IFERROR(LOOKUP(9.99E+307,G15:R15),""),SUM(G15:R15))))
... A63: =IF($B63="","",ROW()-3) | B63: 王五 | C63: 数据中心 | D63: 可拆 | E63: 华北 | F63: 实绩毛利 | G63: 1.8 | H63: 1.3 | I63: 2 | J63: 2.2 | K63: 2.2 | L63: 2.4 | M63: 2.4 | N63: 2.2 | O63: 2.2 | P63: 2.2 | Q63: 2 | R63: 1.3 | S63: =IF($F63="","",IF(IFERROR(VLOOKUP($F63,'维度字典'!$M$2:$N$50,2,0),"求和")="手工录入","",IF(IFERROR(VLOOKUP($F63,'维度字典'!$M$2:$N$50,2,0),"求和")="最新值",IFERROR(LOOKUP(9.99E+307,G63:R63),""),SUM(G63:R63))))
A64: =IF($B64="","",ROW()-3) | S64: =IF($F64="","",IF(IFERROR(VLOOKUP($F64,'维度字典'!$M$2:$N$50,2,0),"求和")="手工录入","",IF(IFERROR(VLOOKUP($F64,'维度字典'!$M$2:$N$50,2,0),"求和")="最新值",IFERROR(LOOKUP(9.99E+307,G64:R64),""),SUM(G64:R64))))
A65: =IF($B65="","",ROW()-3) | S65: =IF($F65="","",IF(IFERROR(VLOOKUP($F65,'维度字典'!$M$2:$N$50,2,0),"求和")="手工录入","",IF(IFERROR(VLOOKUP($F65,'维度字典'!$M$2:$N$50,2,0),"求和")="最新值",IFERROR(LOOKUP(9.99E+307,G65:R65),""),SUM(G65:R65))))
A66: =IF($B66="","",ROW()-3) | S66: =IF($F66="","",IF(IFERROR(VLOOKUP($F66,'维度字典'!$M$2:$N$50,2,0),"求和")="手工录入","",IF(IFERROR(VLOOKUP($F66,'维度字典'!$M$2:$N$50,2,0),"求和")="最新值",IFERROR(LOOKUP(9.99E+307,G66:R66),""),SUM(G66:R66))))
A67: =IF($B67="","",ROW()-3) | S67: =IF($F67="","",IF(IFERROR(VLOOKUP($F67,'维度字典'!$M$2:$N$50,2,0),"求和")="手工录入","",IF(IFERROR(VLOOKUP($F67,'维度字典'!$M$2:$N$50,2,0),"求和")="最新值",IFERROR(LOOKUP(9.99E+307,G67:R67),""),SUM(G67:R67))))
A68: =IF($B68="","",ROW()-3) | S68: =IF($F68="","",IF(IFERROR(VLOOKUP($F68,'维度字典'!$M$2:$N$50,2,0),"求和")="手工录入","",IF(IFERROR(VLOOKUP($F68,'维度字典'!$M$2:$N$50,2,0),"求和")="最新值",IFERROR(LOOKUP(9.99E+307,G68:R68),""),SUM(G68:R68))))
A69: =IF($B69="","",ROW()-3) | S69: =IF($F69="","",IF(IFERROR(VLOOKUP($F69,'维度字典'!$M$2:$N$50,2,0),"求和")="手工录入","",IF(IFERROR(VLOOKUP($F69,'维度字典'!$M$2:$N$50,2,0),"求和")="最新值",IFERROR(LOOKUP(9.99E+307,G69:R69),""),SUM(G69:R69))))
A70: =IF($B70="","",ROW()-3) | S70: =IF($F70="","",IF(IFERROR(VLOOKUP($F70,'维度字典'!$M$2:$N$50,2,0),"求和")="手工录入","",IF(IFERROR(VLOOKUP($F70,'维度字典'!$M$2:$N$50,2,0),"求和")="最新值",IFERROR(LOOKUP(9.99E+307,G70:R70),""),SUM(G70:R70))))
A71: =IF($B71="","",ROW()-3) | S71: =IF($F71="","",IF(IFERROR(VLOOKUP($F71,'维度字典'!$M$2:$N$50,2,0),"求和")="手工录入","",IF(IFERROR(VLOOKUP($F71,'维度字典'!$M$2:$N$50,2,0),"求和")="最新值",IFERROR(LOOKUP(9.99E+307,G71:R71),""),SUM(G71:R71))))
A72: =IF($B72="","",ROW()-3) | S72: =IF($F72="","",IF(IFERROR(VLOOKUP($F72,'维度字典'!$M$2:$N$50,2,0),"求和")="手工录入","",IF(IFERROR(VLOOKUP($F72,'维度字典'!$M$2:$N$50,2,0),"求和")="最新值",IFERROR(LOOKUP(9.99E+307,G72:R72),""),SUM(G72:R72))))
A73: =IF($B73="","",ROW()-3) | S73: =IF($F73="","",IF(IFERROR(VLOOKUP($F73,'维度字典'!$M$2:$N$50,2,0),"求和")="手工录入","",IF(IFERROR(VLOOKUP($F73,'维度字典'!$M$2:$N$50,2,0),"求和")="最新值",IFERROR(LOOKUP(9.99E+307,G73:R73),""),SUM(G73:R73))))
A74: =IF($B74="","",ROW()-3) | S74: =IF($F74="","",IF(IFERROR(VLOOKUP($F74,'维度字典'!$M$2:$N$50,2,0),"求和")="手工录入","",IF(IFERROR(VLOOKUP($F74,'维度字典'!$M$2:$N$50,2,0),"求和")="最新值",IFERROR(LOOKUP(9.99E+307,G74:R74),""),SUM(G74:R74))))
A75: =IF($B75="","",ROW()-3) | S75: =IF($F75="","",IF(IFERROR(VLOOKUP($F75,'维度字典'!$M$2:$N$50,2,0),"求和")="手工录入","",IF(IFERROR(VLOOKUP($F75,'维度字典'!$M$2:$N$50,2,0),"求和")="最新值",IFERROR(LOOKUP(9.99E+307,G75:R75),""),SUM(G75:R75))))
... A1500: =IF($B1500="","",ROW()-3) | S1500: =IF($F1500="","",IF(IFERROR(VLOOKUP($F1500,'维度字典'!$M$2:$N$50,2,0),"求和")="手工录入","",IF(IFERROR(VLOOKUP($F1500,'维度字典'!$M$2:$N$50,2,0),"求和")="最新值",IFERROR(LOOKUP(9.99E+307,G1500:R1500),""),SUM(G1500:R1500))))

Sheet 达成看板
A1: 达成看板 —— 全部公式自动计算，无需填写（当期达成 / 全年累计达成 / 管道充裕度 / 下期预测） | E1: 统计月份(1-12)： | F1: 7
A2: 组合维度（字典自动展开） | E2: 当期达成（本月） | J2: 全年累计达成（1-X月） | P2: 管道充裕度（月末时点） | V2: 下期预测（在手+机会）
A3: 序号 | B3: 业务员 | C3: 应用行业 | D3: 产品 | E3: 本月销售额 | F3: 本月毛利 | G3: 本月毛利率 | H3: 本月目标 | I3: 本月目标达成率 | J3: 累计销售额 | K3: 累计毛利 | L3: 累计毛利率 | M3: 年度目标 | N3: 累计达成率 | O3: 与目标差距 | P3: 在手订单 | Q3: 在手订单目标 | R3: 在手订单达成率 | S3: 目标客户机会 | T3: 目标客户机会目标 | U3: 目标客户机会达成率 | V3: 预测合计 | W3: 剩余目标 | X3: 预测达成率 | Y3: 预测与目标差距
A4: =IF($B4="","",ROW()-3) | B4: =IF(0+1>COUNTA('维度字典'!$C$2:$C$200)*COUNTA('维度字典'!$A$2:$A$200)*COUNTA('维度字典'!$E$2:$E$200),"",INDEX('维度字典'!$C$2:$C$200,MOD(INT(0/(COUNTA('维度字典'!$E$2:$E$200)*COUNTA('维度字典'!$A$2:$A$200))),COUNTA('维度字典'!$C$2:$C$200))+1)) | C4: =IF($B4="","",INDEX('维度字典'!$A$2:$A$200,MOD(INT(0/COUNTA('维度字典'!$E$2:$E$200)),COUNTA('维度字典'!$A$2:$A$200))+1)) | D4: =IF($B4="","",INDEX('维度字典'!$E$2:$E$200,MOD(0,COUNTA('维度字典'!$E$2:$E$200))+1)) | E4: =IF($B4="","",SUMPRODUCT(('系统实绩导入'!$B$4:$B$1500=$B4)*('系统实绩导入'!$C$4:$C$1500=$C4)*('系统实绩导入'!$D$4:$D$1500=$D4)*('系统实绩导入'!$F$4:$F$1500="实绩销售额")*('系统实绩导入'!$G$3:$R$3=$F$1)*'系统实绩导入'!$G$4:$R$1500)) | F4: =IF($B4="","",SUMPRODUCT(('系统实绩导入'!$B$4:$B$1500=$B4)*('系统实绩导入'!$C$4:$C$1500=$C4)*('系统实绩导入'!$D$4:$D$1500=$D4)*('系统实绩导入'!$F$4:$F$1500="实绩毛利")*('系统实绩导入'!$G$3:$R$3=$F$1)*'系统实绩导入'!$G$4:$R$1500)) | G4: =IF($B4="","",IFERROR(F4/E4,"")) | H4: =IF($B4="","",SUMPRODUCT(('目标填报'!$B$4:$B$1500=$B4)*('目标填报'!$C$4:$C$1500=$C4)*('目标填报'!$D$4:$D$1500=$D4)*('目标填报'!$F$4:$F$1500="销售目标额")*('目标填报'!$G$3:$R$3=$F$1)*'目标填报'!$G$4:$R$1500)) | I4: =IF($B4="","",IFERROR(E4/H4,"")) | J4: =IF($B4="","",SUMPRODUCT(('系统实绩导入'!$B$4:$B$1500=$B4)*('系统实绩导入'!$C$4:$C$1500=$C4)*('系统实绩导入'!$D$4:$D$1500=$D4)*('系统实绩导入'!$F$4:$F$1500="实绩销售额")*('系统实绩导入'!$G$3:$R$3<=$F$1)*'系统实绩导入'!$G$4:$R$1500)) | K4: =IF($B4="","",SUMPRODUCT(('系统实绩导入'!$B$4:$B$1500=$B4)*('系统实绩导入'!$C$4:$C$1500=$C4)*('系统实绩导入'!$D$4:$D$1500=$D4)*('系统实绩导入'!$F$4:$F$1500="实绩毛利")*('系统实绩导入'!$G$3:$R$3<=$F$1)*'系统实绩导入'!$G$4:$R$1500)) | L4: =IF($B4="","",IFERROR(K4/J4,"")) | M4: =IF($B4="","",SUMIFS('目标填报'!$S$4:$S$1500,'目标填报'!$B$4:$B$1500,$B4,'目标填报'!$C$4:$C$1500,$C4,'目标填报'!$D$4:$D$1500,$D4,'目标填报'!$F$4:$F$1500,"销售目标额")) | N4: =IF($B4="","",IFERROR(J4/M4,"")) | O4: =IF($B4="","",J4-M4) | P4: =IF($B4="","",SUMPRODUCT(('目标填报'!$B$4:$B$1500=$B4)*('目标填报'!$C$4:$C$1500=$C4)*('目标填报'!$D$4:$D$1500=$D4)*('目标填报'!$F$4:$F$1500="在手订单")*('目标填报'!$G$3:$R$3=$F$1)*'目标填报'!$G$4:$R$1500)) | Q4: =IF($B4="","",SUMPRODUCT(('目标填报'!$B$4:$B$1500=$B4)*('目标填报'!$C$4:$C$1500=$C4)*('目标填报'!$D$4:$D$1500=$D4)*('目标填报'!$F$4:$F$1500="在手订单目标")*('目标填报'!$G$3:$R$3=$F$1)*'目标填报'!$G$4:$R$1500)) | R4: =IF($B4="","",IFERROR(P4/Q4,"")) | S4: =IF($B4="","",SUMPRODUCT(('目标填报'!$B$4:$B$1500=$B4)*('目标填报'!$C$4:$C$1500=$C4)*('目标填报'!$D$4:$D$1500=$D4)*('目标填报'!$F$4:$F$1500="目标客户机会")*('目标填报'!$G$3:$R$3=$F$1)*'目标填报'!$G$4:$R$1500)) | T4: =IF($B4="","",SUMPRODUCT(('目标填报'!$B$4:$B$1500=$B4)*('目标填报'!$C$4:$C$1500=$C4)*('目标填报'!$D$4:$D$1500=$D4)*('目标填报'!$F$4:$F$1500="目标客户机会目标")*('目标填报'!$G$3:$R$3=$F$1)*'目标填报'!$G$4:$R$1500)) | U4: =IF($B4="","",IFERROR(S4/T4,"")) | V4: =IF($B4="","",P4+S4) | W4: =IF($B4="","",M4-J4) | X4: =IF($B4="","",IFERROR(V4/W4,"")) | Y4: =IF($B4="","",V4-W4)
A5: =IF($B5="","",ROW()-3) | B5: =IF(1+1>COUNTA('维度字典'!$C$2:$C$200)*COUNTA('维度字典'!$A$2:$A$200)*COUNTA('维度字典'!$E$2:$E$200),"",INDEX('维度字典'!$C$2:$C$200,MOD(INT(1/(COUNTA('维度字典'!$E$2:$E$200)*COUNTA('维度字典'!$A$2:$A$200))),COUNTA('维度字典'!$C$2:$C$200))+1)) | C5: =IF($B5="","",INDEX('维度字典'!$A$2:$A$200,MOD(INT(1/COUNTA('维度字典'!$E$2:$E$200)),COUNTA('维度字典'!$A$2:$A$200))+1)) | D5: =IF($B5="","",INDEX('维度字典'!$E$2:$E$200,MOD(1,COUNTA('维度字典'!$E$2:$E$200))+1)) | E5: =IF($B5="","",SUMPRODUCT(('系统实绩导入'!$B$4:$B$1500=$B5)*('系统实绩导入'!$C$4:$C$1500=$C5)*('系统实绩导入'!$D$4:$D$1500=$D5)*('系统实绩导入'!$F$4:$F$1500="实绩销售额")*('系统实绩导入'!$G$3:$R$3=$F$1)*'系统实绩导入'!$G$4:$R$1500)) | F5: =IF($B5="","",SUMPRODUCT(('系统实绩导入'!$B$4:$B$1500=$B5)*('系统实绩导入'!$C$4:$C$1500=$C5)*('系统实绩导入'!$D$4:$D$1500=$D5)*('系统实绩导入'!$F$4:$F$1500="实绩毛利")*('系统实绩导入'!$G$3:$R$3=$F$1)*'系统实绩导入'!$G$4:$R$1500)) | G5: =IF($B5="","",IFERROR(F5/E5,"")) | H5: =IF($B5="","",SUMPRODUCT(('目标填报'!$B$4:$B$1500=$B5)*('目标填报'!$C$4:$C$1500=$C5)*('目标填报'!$D$4:$D$1500=$D5)*('目标填报'!$F$4:$F$1500="销售目标额")*('目标填报'!$G$3:$R$3=$F$1)*'目标填报'!$G$4:$R$1500)) | I5: =IF($B5="","",IFERROR(E5/H5,"")) | J5: =IF($B5="","",SUMPRODUCT(('系统实绩导入'!$B$4:$B$1500=$B5)*('系统实绩导入'!$C$4:$C$1500=$C5)*('系统实绩导入'!$D$4:$D$1500=$D5)*('系统实绩导入'!$F$4:$F$1500="实绩销售额")*('系统实绩导入'!$G$3:$R$3<=$F$1)*'系统实绩导入'!$G$4:$R$1500)) | K5: =IF($B5="","",SUMPRODUCT(('系统实绩导入'!$B$4:$B$1500=$B5)*('系统实绩导入'!$C$4:$C$1500=$C5)*('系统实绩导入'!$D$4:$D$1500=$D5)*('系统实绩导入'!$F$4:$F$1500="实绩毛利")*('系统实绩导入'!$G$3:$R$3<=$F$1)*'系统实绩导入'!$G$4:$R$1500)) | L5: =IF($B5="","",IFERROR(K5/J5,"")) | M5: =IF($B5="","",SUMIFS('目标填报'!$S$4:$S$1500,'目标填报'!$B$4:$B$1500,$B5,'目标填报'!$C$4:$C$1500,$C5,'目标填报'!$D$4:$D$1500,$D5,'目标填报'!$F$4:$F$1500,"销售目标额")) | N5: =IF($B5="","",IFERROR(J5/M5,"")) | O5: =IF($B5="","",J5-M5) | P5: =IF($B5="","",SUMPRODUCT(('目标填报'!$B$4:$B$1500=$B5)*('目标填报'!$C$4:$C$1500=$C5)*('目标填报'!$D$4:$D$1500=$D5)*('目标填报'!$F$4:$F$1500="在手订单")*('目标填报'!$G$3:$R$3=$F$1)*'目标填报'!$G$4:$R$1500)) | Q5: =IF($B5="","",SUMPRODUCT(('目标填报'!$B$4:$B$1500=$B5)*('目标填报'!$C$4:$C$1500=$C5)*('目标填报'!$D$4:$D$1500=$D5)*('目标填报'!$F$4:$F$1500="在手订单目标")*('目标填报'!$G$3:$R$3=$F$1)*'目标填报'!$G$4:$R$1500)) | R5: =IF($B5="","",IFERROR(P5/Q5,"")) | S5: =IF($B5="","",SUMPRODUCT(('目标填报'!$B$4:$B$1500=$B5)*('目标填报'!$C$4:$C$1500=$C5)*('目标填报'!$D$4:$D$1500=$D5)*('目标填报'!$F$4:$F$1500="目标客户机会")*('目标填报'!$G$3:$R$3=$F$1)*'目标填报'!$G$4:$R$1500)) | T5: =IF($B5="","",SUMPRODUCT(('目标填报'!$B$4:$B$1500=$B5)*('目标填报'!$C$4:$C$1500=$C5)*('目标填报'!$D$4:$D$1500=$D5)*('目标填报'!$F$4:$F$1500="目标客户机会目标")*('目标填报'!$G$3:$R$3=$F$1)*'目标填报'!$G$4:$R$1500)) | U5: =IF($B5="","",IFERROR(S5/T5,"")) | V5: =IF($B5="","",P5+S5) | W5: =IF($B5="","",M5-J5) | X5: =IF($B5="","",IFERROR(V5/W5,"")) | Y5: =IF($B5="","",V5-W5)
A6: =IF($B6="","",ROW()-3) | B6: =IF(2+1>COUNTA('维度字典'!$C$2:$C$200)*COUNTA('维度字典'!$A$2:$A$200)*COUNTA('维度字典'!$E$2:$E$200),"",INDEX('维度字典'!$C$2:$C$200,MOD(INT(2/(COUNTA('维度字典'!$E$2:$E$200)*COUNTA('维度字典'!$A$2:$A$200))),COUNTA('维度字典'!$C$2:$C$200))+1)) | C6: =IF($B6="","",INDEX('维度字典'!$A$2:$A$200,MOD(INT(2/COUNTA('维度字典'!$E$2:$E$200)),COUNTA('维度字典'!$A$2:$A$200))+1)) | D6: =IF($B6="","",INDEX('维度字典'!$E$2:$E$200,MOD(2,COUNTA('维度字典'!$E$2:$E$200))+1)) | E6: =IF($B6="","",SUMPRODUCT(('系统实绩导入'!$B$4:$B$1500=$B6)*('系统实绩导入'!$C$4:$C$1500=$C6)*('系统实绩导入'!$D$4:$D$1500=$D6)*('系统实绩导入'!$F$4:$F$1500="实绩销售额")*('系统实绩导入'!$G$3:$R$3=$F$1)*'系统实绩导入'!$G$4:$R$1500)) | F6: =IF($B6="","",SUMPRODUCT(('系统实绩导入'!$B$4:$B$1500=$B6)*('系统实绩导入'!$C$4:$C$1500=$C6)*('系统实绩导入'!$D$4:$D$1500=$D6)*('系统实绩导入'!$F$4:$F$1500="实绩毛利")*('系统实绩导入'!$G$3:$R$3=$F$1)*'系统实绩导入'!$G$4:$R$1500)) | G6: =IF($B6="","",IFERROR(F6/E6,"")) | H6: =IF($B6="","",SUMPRODUCT(('目标填报'!$B$4:$B$1500=$B6)*('目标填报'!$C$4:$C$1500=$C6)*('目标填报'!$D$4:$D$1500=$D6)*('目标填报'!$F$4:$F$1500="销售目标额")*('目标填报'!$G$3:$R$3=$F$1)*'目标填报'!$G$4:$R$1500)) | I6: =IF($B6="","",IFERROR(E6/H6,"")) | J6: =IF($B6="","",SUMPRODUCT(('系统实绩导入'!$B$4:$B$1500=$B6)*('系统实绩导入'!$C$4:$C$1500=$C6)*('系统实绩导入'!$D$4:$D$1500=$D6)*('系统实绩导入'!$F$4:$F$1500="实绩销售额")*('系统实绩导入'!$G$3:$R$3<=$F$1)*'系统实绩导入'!$G$4:$R$1500)) | K6: =IF($B6="","",SUMPRODUCT(('系统实绩导入'!$B$4:$B$1500=$B6)*('系统实绩导入'!$C$4:$C$1500=$C6)*('系统实绩导入'!$D$4:$D$1500=$D6)*('系统实绩导入'!$F$4:$F$1500="实绩毛利")*('系统实绩导入'!$G$3:$R$3<=$F$1)*'系统实绩导入'!$G$4:$R$1500)) | L6: =IF($B6="","",IFERROR(K6/J6,"")) | M6: =IF($B6="","",SUMIFS('目标填报'!$S$4:$S$1500,'目标填报'!$B$4:$B$1500,$B6,'目标填报'!$C$4:$C$1500,$C6,'目标填报'!$D$4:$D$1500,$D6,'目标填报'!$F$4:$F$1500,"销售目标额")) | N6: =IF($B6="","",IFERROR(J6/M6,"")) | O6: =IF($B6="","",J6-M6) | P6: =IF($B6="","",SUMPRODUCT(('目标填报'!$B$4:$B$1500=$B6)*('目标填报'!$C$4:$C$1500=$C6)*('目标填报'!$D$4:$D$1500=$D6)*('目标填报'!$F$4:$F$1500="在手订单")*('目标填报'!$G$3:$R$3=$F$1)*'目标填报'!$G$4:$R$1500)) | Q6: =IF($B6="","",SUMPRODUCT(('目标填报'!$B$4:$B$1500=$B6)*('目标填报'!$C$4:$C$1500=$C6)*('目标填报'!$D$4:$D$1500=$D6)*('目标填报'!$F$4:$F$1500="在手订单目标")*('目标填报'!$G$3:$R$3=$F$1)*'目标填报'!$G$4:$R$1500)) | R6: =IF($B6="","",IFERROR(P6/Q6,"")) | S6: =IF($B6="","",SUMPRODUCT(('目标填报'!$B$4:$B$1500=$B6)*('目标填报'!$C$4:$C$1500=$C6)*('目标填报'!$D$4:$D$1500=$D6)*('目标填报'!$F$4:$F$1500="目标客户机会")*('目标填报'!$G$3:$R$3=$F$1)*'目标填报'!$G$4:$R$1500)) | T6: =IF($B6="","",SUMPRODUCT(('目标填报'!$B$4:$B$1500=$B6)*('目标填报'!$C$4:$C$1500=$C6)*('目标填报'!$D$4:$D$1500=$D6)*('目标填报'!$F$4:$F$1500="目标客户机会目标")*('目标填报'!$G$3:$R$3=$F$1)*'目标填报'!$G$4:$R$1500)) | U6: =IF($B6="","",IFERROR(S6/T6,"")) | V6: =IF($B6="","",P6+S6) | W6: =IF($B6="","",M6-J6) | X6: =IF($B6="","",IFERROR(V6/W6,"")) | Y6: =IF($B6="","",V6-W6)
A7: =IF($B7="","",ROW()-3) | B7: =IF(3+1>COUNTA('维度字典'!$C$2:$C$200)*COUNTA('维度字典'!$A$2:$A$200)*COUNTA('维度字典'!$E$2:$E$200),"",INDEX('维度字典'!$C$2:$C$200,MOD(INT(3/(COUNTA('维度字典'!$E$2:$E$200)*COUNTA('维度字典'!$A$2:$A$200))),COUNTA('维度字典'!$C$2:$C$200))+1)) | C7: =IF($B7="","",INDEX('维度字典'!$A$2:$A$200,MOD(INT(3/COUNTA('维度字典'!$E$2:$E$200)),COUNTA('维度字典'!$A$2:$A$200))+1)) | D7: =IF($B7="","",INDEX('维度字典'!$E$2:$E$200,MOD(3,COUNTA('维度字典'!$E$2:$E$200))+1)) | E7: =IF($B7="","",SUMPRODUCT(('系统实绩导入'!$B$4:$B$1500=$B7)*('系统实绩导入'!$C$4:$C$1500=$C7)*('系统实绩导入'!$D$4:$D$1500=$D7)*('系统实绩导入'!$F$4:$F$1500="实绩销售额")*('系统实绩导入'!$G$3:$R$3=$F$1)*'系统实绩导入'!$G$4:$R$1500)) | F7: =IF($B7="","",SUMPRODUCT(('系统实绩导入'!$B$4:$B$1500=$B7)*('系统实绩导入'!$C$4:$C$1500=$C7)*('系统实绩导入'!$D$4:$D$1500=$D7)*('系统实绩导入'!$F$4:$F$1500="实绩毛利")*('系统实绩导入'!$G$3:$R$3=$F$1)*'系统实绩导入'!$G$4:$R$1500)) | G7: =IF($B7="","",IFERROR(F7/E7,"")) | H7: =IF($B7="","",SUMPRODUCT(('目标填报'!$B$4:$B$1500=$B7)*('目标填报'!$C$4:$C$1500=$C7)*('目标填报'!$D$4:$D$1500=$D7)*('目标填报'!$F$4:$F$1500="销售目标额")*('目标填报'!$G$3:$R$3=$F$1)*'目标填报'!$G$4:$R$1500)) | I7: =IF($B7="","",IFERROR(E7/H7,"")) | J7: =IF($B7="","",SUMPRODUCT(('系统实绩导入'!$B$4:$B$1500=$B7)*('系统实绩导入'!$C$4:$C$1500=$C7)*('系统实绩导入'!$D$4:$D$1500=$D7)*('系统实绩导入'!$F$4:$F$1500="实绩销售额")*('系统实绩导入'!$G$3:$R$3<=$F$1)*'系统实绩导入'!$G$4:$R$1500)) | K7: =IF($B7="","",SUMPRODUCT(('系统实绩导入'!$B$4:$B$1500=$B7)*('系统实绩导入'!$C$4:$C$1500=$C7)*('系统实绩导入'!$D$4:$D$1500=$D7)*('系统实绩导入'!$F$4:$F$1500="实绩毛利")*('系统实绩导入'!$G$3:$R$3<=$F$1)*'系统实绩导入'!$G$4:$R$1500)) | L7: =IF($B7="","",IFERROR(K7/J7,"")) | M7: =IF($B7="","",SUMIFS('目标填报'!$S$4:$S$1500,'目标填报'!$B$4:$B$1500,$B7,'目标填报'!$C$4:$C$1500,$C7,'目标填报'!$D$4:$D$1500,$D7,'目标填报'!$F$4:$F$1500,"销售目标额")) | N7: =IF($B7="","",IFERROR(J7/M7,"")) | O7: =IF($B7="","",J7-M7) | P7: =IF($B7="","",SUMPRODUCT(('目标填报'!$B$4:$B$1500=$B7)*('目标填报'!$C$4:$C$1500=$C7)*('目标填报'!$D$4:$D$1500=$D7)*('目标填报'!$F$4:$F$1500="在手订单")*('目标填报'!$G$3:$R$3=$F$1)*'目标填报'!$G$4:$R$1500)) | Q7: =IF($B7="","",SUMPRODUCT(('目标填报'!$B$4:$B$1500=$B7)*('目标填报'!$C$4:$C$1500=$C7)*('目标填报'!$D$4:$D$1500=$D7)*('目标填报'!$F$4:$F$1500="在手订单目标")*('目标填报'!$G$3:$R$3=$F$1)*'目标填报'!$G$4:$R$1500)) | R7: =IF($B7="","",IFERROR(P7/Q7,"")) | S7: =IF($B7="","",SUMPRODUCT(('目标填报'!$B$4:$B$1500=$B7)*('目标填报'!$C$4:$C$1500=$C7)*('目标填报'!$D$4:$D$1500=$D7)*('目标填报'!$F$4:$F$1500="目标客户机会")*('目标填报'!$G$3:$R$3=$F$1)*'目标填报'!$G$4:$R$1500)) | T7: =IF($B7="","",SUMPRODUCT(('目标填报'!$B$4:$B$1500=$B7)*('目标填报'!$C$4:$C$1500=$C7)*('目标填报'!$D$4:$D$1500=$D7)*('目标填报'!$F$4:$F$1500="目标客户机会目标")*('目标填报'!$G$3:$R$3=$F$1)*'目标填报'!$G$4:$R$1500)) | U7: =IF($B7="","",IFERROR(S7/T7,"")) | V7: =IF($B7="","",P7+S7) | W7: =IF($B7="","",M7-J7) | X7: =IF($B7="","",IFERROR(V7/W7,"")) | Y7: =IF($B7="","",V7-W7)
A8: =IF($B8="","",ROW()-3) | B8: =IF(4+1>COUNTA('维度字典'!$C$2:$C$200)*COUNTA('维度字典'!$A$2:$A$200)*COUNTA('维度字典'!$E$2:$E$200),"",INDEX('维度字典'!$C$2:$C$200,MOD(INT(4/(COUNTA('维度字典'!$E$2:$E$200)*COUNTA('维度字典'!$A$2:$A$200))),COUNTA('维度字典'!$C$2:$C$200))+1)) | C8: =IF($B8="","",INDEX('维度字典'!$A$2:$A$200,MOD(INT(4/COUNTA('维度字典'!$E$2:$E$200)),COUNTA('维度字典'!$A$2:$A$200))+1)) | D8: =IF($B8="","",INDEX('维度字典'!$E$2:$E$200,MOD(4,COUNTA('维度字典'!$E$2:$E$200))+1)) | E8: =IF($B8="","",SUMPRODUCT(('系统实绩导入'!$B$4:$B$1500=$B8)*('系统实绩导入'!$C$4:$C$1500=$C8)*('系统实绩导入'!$D$4:$D$1500=$D8)*('系统实绩导入'!$F$4:$F$1500="实绩销售额")*('系统实绩导入'!$G$3:$R$3=$F$1)*'系统实绩导入'!$G$4:$R$1500)) | F8: =IF($B8="","",SUMPRODUCT(('系统实绩导入'!$B$4:$B$1500=$B8)*('系统实绩导入'!$C$4:$C$1500=$C8)*('系统实绩导入'!$D$4:$D$1500=$D8)*('系统实绩导入'!$F$4:$F$1500="实绩毛利")*('系统实绩导入'!$G$3:$R$3=$F$1)*'系统实绩导入'!$G$4:$R$1500)) | G8: =IF($B8="","",IFERROR(F8/E8,"")) | H8: =IF($B8="","",SUMPRODUCT(('目标填报'!$B$4:$B$1500=$B8)*('目标填报'!$C$4:$C$1500=$C8)*('目标填报'!$D$4:$D$1500=$D8)*('目标填报'!$F$4:$F$1500="销售目标额")*('目标填报'!$G$3:$R$3=$F$1)*'目标填报'!$G$4:$R$1500)) | I8: =IF($B8="","",IFERROR(E8/H8,"")) | J8: =IF($B8="","",SUMPRODUCT(('系统实绩导入'!$B$4:$B$1500=$B8)*('系统实绩导入'!$C$4:$C$1500=$C8)*('系统实绩导入'!$D$4:$D$1500=$D8)*('系统实绩导入'!$F$4:$F$1500="实绩销售额")*('系统实绩导入'!$G$3:$R$3<=$F$1)*'系统实绩导入'!$G$4:$R$1500)) | K8: =IF($B8="","",SUMPRODUCT(('系统实绩导入'!$B$4:$B$1500=$B8)*('系统实绩导入'!$C$4:$C$1500=$C8)*('系统实绩导入'!$D$4:$D$1500=$D8)*('系统实绩导入'!$F$4:$F$1500="实绩毛利")*('系统实绩导入'!$G$3:$R$3<=$F$1)*'系统实绩导入'!$G$4:$R$1500)) | L8: =IF($B8="","",IFERROR(K8/J8,"")) | M8: =IF($B8="","",SUMIFS('目标填报'!$S$4:$S$1500,'目标填报'!$B$4:$B$1500,$B8,'目标填报'!$C$4:$C$1500,$C8,'目标填报'!$D$4:$D$1500,$D8,'目标填报'!$F$4:$F$1500,"销售目标额")) | N8: =IF($B8="","",IFERROR(J8/M8,"")) | O8: =IF($B8="","",J8-M8) | P8: =IF($B8="","",SUMPRODUCT(('目标填报'!$B$4:$B$1500=$B8)*('目标填报'!$C$4:$C$1500=$C8)*('目标填报'!$D$4:$D$1500=$D8)*('目标填报'!$F$4:$F$1500="在手订单")*('目标填报'!$G$3:$R$3=$F$1)*'目标填报'!$G$4:$R$1500)) | Q8: =IF($B8="","",SUMPRODUCT(('目标填报'!$B$4:$B$1500=$B8)*('目标填报'!$C$4:$C$1500=$C8)*('目标填报'!$D$4:$D$1500=$D8)*('目标填报'!$F$4:$F$1500="在手订单目标")*('目标填报'!$G$3:$R$3=$F$1)*'目标填报'!$G$4:$R$1500)) | R8: =IF($B8="","",IFERROR(P8/Q8,"")) | S8: =IF($B8="","",SUMPRODUCT(('目标填报'!$B$4:$B$1500=$B8)*('目标填报'!$C$4:$C$1500=$C8)*('目标填报'!$D$4:$D$1500=$D8)*('目标填报'!$F$4:$F$1500="目标客户机会")*('目标填报'!$G$3:$R$3=$F$1)*'目标填报'!$G$4:$R$1500)) | T8: =IF($B8="","",SUMPRODUCT(('目标填报'!$B$4:$B$1500=$B8)*('目标填报'!$C$4:$C$1500=$C8)*('目标填报'!$D$4:$D$1500=$D8)*('目标填报'!$F$4:$F$1500="目标客户机会目标")*('目标填报'!$G$3:$R$3=$F$1)*'目标填报'!$G$4:$R$1500)) | U8: =IF($B8="","",IFERROR(S8/T8,"")) | V8: =IF($B8="","",P8+S8) | W8: =IF($B8="","",M8-J8) | X8: =IF($B8="","",IFERROR(V8/W8,"")) | Y8: =IF($B8="","",V8-W8)
A9: =IF($B9="","",ROW()-3) | B9: =IF(5+1>COUNTA('维度字典'!$C$2:$C$200)*COUNTA('维度字典'!$A$2:$A$200)*COUNTA('维度字典'!$E$2:$E$200),"",INDEX('维度字典'!$C$2:$C$200,MOD(INT(5/(COUNTA('维度字典'!$E$2:$E$200)*COUNTA('维度字典'!$A$2:$A$200))),COUNTA('维度字典'!$C$2:$C$200))+1)) | C9: =IF($B9="","",INDEX('维度字典'!$A$2:$A$200,MOD(INT(5/COUNTA('维度字典'!$E$2:$E$200)),COUNTA('维度字典'!$A$2:$A$200))+1)) | D9: =IF($B9="","",INDEX('维度字典'!$E$2:$E$200,MOD(5,COUNTA('维度字典'!$E$2:$E$200))+1)) | E9: =IF($B9="","",SUMPRODUCT(('系统实绩导入'!$B$4:$B$1500=$B9)*('系统实绩导入'!$C$4:$C$1500=$C9)*('系统实绩导入'!$D$4:$D$1500=$D9)*('系统实绩导入'!$F$4:$F$1500="实绩销售额")*('系统实绩导入'!$G$3:$R$3=$F$1)*'系统实绩导入'!$G$4:$R$1500)) | F9: =IF($B9="","",SUMPRODUCT(('系统实绩导入'!$B$4:$B$1500=$B9)*('系统实绩导入'!$C$4:$C$1500=$C9)*('系统实绩导入'!$D$4:$D$1500=$D9)*('系统实绩导入'!$F$4:$F$1500="实绩毛利")*('系统实绩导入'!$G$3:$R$3=$F$1)*'系统实绩导入'!$G$4:$R$1500)) | G9: =IF($B9="","",IFERROR(F9/E9,"")) | H9: =IF($B9="","",SUMPRODUCT(('目标填报'!$B$4:$B$1500=$B9)*('目标填报'!$C$4:$C$1500=$C9)*('目标填报'!$D$4:$D$1500=$D9)*('目标填报'!$F$4:$F$1500="销售目标额")*('目标填报'!$G$3:$R$3=$F$1)*'目标填报'!$G$4:$R$1500)) | I9: =IF($B9="","",IFERROR(E9/H9,"")) | J9: =IF($B9="","",SUMPRODUCT(('系统实绩导入'!$B$4:$B$1500=$B9)*('系统实绩导入'!$C$4:$C$1500=$C9)*('系统实绩导入'!$D$4:$D$1500=$D9)*('系统实绩导入'!$F$4:$F$1500="实绩销售额")*('系统实绩导入'!$G$3:$R$3<=$F$1)*'系统实绩导入'!$G$4:$R$1500)) | K9: =IF($B9="","",SUMPRODUCT(('系统实绩导入'!$B$4:$B$1500=$B9)*('系统实绩导入'!$C$4:$C$1500=$C9)*('系统实绩导入'!$D$4:$D$1500=$D9)*('系统实绩导入'!$F$4:$F$1500="实绩毛利")*('系统实绩导入'!$G$3:$R$3<=$F$1)*'系统实绩导入'!$G$4:$R$1500)) | L9: =IF($B9="","",IFERROR(K9/J9,"")) | M9: =IF($B9="","",SUMIFS('目标填报'!$S$4:$S$1500,'目标填报'!$B$4:$B$1500,$B9,'目标填报'!$C$4:$C$1500,$C9,'目标填报'!$D$4:$D$1500,$D9,'目标填报'!$F$4:$F$1500,"销售目标额")) | N9: =IF($B9="","",IFERROR(J9/M9,"")) | O9: =IF($B9="","",J9-M9) | P9: =IF($B9="","",SUMPRODUCT(('目标填报'!$B$4:$B$1500=$B9)*('目标填报'!$C$4:$C$1500=$C9)*('目标填报'!$D$4:$D$1500=$D9)*('目标填报'!$F$4:$F$1500="在手订单")*('目标填报'!$G$3:$R$3=$F$1)*'目标填报'!$G$4:$R$1500)) | Q9: =IF($B9="","",SUMPRODUCT(('目标填报'!$B$4:$B$1500=$B9)*('目标填报'!$C$4:$C$1500=$C9)*('目标填报'!$D$4:$D$1500=$D9)*('目标填报'!$F$4:$F$1500="在手订单目标")*('目标填报'!$G$3:$R$3=$F$1)*'目标填报'!$G$4:$R$1500)) | R9: =IF($B9="","",IFERROR(P9/Q9,"")) | S9: =IF($B9="","",SUMPRODUCT(('目标填报'!$B$4:$B$1500=$B9)*('目标填报'!$C$4:$C$1500=$C9)*('目标填报'!$D$4:$D$1500=$D9)*('目标填报'!$F$4:$F$1500="目标客户机会")*('目标填报'!$G$3:$R$3=$F$1)*'目标填报'!$G$4:$R$1500)) | T9: =IF($B9="","",SUMPRODUCT(('目标填报'!$B$4:$B$1500=$B9)*('目标填报'!$C$4:$C$1500=$C9)*('目标填报'!$D$4:$D$1500=$D9)*('目标填报'!$F$4:$F$1500="目标客户机会目标")*('目标填报'!$G$3:$R$3=$F$1)*'目标填报'!$G$4:$R$1500)) | U9: =IF($B9="","",IFERROR(S9/T9,"")) | V9: =IF($B9="","",P9+S9) | W9: =IF($B9="","",M9-J9) | X9: =IF($B9="","",IFERROR(V9/W9,"")) | Y9: =IF($B9="","",V9-W9)
A10: =IF($B10="","",ROW()-3) | B10: =IF(6+1>COUNTA('维度字典'!$C$2:$C$200)*COUNTA('维度字典'!$A$2:$A$200)*COUNTA('维度字典'!$E$2:$E$200),"",INDEX('维度字典'!$C$2:$C$200,MOD(INT(6/(COUNTA('维度字典'!$E$2:$E$200)*COUNTA('维度字典'!$A$2:$A$200))),COUNTA('维度字典'!$C$2:$C$200))+1)) | C10: =IF($B10="","",INDEX('维度字典'!$A$2:$A$200,MOD(INT(6/COUNTA('维度字典'!$E$2:$E$200)),COUNTA('维度字典'!$A$2:$A$200))+1)) | D10: =IF($B10="","",INDEX('维度字典'!$E$2:$E$200,MOD(6,COUNTA('维度字典'!$E$2:$E$200))+1)) | E10: =IF($B10="","",SUMPRODUCT(('系统实绩导入'!$B$4:$B$1500=$B10)*('系统实绩导入'!$C$4:$C$1500=$C10)*('系统实绩导入'!$D$4:$D$1500=$D10)*('系统实绩导入'!$F$4:$F$1500="实绩销售额")*('系统实绩导入'!$G$3:$R$3=$F$1)*'系统实绩导入'!$G$4:$R$1500)) | F10: =IF($B10="","",SUMPRODUCT(('系统实绩导入'!$B$4:$B$1500=$B10)*('系统实绩导入'!$C$4:$C$1500=$C10)*('系统实绩导入'!$D$4:$D$1500=$D10)*('系统实绩导入'!$F$4:$F$1500="实绩毛利")*('系统实绩导入'!$G$3:$R$3=$F$1)*'系统实绩导入'!$G$4:$R$1500)) | G10: =IF($B10="","",IFERROR(F10/E10,"")) | H10: =IF($B10="","",SUMPRODUCT(('目标填报'!$B$4:$B$1500=$B10)*('目标填报'!$C$4:$C$1500=$C10)*('目标填报'!$D$4:$D$1500=$D10)*('目标填报'!$F$4:$F$1500="销售目标额")*('目标填报'!$G$3:$R$3=$F$1)*'目标填报'!$G$4:$R$1500)) | I10: =IF($B10="","",IFERROR(E10/H10,"")) | J10: =IF($B10="","",SUMPRODUCT(('系统实绩导入'!$B$4:$B$1500=$B10)*('系统实绩导入'!$C$4:$C$1500=$C10)*('系统实绩导入'!$D$4:$D$1500=$D10)*('系统实绩导入'!$F$4:$F$1500="实绩销售额")*('系统实绩导入'!$G$3:$R$3<=$F$1)*'系统实绩导入'!$G$4:$R$1500)) | K10: =IF($B10="","",SUMPRODUCT(('系统实绩导入'!$B$4:$B$1500=$B10)*('系统实绩导入'!$C$4:$C$1500=$C10)*('系统实绩导入'!$D$4:$D$1500=$D10)*('系统实绩导入'!$F$4:$F$1500="实绩毛利")*('系统实绩导入'!$G$3:$R$3<=$F$1)*'系统实绩导入'!$G$4:$R$1500)) | L10: =IF($B10="","",IFERROR(K10/J10,"")) | M10: =IF($B10="","",SUMIFS('目标填报'!$S$4:$S$1500,'目标填报'!$B$4:$B$1500,$B10,'目标填报'!$C$4:$C$1500,$C10,'目标填报'!$D$4:$D$1500,$D10,'目标填报'!$F$4:$F$1500,"销售目标额")) | N10: =IF($B10="","",IFERROR(J10/M10,"")) | O10: =IF($B10="","",J10-M10) | P10: =IF($B10="","",SUMPRODUCT(('目标填报'!$B$4:$B$1500=$B10)*('目标填报'!$C$4:$C$1500=$C10)*('目标填报'!$D$4:$D$1500=$D10)*('目标填报'!$F$4:$F$1500="在手订单")*('目标填报'!$G$3:$R$3=$F$1)*'目标填报'!$G$4:$R$1500)) | Q10: =IF($B10="","",SUMPRODUCT(('目标填报'!$B$4:$B$1500=$B10)*('目标填报'!$C$4:$C$1500=$C10)*('目标填报'!$D$4:$D$1500=$D10)*('目标填报'!$F$4:$F$1500="在手订单目标")*('目标填报'!$G$3:$R$3=$F$1)*'目标填报'!$G$4:$R$1500)) | R10: =IF($B10="","",IFERROR(P10/Q10,"")) | S10: =IF($B10="","",SUMPRODUCT(('目标填报'!$B$4:$B$1500=$B10)*('目标填报'!$C$4:$C$1500=$C10)*('目标填报'!$D$4:$D$1500=$D10)*('目标填报'!$F$4:$F$1500="目标客户机会")*('目标填报'!$G$3:$R$3=$F$1)*'目标填报'!$G$4:$R$1500)) | T10: =IF($B10="","",SUMPRODUCT(('目标填报'!$B$4:$B$1500=$B10)*('目标填报'!$C$4:$C$1500=$C10)*('目标填报'!$D$4:$D$1500=$D10)*('目标填报'!$F$4:$F$1500="目标客户机会目标")*('目标填报'!$G$3:$R$3=$F$1)*'目标填报'!$G$4:$R$1500)) | U10: =IF($B10="","",IFERROR(S10/T10,"")) | V10: =IF($B10="","",P10+S10) | W10: =IF($B10="","",M10-J10) | X10: =IF($B10="","",IFERROR(V10/W10,"")) | Y10: =IF($B10="","",V10-W10)
A11: =IF($B11="","",ROW()-3) | B11: =IF(7+1>COUNTA('维度字典'!$C$2:$C$200)*COUNTA('维度字典'!$A$2:$A$200)*COUNTA('维度字典'!$E$2:$E$200),"",INDEX('维度字典'!$C$2:$C$200,MOD(INT(7/(COUNTA('维度字典'!$E$2:$E$200)*COUNTA('维度字典'!$A$2:$A$200))),COUNTA('维度字典'!$C$2:$C$200))+1)) | C11: =IF($B11="","",INDEX('维度字典'!$A$2:$A$200,MOD(INT(7/COUNTA('维度字典'!$E$2:$E$200)),COUNTA('维度字典'!$A$2:$A$200))+1)) | D11: =IF($B11="","",INDEX('维度字典'!$E$2:$E$200,MOD(7,COUNTA('维度字典'!$E$2:$E$200))+1)) | E11: =IF($B11="","",SUMPRODUCT(('系统实绩导入'!$B$4:$B$1500=$B11)*('系统实绩导入'!$C$4:$C$1500=$C11)*('系统实绩导入'!$D$4:$D$1500=$D11)*('系统实绩导入'!$F$4:$F$1500="实绩销售额")*('系统实绩导入'!$G$3:$R$3=$F$1)*'系统实绩导入'!$G$4:$R$1500)) | F11: =IF($B11="","",SUMPRODUCT(('系统实绩导入'!$B$4:$B$1500=$B11)*('系统实绩导入'!$C$4:$C$1500=$C11)*('系统实绩导入'!$D$4:$D$1500=$D11)*('系统实绩导入'!$F$4:$F$1500="实绩毛利")*('系统实绩导入'!$G$3:$R$3=$F$1)*'系统实绩导入'!$G$4:$R$1500)) | G11: =IF($B11="","",IFERROR(F11/E11,"")) | H11: =IF($B11="","",SUMPRODUCT(('目标填报'!$B$4:$B$1500=$B11)*('目标填报'!$C$4:$C$1500=$C11)*('目标填报'!$D$4:$D$1500=$D11)*('目标填报'!$F$4:$F$1500="销售目标额")*('目标填报'!$G$3:$R$3=$F$1)*'目标填报'!$G$4:$R$1500)) | I11: =IF($B11="","",IFERROR(E11/H11,"")) | J11: =IF($B11="","",SUMPRODUCT(('系统实绩导入'!$B$4:$B$1500=$B11)*('系统实绩导入'!$C$4:$C$1500=$C11)*('系统实绩导入'!$D$4:$D$1500=$D11)*('系统实绩导入'!$F$4:$F$1500="实绩销售额")*('系统实绩导入'!$G$3:$R$3<=$F$1)*'系统实绩导入'!$G$4:$R$1500)) | K11: =IF($B11="","",SUMPRODUCT(('系统实绩导入'!$B$4:$B$1500=$B11)*('系统实绩导入'!$C$4:$C$1500=$C11)*('系统实绩导入'!$D$4:$D$1500=$D11)*('系统实绩导入'!$F$4:$F$1500="实绩毛利")*('系统实绩导入'!$G$3:$R$3<=$F$1)*'系统实绩导入'!$G$4:$R$1500)) | L11: =IF($B11="","",IFERROR(K11/J11,"")) | M11: =IF($B11="","",SUMIFS('目标填报'!$S$4:$S$1500,'目标填报'!$B$4:$B$1500,$B11,'目标填报'!$C$4:$C$1500,$C11,'目标填报'!$D$4:$D$1500,$D11,'目标填报'!$F$4:$F$1500,"销售目标额")) | N11: =IF($B11="","",IFERROR(J11/M11,"")) | O11: =IF($B11="","",J11-M11) | P11: =IF($B11="","",SUMPRODUCT(('目标填报'!$B$4:$B$1500=$B11)*('目标填报'!$C$4:$C$1500=$C11)*('目标填报'!$D$4:$D$1500=$D11)*('目标填报'!$F$4:$F$1500="在手订单")*('目标填报'!$G$3:$R$3=$F$1)*'目标填报'!$G$4:$R$1500)) | Q11: =IF($B11="","",SUMPRODUCT(('目标填报'!$B$4:$B$1500=$B11)*('目标填报'!$C$4:$C$1500=$C11)*('目标填报'!$D$4:$D$1500=$D11)*('目标填报'!$F$4:$F$1500="在手订单目标")*('目标填报'!$G$3:$R$3=$F$1)*'目标填报'!$G$4:$R$1500)) | R11: =IF($B11="","",IFERROR(P11/Q11,"")) | S11: =IF($B11="","",SUMPRODUCT(('目标填报'!$B$4:$B$1500=$B11)*('目标填报'!$C$4:$C$1500=$C11)*('目标填报'!$D$4:$D$1500=$D11)*('目标填报'!$F$4:$F$1500="目标客户机会")*('目标填报'!$G$3:$R$3=$F$1)*'目标填报'!$G$4:$R$1500)) | T11: =IF($B11="","",SUMPRODUCT(('目标填报'!$B$4:$B$1500=$B11)*('目标填报'!$C$4:$C$1500=$C11)*('目标填报'!$D$4:$D$1500=$D11)*('目标填报'!$F$4:$F$1500="目标客户机会目标")*('目标填报'!$G$3:$R$3=$F$1)*'目标填报'!$G$4:$R$1500)) | U11: =IF($B11="","",IFERROR(S11/T11,"")) | V11: =IF($B11="","",P11+S11) | W11: =IF($B11="","",M11-J11) | X11: =IF($B11="","",IFERROR(V11/W11,"")) | Y11: =IF($B11="","",V11-W11)
A12: =IF($B12="","",ROW()-3) | B12: =IF(8+1>COUNTA('维度字典'!$C$2:$C$200)*COUNTA('维度字典'!$A$2:$A$200)*COUNTA('维度字典'!$E$2:$E$200),"",INDEX('维度字典'!$C$2:$C$200,MOD(INT(8/(COUNTA('维度字典'!$E$2:$E$200)*COUNTA('维度字典'!$A$2:$A$200))),COUNTA('维度字典'!$C$2:$C$200))+1)) | C12: =IF($B12="","",INDEX('维度字典'!$A$2:$A$200,MOD(INT(8/COUNTA('维度字典'!$E$2:$E$200)),COUNTA('维度字典'!$A$2:$A$200))+1)) | D12: =IF($B12="","",INDEX('维度字典'!$E$2:$E$200,MOD(8,COUNTA('维度字典'!$E$2:$E$200))+1)) | E12: =IF($B12="","",SUMPRODUCT(('系统实绩导入'!$B$4:$B$1500=$B12)*('系统实绩导入'!$C$4:$C$1500=$C12)*('系统实绩导入'!$D$4:$D$1500=$D12)*('系统实绩导入'!$F$4:$F$1500="实绩销售额")*('系统实绩导入'!$G$3:$R$3=$F$1)*'系统实绩导入'!$G$4:$R$1500)) | F12: =IF($B12="","",SUMPRODUCT(('系统实绩导入'!$B$4:$B$1500=$B12)*('系统实绩导入'!$C$4:$C$1500=$C12)*('系统实绩导入'!$D$4:$D$1500=$D12)*('系统实绩导入'!$F$4:$F$1500="实绩毛利")*('系统实绩导入'!$G$3:$R$3=$F$1)*'系统实绩导入'!$G$4:$R$1500)) | G12: =IF($B12="","",IFERROR(F12/E12,"")) | H12: =IF($B12="","",SUMPRODUCT(('目标填报'!$B$4:$B$1500=$B12)*('目标填报'!$C$4:$C$1500=$C12)*('目标填报'!$D$4:$D$1500=$D12)*('目标填报'!$F$4:$F$1500="销售目标额")*('目标填报'!$G$3:$R$3=$F$1)*'目标填报'!$G$4:$R$1500)) | I12: =IF($B12="","",IFERROR(E12/H12,"")) | J12: =IF($B12="","",SUMPRODUCT(('系统实绩导入'!$B$4:$B$1500=$B12)*('系统实绩导入'!$C$4:$C$1500=$C12)*('系统实绩导入'!$D$4:$D$1500=$D12)*('系统实绩导入'!$F$4:$F$1500="实绩销售额")*('系统实绩导入'!$G$3:$R$3<=$F$1)*'系统实绩导入'!$G$4:$R$1500)) | K12: =IF($B12="","",SUMPRODUCT(('系统实绩导入'!$B$4:$B$1500=$B12)*('系统实绩导入'!$C$4:$C$1500=$C12)*('系统实绩导入'!$D$4:$D$1500=$D12)*('系统实绩导入'!$F$4:$F$1500="实绩毛利")*('系统实绩导入'!$G$3:$R$3<=$F$1)*'系统实绩导入'!$G$4:$R$1500)) | L12: =IF($B12="","",IFERROR(K12/J12,"")) | M12: =IF($B12="","",SUMIFS('目标填报'!$S$4:$S$1500,'目标填报'!$B$4:$B$1500,$B12,'目标填报'!$C$4:$C$1500,$C12,'目标填报'!$D$4:$D$1500,$D12,'目标填报'!$F$4:$F$1500,"销售目标额")) | N12: =IF($B12="","",IFERROR(J12/M12,"")) | O12: =IF($B12="","",J12-M12) | P12: =IF($B12="","",SUMPRODUCT(('目标填报'!$B$4:$B$1500=$B12)*('目标填报'!$C$4:$C$1500=$C12)*('目标填报'!$D$4:$D$1500=$D12)*('目标填报'!$F$4:$F$1500="在手订单")*('目标填报'!$G$3:$R$3=$F$1)*'目标填报'!$G$4:$R$1500)) | Q12: =IF($B12="","",SUMPRODUCT(('目标填报'!$B$4:$B$1500=$B12)*('目标填报'!$C$4:$C$1500=$C12)*('目标填报'!$D$4:$D$1500=$D12)*('目标填报'!$F$4:$F$1500="在手订单目标")*('目标填报'!$G$3:$R$3=$F$1)*'目标填报'!$G$4:$R$1500)) | R12: =IF($B12="","",IFERROR(P12/Q12,"")) | S12: =IF($B12="","",SUMPRODUCT(('目标填报'!$B$4:$B$1500=$B12)*('目标填报'!$C$4:$C$1500=$C12)*('目标填报'!$D$4:$D$1500=$D12)*('目标填报'!$F$4:$F$1500="目标客户机会")*('目标填报'!$G$3:$R$3=$F$1)*'目标填报'!$G$4:$R$1500)) | T12: =IF($B12="","",SUMPRODUCT(('目标填报'!$B$4:$B$1500=$B12)*('目标填报'!$C$4:$C$1500=$C12)*('目标填报'!$D$4:$D$1500=$D12)*('目标填报'!$F$4:$F$1500="目标客户机会目标")*('目标填报'!$G$3:$R$3=$F$1)*'目标填报'!$G$4:$R$1500)) | U12: =IF($B12="","",IFERROR(S12/T12,"")) | V12: =IF($B12="","",P12+S12) | W12: =IF($B12="","",M12-J12) | X12: =IF($B12="","",IFERROR(V12/W12,"")) | Y12: =IF($B12="","",V12-W12)
A13: =IF($B13="","",ROW()-3) | B13: =IF(9+1>COUNTA('维度字典'!$C$2:$C$200)*COUNTA('维度字典'!$A$2:$A$200)*COUNTA('维度字典'!$E$2:$E$200),"",INDEX('维度字典'!$C$2:$C$200,MOD(INT(9/(COUNTA('维度字典'!$E$2:$E$200)*COUNTA('维度字典'!$A$2:$A$200))),COUNTA('维度字典'!$C$2:$C$200))+1)) | C13: =IF($B13="","",INDEX('维度字典'!$A$2:$A$200,MOD(INT(9/COUNTA('维度字典'!$E$2:$E$200)),COUNTA('维度字典'!$A$2:$A$200))+1)) | D13: =IF($B13="","",INDEX('维度字典'!$E$2:$E$200,MOD(9,COUNTA('维度字典'!$E$2:$E$200))+1)) | E13: =IF($B13="","",SUMPRODUCT(('系统实绩导入'!$B$4:$B$1500=$B13)*('系统实绩导入'!$C$4:$C$1500=$C13)*('系统实绩导入'!$D$4:$D$1500=$D13)*('系统实绩导入'!$F$4:$F$1500="实绩销售额")*('系统实绩导入'!$G$3:$R$3=$F$1)*'系统实绩导入'!$G$4:$R$1500)) | F13: =IF($B13="","",SUMPRODUCT(('系统实绩导入'!$B$4:$B$1500=$B13)*('系统实绩导入'!$C$4:$C$1500=$C13)*('系统实绩导入'!$D$4:$D$1500=$D13)*('系统实绩导入'!$F$4:$F$1500="实绩毛利")*('系统实绩导入'!$G$3:$R$3=$F$1)*'系统实绩导入'!$G$4:$R$1500)) | G13: =IF($B13="","",IFERROR(F13/E13,"")) | H13: =IF($B13="","",SUMPRODUCT(('目标填报'!$B$4:$B$1500=$B13)*('目标填报'!$C$4:$C$1500=$C13)*('目标填报'!$D$4:$D$1500=$D13)*('目标填报'!$F$4:$F$1500="销售目标额")*('目标填报'!$G$3:$R$3=$F$1)*'目标填报'!$G$4:$R$1500)) | I13: =IF($B13="","",IFERROR(E13/H13,"")) | J13: =IF($B13="","",SUMPRODUCT(('系统实绩导入'!$B$4:$B$1500=$B13)*('系统实绩导入'!$C$4:$C$1500=$C13)*('系统实绩导入'!$D$4:$D$1500=$D13)*('系统实绩导入'!$F$4:$F$1500="实绩销售额")*('系统实绩导入'!$G$3:$R$3<=$F$1)*'系统实绩导入'!$G$4:$R$1500)) | K13: =IF($B13="","",SUMPRODUCT(('系统实绩导入'!$B$4:$B$1500=$B13)*('系统实绩导入'!$C$4:$C$1500=$C13)*('系统实绩导入'!$D$4:$D$1500=$D13)*('系统实绩导入'!$F$4:$F$1500="实绩毛利")*('系统实绩导入'!$G$3:$R$3<=$F$1)*'系统实绩导入'!$G$4:$R$1500)) | L13: =IF($B13="","",IFERROR(K13/J13,"")) | M13: =IF($B13="","",SUMIFS('目标填报'!$S$4:$S$1500,'目标填报'!$B$4:$B$1500,$B13,'目标填报'!$C$4:$C$1500,$C13,'目标填报'!$D$4:$D$1500,$D13,'目标填报'!$F$4:$F$1500,"销售目标额")) | N13: =IF($B13="","",IFERROR(J13/M13,"")) | O13: =IF($B13="","",J13-M13) | P13: =IF($B13="","",SUMPRODUCT(('目标填报'!$B$4:$B$1500=$B13)*('目标填报'!$C$4:$C$1500=$C13)*('目标填报'!$D$4:$D$1500=$D13)*('目标填报'!$F$4:$F$1500="在手订单")*('目标填报'!$G$3:$R$3=$F$1)*'目标填报'!$G$4:$R$1500)) | Q13: =IF($B13="","",SUMPRODUCT(('目标填报'!$B$4:$B$1500=$B13)*('目标填报'!$C$4:$C$1500=$C13)*('目标填报'!$D$4:$D$1500=$D13)*('目标填报'!$F$4:$F$1500="在手订单目标")*('目标填报'!$G$3:$R$3=$F$1)*'目标填报'!$G$4:$R$1500)) | R13: =IF($B13="","",IFERROR(P13/Q13,"")) | S13: =IF($B13="","",SUMPRODUCT(('目标填报'!$B$4:$B$1500=$B13)*('目标填报'!$C$4:$C$1500=$C13)*('目标填报'!$D$4:$D$1500=$D13)*('目标填报'!$F$4:$F$1500="目标客户机会")*('目标填报'!$G$3:$R$3=$F$1)*'目标填报'!$G$4:$R$1500)) | T13: =IF($B13="","",SUMPRODUCT(('目标填报'!$B$4:$B$1500=$B13)*('目标填报'!$C$4:$C$1500=$C13)*('目标填报'!$D$4:$D$1500=$D13)*('目标填报'!$F$4:$F$1500="目标客户机会目标")*('目标填报'!$G$3:$R$3=$F$1)*'目标填报'!$G$4:$R$1500)) | U13: =IF($B13="","",IFERROR(S13/T13,"")) | V13: =IF($B13="","",P13+S13) | W13: =IF($B13="","",M13-J13) | X13: =IF($B13="","",IFERROR(V13/W13,"")) | Y13: =IF($B13="","",V13-W13)
A14: =IF($B14="","",ROW()-3) | B14: =IF(10+1>COUNTA('维度字典'!$C$2:$C$200)*COUNTA('维度字典'!$A$2:$A$200)*COUNTA('维度字典'!$E$2:$E$200),"",INDEX('维度字典'!$C$2:$C$200,MOD(INT(10/(COUNTA('维度字典'!$E$2:$E$200)*COUNTA('维度字典'!$A$2:$A$200))),COUNTA('维度字典'!$C$2:$C$200))+1)) | C14: =IF($B14="","",INDEX('维度字典'!$A$2:$A$200,MOD(INT(10/COUNTA('维度字典'!$E$2:$E$200)),COUNTA('维度字典'!$A$2:$A$200))+1)) | D14: =IF($B14="","",INDEX('维度字典'!$E$2:$E$200,MOD(10,COUNTA('维度字典'!$E$2:$E$200))+1)) | E14: =IF($B14="","",SUMPRODUCT(('系统实绩导入'!$B$4:$B$1500=$B14)*('系统实绩导入'!$C$4:$C$1500=$C14)*('系统实绩导入'!$D$4:$D$1500=$D14)*('系统实绩导入'!$F$4:$F$1500="实绩销售额")*('系统实绩导入'!$G$3:$R$3=$F$1)*'系统实绩导入'!$G$4:$R$1500)) | F14: =IF($B14="","",SUMPRODUCT(('系统实绩导入'!$B$4:$B$1500=$B14)*('系统实绩导入'!$C$4:$C$1500=$C14)*('系统实绩导入'!$D$4:$D$1500=$D14)*('系统实绩导入'!$F$4:$F$1500="实绩毛利")*('系统实绩导入'!$G$3:$R$3=$F$1)*'系统实绩导入'!$G$4:$R$1500)) | G14: =IF($B14="","",IFERROR(F14/E14,"")) | H14: =IF($B14="","",SUMPRODUCT(('目标填报'!$B$4:$B$1500=$B14)*('目标填报'!$C$4:$C$1500=$C14)*('目标填报'!$D$4:$D$1500=$D14)*('目标填报'!$F$4:$F$1500="销售目标额")*('目标填报'!$G$3:$R$3=$F$1)*'目标填报'!$G$4:$R$1500)) | I14: =IF($B14="","",IFERROR(E14/H14,"")) | J14: =IF($B14="","",SUMPRODUCT(('系统实绩导入'!$B$4:$B$1500=$B14)*('系统实绩导入'!$C$4:$C$1500=$C14)*('系统实绩导入'!$D$4:$D$1500=$D14)*('系统实绩导入'!$F$4:$F$1500="实绩销售额")*('系统实绩导入'!$G$3:$R$3<=$F$1)*'系统实绩导入'!$G$4:$R$1500)) | K14: =IF($B14="","",SUMPRODUCT(('系统实绩导入'!$B$4:$B$1500=$B14)*('系统实绩导入'!$C$4:$C$1500=$C14)*('系统实绩导入'!$D$4:$D$1500=$D14)*('系统实绩导入'!$F$4:$F$1500="实绩毛利")*('系统实绩导入'!$G$3:$R$3<=$F$1)*'系统实绩导入'!$G$4:$R$1500)) | L14: =IF($B14="","",IFERROR(K14/J14,"")) | M14: =IF($B14="","",SUMIFS('目标填报'!$S$4:$S$1500,'目标填报'!$B$4:$B$1500,$B14,'目标填报'!$C$4:$C$1500,$C14,'目标填报'!$D$4:$D$1500,$D14,'目标填报'!$F$4:$F$1500,"销售目标额")) | N14: =IF($B14="","",IFERROR(J14/M14,"")) | O14: =IF($B14="","",J14-M14) | P14: =IF($B14="","",SUMPRODUCT(('目标填报'!$B$4:$B$1500=$B14)*('目标填报'!$C$4:$C$1500=$C14)*('目标填报'!$D$4:$D$1500=$D14)*('目标填报'!$F$4:$F$1500="在手订单")*('目标填报'!$G$3:$R$3=$F$1)*'目标填报'!$G$4:$R$1500)) | Q14: =IF($B14="","",SUMPRODUCT(('目标填报'!$B$4:$B$1500=$B14)*('目标填报'!$C$4:$C$1500=$C14)*('目标填报'!$D$4:$D$1500=$D14)*('目标填报'!$F$4:$F$1500="在手订单目标")*('目标填报'!$G$3:$R$3=$F$1)*'目标填报'!$G$4:$R$1500)) | R14: =IF($B14="","",IFERROR(P14/Q14,"")) | S14: =IF($B14="","",SUMPRODUCT(('目标填报'!$B$4:$B$1500=$B14)*('目标填报'!$C$4:$C$1500=$C14)*('目标填报'!$D$4:$D$1500=$D14)*('目标填报'!$F$4:$F$1500="目标客户机会")*('目标填报'!$G$3:$R$3=$F$1)*'目标填报'!$G$4:$R$1500)) | T14: =IF($B14="","",SUMPRODUCT(('目标填报'!$B$4:$B$1500=$B14)*('目标填报'!$C$4:$C$1500=$C14)*('目标填报'!$D$4:$D$1500=$D14)*('目标填报'!$F$4:$F$1500="目标客户机会目标")*('目标填报'!$G$3:$R$3=$F$1)*'目标填报'!$G$4:$R$1500)) | U14: =IF($B14="","",IFERROR(S14/T14,"")) | V14: =IF($B14="","",P14+S14) | W14: =IF($B14="","",M14-J14) | X14: =IF($B14="","",IFERROR(V14/W14,"")) | Y14: =IF($B14="","",V14-W14)
A15: =IF($B15="","",ROW()-3) | B15: =IF(11+1>COUNTA('维度字典'!$C$2:$C$200)*COUNTA('维度字典'!$A$2:$A$200)*COUNTA('维度字典'!$E$2:$E$200),"",INDEX('维度字典'!$C$2:$C$200,MOD(INT(11/(COUNTA('维度字典'!$E$2:$E$200)*COUNTA('维度字典'!$A$2:$A$200))),COUNTA('维度字典'!$C$2:$C$200))+1)) | C15: =IF($B15="","",INDEX('维度字典'!$A$2:$A$200,MOD(INT(11/COUNTA('维度字典'!$E$2:$E$200)),COUNTA('维度字典'!$A$2:$A$200))+1)) | D15: =IF($B15="","",INDEX('维度字典'!$E$2:$E$200,MOD(11,COUNTA('维度字典'!$E$2:$E$200))+1)) | E15: =IF($B15="","",SUMPRODUCT(('系统实绩导入'!$B$4:$B$1500=$B15)*('系统实绩导入'!$C$4:$C$1500=$C15)*('系统实绩导入'!$D$4:$D$1500=$D15)*('系统实绩导入'!$F$4:$F$1500="实绩销售额")*('系统实绩导入'!$G$3:$R$3=$F$1)*'系统实绩导入'!$G$4:$R$1500)) | F15: =IF($B15="","",SUMPRODUCT(('系统实绩导入'!$B$4:$B$1500=$B15)*('系统实绩导入'!$C$4:$C$1500=$C15)*('系统实绩导入'!$D$4:$D$1500=$D15)*('系统实绩导入'!$F$4:$F$1500="实绩毛利")*('系统实绩导入'!$G$3:$R$3=$F$1)*'系统实绩导入'!$G$4:$R$1500)) | G15: =IF($B15="","",IFERROR(F15/E15,"")) | H15: =IF($B15="","",SUMPRODUCT(('目标填报'!$B$4:$B$1500=$B15)*('目标填报'!$C$4:$C$1500=$C15)*('目标填报'!$D$4:$D$1500=$D15)*('目标填报'!$F$4:$F$1500="销售目标额")*('目标填报'!$G$3:$R$3=$F$1)*'目标填报'!$G$4:$R$1500)) | I15: =IF($B15="","",IFERROR(E15/H15,"")) | J15: =IF($B15="","",SUMPRODUCT(('系统实绩导入'!$B$4:$B$1500=$B15)*('系统实绩导入'!$C$4:$C$1500=$C15)*('系统实绩导入'!$D$4:$D$1500=$D15)*('系统实绩导入'!$F$4:$F$1500="实绩销售额")*('系统实绩导入'!$G$3:$R$3<=$F$1)*'系统实绩导入'!$G$4:$R$1500)) | K15: =IF($B15="","",SUMPRODUCT(('系统实绩导入'!$B$4:$B$1500=$B15)*('系统实绩导入'!$C$4:$C$1500=$C15)*('系统实绩导入'!$D$4:$D$1500=$D15)*('系统实绩导入'!$F$4:$F$1500="实绩毛利")*('系统实绩导入'!$G$3:$R$3<=$F$1)*'系统实绩导入'!$G$4:$R$1500)) | L15: =IF($B15="","",IFERROR(K15/J15,"")) | M15: =IF($B15="","",SUMIFS('目标填报'!$S$4:$S$1500,'目标填报'!$B$4:$B$1500,$B15,'目标填报'!$C$4:$C$1500,$C15,'目标填报'!$D$4:$D$1500,$D15,'目标填报'!$F$4:$F$1500,"销售目标额")) | N15: =IF($B15="","",IFERROR(J15/M15,"")) | O15: =IF($B15="","",J15-M15) | P15: =IF($B15="","",SUMPRODUCT(('目标填报'!$B$4:$B$1500=$B15)*('目标填报'!$C$4:$C$1500=$C15)*('目标填报'!$D$4:$D$1500=$D15)*('目标填报'!$F$4:$F$1500="在手订单")*('目标填报'!$G$3:$R$3=$F$1)*'目标填报'!$G$4:$R$1500)) | Q15: =IF($B15="","",SUMPRODUCT(('目标填报'!$B$4:$B$1500=$B15)*('目标填报'!$C$4:$C$1500=$C15)*('目标填报'!$D$4:$D$1500=$D15)*('目标填报'!$F$4:$F$1500="在手订单目标")*('目标填报'!$G$3:$R$3=$F$1)*'目标填报'!$G$4:$R$1500)) | R15: =IF($B15="","",IFERROR(P15/Q15,"")) | S15: =IF($B15="","",SUMPRODUCT(('目标填报'!$B$4:$B$1500=$B15)*('目标填报'!$C$4:$C$1500=$C15)*('目标填报'!$D$4:$D$1500=$D15)*('目标填报'!$F$4:$F$1500="目标客户机会")*('目标填报'!$G$3:$R$3=$F$1)*'目标填报'!$G$4:$R$1500)) | T15: =IF($B15="","",SUMPRODUCT(('目标填报'!$B$4:$B$1500=$B15)*('目标填报'!$C$4:$C$1500=$C15)*('目标填报'!$D$4:$D$1500=$D15)*('目标填报'!$F$4:$F$1500="目标客户机会目标")*('目标填报'!$G$3:$R$3=$F$1)*'目标填报'!$G$4:$R$1500)) | U15: =IF($B15="","",IFERROR(S15/T15,"")) | V15: =IF($B15="","",P15+S15) | W15: =IF($B15="","",M15-J15) | X15: =IF($B15="","",IFERROR(V15/W15,"")) | Y15: =IF($B15="","",V15-W15)
A16: =IF($B16="","",ROW()-3) | B16: =IF(12+1>COUNTA('维度字典'!$C$2:$C$200)*COUNTA('维度字典'!$A$2:$A$200)*COUNTA('维度字典'!$E$2:$E$200),"",INDEX('维度字典'!$C$2:$C$200,MOD(INT(12/(COUNTA('维度字典'!$E$2:$E$200)*COUNTA('维度字典'!$A$2:$A$200))),COUNTA('维度字典'!$C$2:$C$200))+1)) | C16: =IF($B16="","",INDEX('维度字典'!$A$2:$A$200,MOD(INT(12/COUNTA('维度字典'!$E$2:$E$200)),COUNTA('维度字典'!$A$2:$A$200))+1)) | D16: =IF($B16="","",INDEX('维度字典'!$E$2:$E$200,MOD(12,COUNTA('维度字典'!$E$2:$E$200))+1)) | E16: =IF($B16="","",SUMPRODUCT(('系统实绩导入'!$B$4:$B$1500=$B16)*('系统实绩导入'!$C$4:$C$1500=$C16)*('系统实绩导入'!$D$4:$D$1500=$D16)*('系统实绩导入'!$F$4:$F$1500="实绩销售额")*('系统实绩导入'!$G$3:$R$3=$F$1)*'系统实绩导入'!$G$4:$R$1500)) | F16: =IF($B16="","",SUMPRODUCT(('系统实绩导入'!$B$4:$B$1500=$B16)*('系统实绩导入'!$C$4:$C$1500=$C16)*('系统实绩导入'!$D$4:$D$1500=$D16)*('系统实绩导入'!$F$4:$F$1500="实绩毛利")*('系统实绩导入'!$G$3:$R$3=$F$1)*'系统实绩导入'!$G$4:$R$1500)) | G16: =IF($B16="","",IFERROR(F16/E16,"")) | H16: =IF($B16="","",SUMPRODUCT(('目标填报'!$B$4:$B$1500=$B16)*('目标填报'!$C$4:$C$1500=$C16)*('目标填报'!$D$4:$D$1500=$D16)*('目标填报'!$F$4:$F$1500="销售目标额")*('目标填报'!$G$3:$R$3=$F$1)*'目标填报'!$G$4:$R$1500)) | I16: =IF($B16="","",IFERROR(E16/H16,"")) | J16: =IF($B16="","",SUMPRODUCT(('系统实绩导入'!$B$4:$B$1500=$B16)*('系统实绩导入'!$C$4:$C$1500=$C16)*('系统实绩导入'!$D$4:$D$1500=$D16)*('系统实绩导入'!$F$4:$F$1500="实绩销售额")*('系统实绩导入'!$G$3:$R$3<=$F$1)*'系统实绩导入'!$G$4:$R$1500)) | K16: =IF($B16="","",SUMPRODUCT(('系统实绩导入'!$B$4:$B$1500=$B16)*('系统实绩导入'!$C$4:$C$1500=$C16)*('系统实绩导入'!$D$4:$D$1500=$D16)*('系统实绩导入'!$F$4:$F$1500="实绩毛利")*('系统实绩导入'!$G$3:$R$3<=$F$1)*'系统实绩导入'!$G$4:$R$1500)) | L16: =IF($B16="","",IFERROR(K16/J16,"")) | M16: =IF($B16="","",SUMIFS('目标填报'!$S$4:$S$1500,'目标填报'!$B$4:$B$1500,$B16,'目标填报'!$C$4:$C$1500,$C16,'目标填报'!$D$4:$D$1500,$D16,'目标填报'!$F$4:$F$1500,"销售目标额")) | N16: =IF($B16="","",IFERROR(J16/M16,"")) | O16: =IF($B16="","",J16-M16) | P16: =IF($B16="","",SUMPRODUCT(('目标填报'!$B$4:$B$1500=$B16)*('目标填报'!$C$4:$C$1500=$C16)*('目标填报'!$D$4:$D$1500=$D16)*('目标填报'!$F$4:$F$1500="在手订单")*('目标填报'!$G$3:$R$3=$F$1)*'目标填报'!$G$4:$R$1500)) | Q16: =IF($B16="","",SUMPRODUCT(('目标填报'!$B$4:$B$1500=$B16)*('目标填报'!$C$4:$C$1500=$C16)*('目标填报'!$D$4:$D$1500=$D16)*('目标填报'!$F$4:$F$1500="在手订单目标")*('目标填报'!$G$3:$R$3=$F$1)*'目标填报'!$G$4:$R$1500)) | R16: =IF($B16="","",IFERROR(P16/Q16,"")) | S16: =IF($B16="","",SUMPRODUCT(('目标填报'!$B$4:$B$1500=$B16)*('目标填报'!$C$4:$C$1500=$C16)*('目标填报'!$D$4:$D$1500=$D16)*('目标填报'!$F$4:$F$1500="目标客户机会")*('目标填报'!$G$3:$R$3=$F$1)*'目标填报'!$G$4:$R$1500)) | T16: =IF($B16="","",SUMPRODUCT(('目标填报'!$B$4:$B$1500=$B16)*('目标填报'!$C$4:$C$1500=$C16)*('目标填报'!$D$4:$D$1500=$D16)*('目标填报'!$F$4:$F$1500="目标客户机会目标")*('目标填报'!$G$3:$R$3=$F$1)*'目标填报'!$G$4:$R$1500)) | U16: =IF($B16="","",IFERROR(S16/T16,"")) | V16: =IF($B16="","",P16+S16) | W16: =IF($B16="","",M16-J16) | X16: =IF($B16="","",IFERROR(V16/W16,"")) | Y16: =IF($B16="","",V16-W16)
A17: =IF($B17="","",ROW()-3) | B17: =IF(13+1>COUNTA('维度字典'!$C$2:$C$200)*COUNTA('维度字典'!$A$2:$A$200)*COUNTA('维度字典'!$E$2:$E$200),"",INDEX('维度字典'!$C$2:$C$200,MOD(INT(13/(COUNTA('维度字典'!$E$2:$E$200)*COUNTA('维度字典'!$A$2:$A$200))),COUNTA('维度字典'!$C$2:$C$200))+1)) | C17: =IF($B17="","",INDEX('维度字典'!$A$2:$A$200,MOD(INT(13/COUNTA('维度字典'!$E$2:$E$200)),COUNTA('维度字典'!$A$2:$A$200))+1)) | D17: =IF($B17="","",INDEX('维度字典'!$E$2:$E$200,MOD(13,COUNTA('维度字典'!$E$2:$E$200))+1)) | E17: =IF($B17="","",SUMPRODUCT(('系统实绩导入'!$B$4:$B$1500=$B17)*('系统实绩导入'!$C$4:$C$1500=$C17)*('系统实绩导入'!$D$4:$D$1500=$D17)*('系统实绩导入'!$F$4:$F$1500="实绩销售额")*('系统实绩导入'!$G$3:$R$3=$F$1)*'系统实绩导入'!$G$4:$R$1500)) | F17: =IF($B17="","",SUMPRODUCT(('系统实绩导入'!$B$4:$B$1500=$B17)*('系统实绩导入'!$C$4:$C$1500=$C17)*('系统实绩导入'!$D$4:$D$1500=$D17)*('系统实绩导入'!$F$4:$F$1500="实绩毛利")*('系统实绩导入'!$G$3:$R$3=$F$1)*'系统实绩导入'!$G$4:$R$1500)) | G17: =IF($B17="","",IFERROR(F17/E17,"")) | H17: =IF($B17="","",SUMPRODUCT(('目标填报'!$B$4:$B$1500=$B17)*('目标填报'!$C$4:$C$1500=$C17)*('目标填报'!$D$4:$D$1500=$D17)*('目标填报'!$F$4:$F$1500="销售目标额")*('目标填报'!$G$3:$R$3=$F$1)*'目标填报'!$G$4:$R$1500)) | I17: =IF($B17="","",IFERROR(E17/H17,"")) | J17: =IF($B17="","",SUMPRODUCT(('系统实绩导入'!$B$4:$B$1500=$B17)*('系统实绩导入'!$C$4:$C$1500=$C17)*('系统实绩导入'!$D$4:$D$1500=$D17)*('系统实绩导入'!$F$4:$F$1500="实绩销售额")*('系统实绩导入'!$G$3:$R$3<=$F$1)*'系统实绩导入'!$G$4:$R$1500)) | K17: =IF($B17="","",SUMPRODUCT(('系统实绩导入'!$B$4:$B$1500=$B17)*('系统实绩导入'!$C$4:$C$1500=$C17)*('系统实绩导入'!$D$4:$D$1500=$D17)*('系统实绩导入'!$F$4:$F$1500="实绩毛利")*('系统实绩导入'!$G$3:$R$3<=$F$1)*'系统实绩导入'!$G$4:$R$1500)) | L17: =IF($B17="","",IFERROR(K17/J17,"")) | M17: =IF($B17="","",SUMIFS('目标填报'!$S$4:$S$1500,'目标填报'!$B$4:$B$1500,$B17,'目标填报'!$C$4:$C$1500,$C17,'目标填报'!$D$4:$D$1500,$D17,'目标填报'!$F$4:$F$1500,"销售目标额")) | N17: =IF($B17="","",IFERROR(J17/M17,"")) | O17: =IF($B17="","",J17-M17) | P17: =IF($B17="","",SUMPRODUCT(('目标填报'!$B$4:$B$1500=$B17)*('目标填报'!$C$4:$C$1500=$C17)*('目标填报'!$D$4:$D$1500=$D17)*('目标填报'!$F$4:$F$1500="在手订单")*('目标填报'!$G$3:$R$3=$F$1)*'目标填报'!$G$4:$R$1500)) | Q17: =IF($B17="","",SUMPRODUCT(('目标填报'!$B$4:$B$1500=$B17)*('目标填报'!$C$4:$C$1500=$C17)*('目标填报'!$D$4:$D$1500=$D17)*('目标填报'!$F$4:$F$1500="在手订单目标")*('目标填报'!$G$3:$R$3=$F$1)*'目标填报'!$G$4:$R$1500)) | R17: =IF($B17="","",IFERROR(P17/Q17,"")) | S17: =IF($B17="","",SUMPRODUCT(('目标填报'!$B$4:$B$1500=$B17)*('目标填报'!$C$4:$C$1500=$C17)*('目标填报'!$D$4:$D$1500=$D17)*('目标填报'!$F$4:$F$1500="目标客户机会")*('目标填报'!$G$3:$R$3=$F$1)*'目标填报'!$G$4:$R$1500)) | T17: =IF($B17="","",SUMPRODUCT(('目标填报'!$B$4:$B$1500=$B17)*('目标填报'!$C$4:$C$1500=$C17)*('目标填报'!$D$4:$D$1500=$D17)*('目标填报'!$F$4:$F$1500="目标客户机会目标")*('目标填报'!$G$3:$R$3=$F$1)*'目标填报'!$G$4:$R$1500)) | U17: =IF($B17="","",IFERROR(S17/T17,"")) | V17: =IF($B17="","",P17+S17) | W17: =IF($B17="","",M17-J17) | X17: =IF($B17="","",IFERROR(V17/W17,"")) | Y17: =IF($B17="","",V17-W17)
A18: =IF($B18="","",ROW()-3) | B18: =IF(14+1>COUNTA('维度字典'!$C$2:$C$200)*COUNTA('维度字典'!$A$2:$A$200)*COUNTA('维度字典'!$E$2:$E$200),"",INDEX('维度字典'!$C$2:$C$200,MOD(INT(14/(COUNTA('维度字典'!$E$2:$E$200)*COUNTA('维度字典'!$A$2:$A$200))),COUNTA('维度字典'!$C$2:$C$200))+1)) | C18: =IF($B18="","",INDEX('维度字典'!$A$2:$A$200,MOD(INT(14/COUNTA('维度字典'!$E$2:$E$200)),COUNTA('维度字典'!$A$2:$A$200))+1)) | D18: =IF($B18="","",INDEX('维度字典'!$E$2:$E$200,MOD(14,COUNTA('维度字典'!$E$2:$E$200))+1)) | E18: =IF($B18="","",SUMPRODUCT(('系统实绩导入'!$B$4:$B$1500=$B18)*('系统实绩导入'!$C$4:$C$1500=$C18)*('系统实绩导入'!$D$4:$D$1500=$D18)*('系统实绩导入'!$F$4:$F$1500="实绩销售额")*('系统实绩导入'!$G$3:$R$3=$F$1)*'系统实绩导入'!$G$4:$R$1500)) | F18: =IF($B18="","",SUMPRODUCT(('系统实绩导入'!$B$4:$B$1500=$B18)*('系统实绩导入'!$C$4:$C$1500=$C18)*('系统实绩导入'!$D$4:$D$1500=$D18)*('系统实绩导入'!$F$4:$F$1500="实绩毛利")*('系统实绩导入'!$G$3:$R$3=$F$1)*'系统实绩导入'!$G$4:$R$1500)) | G18: =IF($B18="","",IFERROR(F18/E18,"")) | H18: =IF($B18="","",SUMPRODUCT(('目标填报'!$B$4:$B$1500=$B18)*('目标填报'!$C$4:$C$1500=$C18)*('目标填报'!$D$4:$D$1500=$D18)*('目标填报'!$F$4:$F$1500="销售目标额")*('目标填报'!$G$3:$R$3=$F$1)*'目标填报'!$G$4:$R$1500)) | I18: =IF($B18="","",IFERROR(E18/H18,"")) | J18: =IF($B18="","",SUMPRODUCT(('系统实绩导入'!$B$4:$B$1500=$B18)*('系统实绩导入'!$C$4:$C$1500=$C18)*('系统实绩导入'!$D$4:$D$1500=$D18)*('系统实绩导入'!$F$4:$F$1500="实绩销售额")*('系统实绩导入'!$G$3:$R$3<=$F$1)*'系统实绩导入'!$G$4:$R$1500)) | K18: =IF($B18="","",SUMPRODUCT(('系统实绩导入'!$B$4:$B$1500=$B18)*('系统实绩导入'!$C$4:$C$1500=$C18)*('系统实绩导入'!$D$4:$D$1500=$D18)*('系统实绩导入'!$F$4:$F$1500="实绩毛利")*('系统实绩导入'!$G$3:$R$3<=$F$1)*'系统实绩导入'!$G$4:$R$1500)) | L18: =IF($B18="","",IFERROR(K18/J18,"")) | M18: =IF($B18="","",SUMIFS('目标填报'!$S$4:$S$1500,'目标填报'!$B$4:$B$1500,$B18,'目标填报'!$C$4:$C$1500,$C18,'目标填报'!$D$4:$D$1500,$D18,'目标填报'!$F$4:$F$1500,"销售目标额")) | N18: =IF($B18="","",IFERROR(J18/M18,"")) | O18: =IF($B18="","",J18-M18) | P18: =IF($B18="","",SUMPRODUCT(('目标填报'!$B$4:$B$1500=$B18)*('目标填报'!$C$4:$C$1500=$C18)*('目标填报'!$D$4:$D$1500=$D18)*('目标填报'!$F$4:$F$1500="在手订单")*('目标填报'!$G$3:$R$3=$F$1)*'目标填报'!$G$4:$R$1500)) | Q18: =IF($B18="","",SUMPRODUCT(('目标填报'!$B$4:$B$1500=$B18)*('目标填报'!$C$4:$C$1500=$C18)*('目标填报'!$D$4:$D$1500=$D18)*('目标填报'!$F$4:$F$1500="在手订单目标")*('目标填报'!$G$3:$R$3=$F$1)*'目标填报'!$G$4:$R$1500)) | R18: =IF($B18="","",IFERROR(P18/Q18,"")) | S18: =IF($B18="","",SUMPRODUCT(('目标填报'!$B$4:$B$1500=$B18)*('目标填报'!$C$4:$C$1500=$C18)*('目标填报'!$D$4:$D$1500=$D18)*('目标填报'!$F$4:$F$1500="目标客户机会")*('目标填报'!$G$3:$R$3=$F$1)*'目标填报'!$G$4:$R$1500)) | T18: =IF($B18="","",SUMPRODUCT(('目标填报'!$B$4:$B$1500=$B18)*('目标填报'!$C$4:$C$1500=$C18)*('目标填报'!$D$4:$D$1500=$D18)*('目标填报'!$F$4:$F$1500="目标客户机会目标")*('目标填报'!$G$3:$R$3=$F$1)*'目标填报'!$G$4:$R$1500)) | U18: =IF($B18="","",IFERROR(S18/T18,"")) | V18: =IF($B18="","",P18+S18) | W18: =IF($B18="","",M18-J18) | X18: =IF($B18="","",IFERROR(V18/W18,"")) | Y18: =IF($B18="","",V18-W18)
A19: =IF($B19="","",ROW()-3) | B19: =IF(15+1>COUNTA('维度字典'!$C$2:$C$200)*COUNTA('维度字典'!$A$2:$A$200)*COUNTA('维度字典'!$E$2:$E$200),"",INDEX('维度字典'!$C$2:$C$200,MOD(INT(15/(COUNTA('维度字典'!$E$2:$E$200)*COUNTA('维度字典'!$A$2:$A$200))),COUNTA('维度字典'!$C$2:$C$200))+1)) | C19: =IF($B19="","",INDEX('维度字典'!$A$2:$A$200,MOD(INT(15/COUNTA('维度字典'!$E$2:$E$200)),COUNTA('维度字典'!$A$2:$A$200))+1)) | D19: =IF($B19="","",INDEX('维度字典'!$E$2:$E$200,MOD(15,COUNTA('维度字典'!$E$2:$E$200))+1)) | E19: =IF($B19="","",SUMPRODUCT(('系统实绩导入'!$B$4:$B$1500=$B19)*('系统实绩导入'!$C$4:$C$1500=$C19)*('系统实绩导入'!$D$4:$D$1500=$D19)*('系统实绩导入'!$F$4:$F$1500="实绩销售额")*('系统实绩导入'!$G$3:$R$3=$F$1)*'系统实绩导入'!$G$4:$R$1500)) | F19: =IF($B19="","",SUMPRODUCT(('系统实绩导入'!$B$4:$B$1500=$B19)*('系统实绩导入'!$C$4:$C$1500=$C19)*('系统实绩导入'!$D$4:$D$1500=$D19)*('系统实绩导入'!$F$4:$F$1500="实绩毛利")*('系统实绩导入'!$G$3:$R$3=$F$1)*'系统实绩导入'!$G$4:$R$1500)) | G19: =IF($B19="","",IFERROR(F19/E19,"")) | H19: =IF($B19="","",SUMPRODUCT(('目标填报'!$B$4:$B$1500=$B19)*('目标填报'!$C$4:$C$1500=$C19)*('目标填报'!$D$4:$D$1500=$D19)*('目标填报'!$F$4:$F$1500="销售目标额")*('目标填报'!$G$3:$R$3=$F$1)*'目标填报'!$G$4:$R$1500)) | I19: =IF($B19="","",IFERROR(E19/H19,"")) | J19: =IF($B19="","",SUMPRODUCT(('系统实绩导入'!$B$4:$B$1500=$B19)*('系统实绩导入'!$C$4:$C$1500=$C19)*('系统实绩导入'!$D$4:$D$1500=$D19)*('系统实绩导入'!$F$4:$F$1500="实绩销售额")*('系统实绩导入'!$G$3:$R$3<=$F$1)*'系统实绩导入'!$G$4:$R$1500)) | K19: =IF($B19="","",SUMPRODUCT(('系统实绩导入'!$B$4:$B$1500=$B19)*('系统实绩导入'!$C$4:$C$1500=$C19)*('系统实绩导入'!$D$4:$D$1500=$D19)*('系统实绩导入'!$F$4:$F$1500="实绩毛利")*('系统实绩导入'!$G$3:$R$3<=$F$1)*'系统实绩导入'!$G$4:$R$1500)) | L19: =IF($B19="","",IFERROR(K19/J19,"")) | M19: =IF($B19="","",SUMIFS('目标填报'!$S$4:$S$1500,'目标填报'!$B$4:$B$1500,$B19,'目标填报'!$C$4:$C$1500,$C19,'目标填报'!$D$4:$D$1500,$D19,'目标填报'!$F$4:$F$1500,"销售目标额")) | N19: =IF($B19="","",IFERROR(J19/M19,"")) | O19: =IF($B19="","",J19-M19) | P19: =IF($B19="","",SUMPRODUCT(('目标填报'!$B$4:$B$1500=$B19)*('目标填报'!$C$4:$C$1500=$C19)*('目标填报'!$D$4:$D$1500=$D19)*('目标填报'!$F$4:$F$1500="在手订单")*('目标填报'!$G$3:$R$3=$F$1)*'目标填报'!$G$4:$R$1500)) | Q19: =IF($B19="","",SUMPRODUCT(('目标填报'!$B$4:$B$1500=$B19)*('目标填报'!$C$4:$C$1500=$C19)*('目标填报'!$D$4:$D$1500=$D19)*('目标填报'!$F$4:$F$1500="在手订单目标")*('目标填报'!$G$3:$R$3=$F$1)*'目标填报'!$G$4:$R$1500)) | R19: =IF($B19="","",IFERROR(P19/Q19,"")) | S19: =IF($B19="","",SUMPRODUCT(('目标填报'!$B$4:$B$1500=$B19)*('目标填报'!$C$4:$C$1500=$C19)*('目标填报'!$D$4:$D$1500=$D19)*('目标填报'!$F$4:$F$1500="目标客户机会")*('目标填报'!$G$3:$R$3=$F$1)*'目标填报'!$G$4:$R$1500)) | T19: =IF($B19="","",SUMPRODUCT(('目标填报'!$B$4:$B$1500=$B19)*('目标填报'!$C$4:$C$1500=$C19)*('目标填报'!$D$4:$D$1500=$D19)*('目标填报'!$F$4:$F$1500="目标客户机会目标")*('目标填报'!$G$3:$R$3=$F$1)*'目标填报'!$G$4:$R$1500)) | U19: =IF($B19="","",IFERROR(S19/T19,"")) | V19: =IF($B19="","",P19+S19) | W19: =IF($B19="","",M19-J19) | X19: =IF($B19="","",IFERROR(V19/W19,"")) | Y19: =IF($B19="","",V19-W19)
A20: =IF($B20="","",ROW()-3) | B20: =IF(16+1>COUNTA('维度字典'!$C$2:$C$200)*COUNTA('维度字典'!$A$2:$A$200)*COUNTA('维度字典'!$E$2:$E$200),"",INDEX('维度字典'!$C$2:$C$200,MOD(INT(16/(COUNTA('维度字典'!$E$2:$E$200)*COUNTA('维度字典'!$A$2:$A$200))),COUNTA('维度字典'!$C$2:$C$200))+1)) | C20: =IF($B20="","",INDEX('维度字典'!$A$2:$A$200,MOD(INT(16/COUNTA('维度字典'!$E$2:$E$200)),COUNTA('维度字典'!$A$2:$A$200))+1)) | D20: =IF($B20="","",INDEX('维度字典'!$E$2:$E$200,MOD(16,COUNTA('维度字典'!$E$2:$E$200))+1)) | E20: =IF($B20="","",SUMPRODUCT(('系统实绩导入'!$B$4:$B$1500=$B20)*('系统实绩导入'!$C$4:$C$1500=$C20)*('系统实绩导入'!$D$4:$D$1500=$D20)*('系统实绩导入'!$F$4:$F$1500="实绩销售额")*('系统实绩导入'!$G$3:$R$3=$F$1)*'系统实绩导入'!$G$4:$R$1500)) | F20: =IF($B20="","",SUMPRODUCT(('系统实绩导入'!$B$4:$B$1500=$B20)*('系统实绩导入'!$C$4:$C$1500=$C20)*('系统实绩导入'!$D$4:$D$1500=$D20)*('系统实绩导入'!$F$4:$F$1500="实绩毛利")*('系统实绩导入'!$G$3:$R$3=$F$1)*'系统实绩导入'!$G$4:$R$1500)) | G20: =IF($B20="","",IFERROR(F20/E20,"")) | H20: =IF($B20="","",SUMPRODUCT(('目标填报'!$B$4:$B$1500=$B20)*('目标填报'!$C$4:$C$1500=$C20)*('目标填报'!$D$4:$D$1500=$D20)*('目标填报'!$F$4:$F$1500="销售目标额")*('目标填报'!$G$3:$R$3=$F$1)*'目标填报'!$G$4:$R$1500)) | I20: =IF($B20="","",IFERROR(E20/H20,"")) | J20: =IF($B20="","",SUMPRODUCT(('系统实绩导入'!$B$4:$B$1500=$B20)*('系统实绩导入'!$C$4:$C$1500=$C20)*('系统实绩导入'!$D$4:$D$1500=$D20)*('系统实绩导入'!$F$4:$F$1500="实绩销售额")*('系统实绩导入'!$G$3:$R$3<=$F$1)*'系统实绩导入'!$G$4:$R$1500)) | K20: =IF($B20="","",SUMPRODUCT(('系统实绩导入'!$B$4:$B$1500=$B20)*('系统实绩导入'!$C$4:$C$1500=$C20)*('系统实绩导入'!$D$4:$D$1500=$D20)*('系统实绩导入'!$F$4:$F$1500="实绩毛利")*('系统实绩导入'!$G$3:$R$3<=$F$1)*'系统实绩导入'!$G$4:$R$1500)) | L20: =IF($B20="","",IFERROR(K20/J20,"")) | M20: =IF($B20="","",SUMIFS('目标填报'!$S$4:$S$1500,'目标填报'!$B$4:$B$1500,$B20,'目标填报'!$C$4:$C$1500,$C20,'目标填报'!$D$4:$D$1500,$D20,'目标填报'!$F$4:$F$1500,"销售目标额")) | N20: =IF($B20="","",IFERROR(J20/M20,"")) | O20: =IF($B20="","",J20-M20) | P20: =IF($B20="","",SUMPRODUCT(('目标填报'!$B$4:$B$1500=$B20)*('目标填报'!$C$4:$C$1500=$C20)*('目标填报'!$D$4:$D$1500=$D20)*('目标填报'!$F$4:$F$1500="在手订单")*('目标填报'!$G$3:$R$3=$F$1)*'目标填报'!$G$4:$R$1500)) | Q20: =IF($B20="","",SUMPRODUCT(('目标填报'!$B$4:$B$1500=$B20)*('目标填报'!$C$4:$C$1500=$C20)*('目标填报'!$D$4:$D$1500=$D20)*('目标填报'!$F$4:$F$1500="在手订单目标")*('目标填报'!$G$3:$R$3=$F$1)*'目标填报'!$G$4:$R$1500)) | R20: =IF($B20="","",IFERROR(P20/Q20,"")) | S20: =IF($B20="","",SUMPRODUCT(('目标填报'!$B$4:$B$1500=$B20)*('目标填报'!$C$4:$C$1500=$C20)*('目标填报'!$D$4:$D$1500=$D20)*('目标填报'!$F$4:$F$1500="目标客户机会")*('目标填报'!$G$3:$R$3=$F$1)*'目标填报'!$G$4:$R$1500)) | T20: =IF($B20="","",SUMPRODUCT(('目标填报'!$B$4:$B$1500=$B20)*('目标填报'!$C$4:$C$1500=$C20)*('目标填报'!$D$4:$D$1500=$D20)*('目标填报'!$F$4:$F$1500="目标客户机会目标")*('目标填报'!$G$3:$R$3=$F$1)*'目标填报'!$G$4:$R$1500)) | U20: =IF($B20="","",IFERROR(S20/T20,"")) | V20: =IF($B20="","",P20+S20) | W20: =IF($B20="","",M20-J20) | X20: =IF($B20="","",IFERROR(V20/W20,"")) | Y20: =IF($B20="","",V20-W20)
A21: =IF($B21="","",ROW()-3) | B21: =IF(17+1>COUNTA('维度字典'!$C$2:$C$200)*COUNTA('维度字典'!$A$2:$A$200)*COUNTA('维度字典'!$E$2:$E$200),"",INDEX('维度字典'!$C$2:$C$200,MOD(INT(17/(COUNTA('维度字典'!$E$2:$E$200)*COUNTA('维度字典'!$A$2:$A$200))),COUNTA('维度字典'!$C$2:$C$200))+1)) | C21: =IF($B21="","",INDEX('维度字典'!$A$2:$A$200,MOD(INT(17/COUNTA('维度字典'!$E$2:$E$200)),COUNTA('维度字典'!$A$2:$A$200))+1)) | D21: =IF($B21="","",INDEX('维度字典'!$E$2:$E$200,MOD(17,COUNTA('维度字典'!$E$2:$E$200))+1)) | E21: =IF($B21="","",SUMPRODUCT(('系统实绩导入'!$B$4:$B$1500=$B21)*('系统实绩导入'!$C$4:$C$1500=$C21)*('系统实绩导入'!$D$4:$D$1500=$D21)*('系统实绩导入'!$F$4:$F$1500="实绩销售额")*('系统实绩导入'!$G$3:$R$3=$F$1)*'系统实绩导入'!$G$4:$R$1500)) | F21: =IF($B21="","",SUMPRODUCT(('系统实绩导入'!$B$4:$B$1500=$B21)*('系统实绩导入'!$C$4:$C$1500=$C21)*('系统实绩导入'!$D$4:$D$1500=$D21)*('系统实绩导入'!$F$4:$F$1500="实绩毛利")*('系统实绩导入'!$G$3:$R$3=$F$1)*'系统实绩导入'!$G$4:$R$1500)) | G21: =IF($B21="","",IFERROR(F21/E21,"")) | H21: =IF($B21="","",SUMPRODUCT(('目标填报'!$B$4:$B$1500=$B21)*('目标填报'!$C$4:$C$1500=$C21)*('目标填报'!$D$4:$D$1500=$D21)*('目标填报'!$F$4:$F$1500="销售目标额")*('目标填报'!$G$3:$R$3=$F$1)*'目标填报'!$G$4:$R$1500)) | I21: =IF($B21="","",IFERROR(E21/H21,"")) | J21: =IF($B21="","",SUMPRODUCT(('系统实绩导入'!$B$4:$B$1500=$B21)*('系统实绩导入'!$C$4:$C$1500=$C21)*('系统实绩导入'!$D$4:$D$1500=$D21)*('系统实绩导入'!$F$4:$F$1500="实绩销售额")*('系统实绩导入'!$G$3:$R$3<=$F$1)*'系统实绩导入'!$G$4:$R$1500)) | K21: =IF($B21="","",SUMPRODUCT(('系统实绩导入'!$B$4:$B$1500=$B21)*('系统实绩导入'!$C$4:$C$1500=$C21)*('系统实绩导入'!$D$4:$D$1500=$D21)*('系统实绩导入'!$F$4:$F$1500="实绩毛利")*('系统实绩导入'!$G$3:$R$3<=$F$1)*'系统实绩导入'!$G$4:$R$1500)) | L21: =IF($B21="","",IFERROR(K21/J21,"")) | M21: =IF($B21="","",SUMIFS('目标填报'!$S$4:$S$1500,'目标填报'!$B$4:$B$1500,$B21,'目标填报'!$C$4:$C$1500,$C21,'目标填报'!$D$4:$D$1500,$D21,'目标填报'!$F$4:$F$1500,"销售目标额")) | N21: =IF($B21="","",IFERROR(J21/M21,"")) | O21: =IF($B21="","",J21-M21) | P21: =IF($B21="","",SUMPRODUCT(('目标填报'!$B$4:$B$1500=$B21)*('目标填报'!$C$4:$C$1500=$C21)*('目标填报'!$D$4:$D$1500=$D21)*('目标填报'!$F$4:$F$1500="在手订单")*('目标填报'!$G$3:$R$3=$F$1)*'目标填报'!$G$4:$R$1500)) | Q21: =IF($B21="","",SUMPRODUCT(('目标填报'!$B$4:$B$1500=$B21)*('目标填报'!$C$4:$C$1500=$C21)*('目标填报'!$D$4:$D$1500=$D21)*('目标填报'!$F$4:$F$1500="在手订单目标")*('目标填报'!$G$3:$R$3=$F$1)*'目标填报'!$G$4:$R$1500)) | R21: =IF($B21="","",IFERROR(P21/Q21,"")) | S21: =IF($B21="","",SUMPRODUCT(('目标填报'!$B$4:$B$1500=$B21)*('目标填报'!$C$4:$C$1500=$C21)*('目标填报'!$D$4:$D$1500=$D21)*('目标填报'!$F$4:$F$1500="目标客户机会")*('目标填报'!$G$3:$R$3=$F$1)*'目标填报'!$G$4:$R$1500)) | T21: =IF($B21="","",SUMPRODUCT(('目标填报'!$B$4:$B$1500=$B21)*('目标填报'!$C$4:$C$1500=$C21)*('目标填报'!$D$4:$D$1500=$D21)*('目标填报'!$F$4:$F$1500="目标客户机会目标")*('目标填报'!$G$3:$R$3=$F$1)*'目标填报'!$G$4:$R$1500)) | U21: =IF($B21="","",IFERROR(S21/T21,"")) | V21: =IF($B21="","",P21+S21) | W21: =IF($B21="","",M21-J21) | X21: =IF($B21="","",IFERROR(V21/W21,"")) | Y21: =IF($B21="","",V21-W21)
A22: =IF($B22="","",ROW()-3) | B22: =IF(18+1>COUNTA('维度字典'!$C$2:$C$200)*COUNTA('维度字典'!$A$2:$A$200)*COUNTA('维度字典'!$E$2:$E$200),"",INDEX('维度字典'!$C$2:$C$200,MOD(INT(18/(COUNTA('维度字典'!$E$2:$E$200)*COUNTA('维度字典'!$A$2:$A$200))),COUNTA('维度字典'!$C$2:$C$200))+1)) | C22: =IF($B22="","",INDEX('维度字典'!$A$2:$A$200,MOD(INT(18/COUNTA('维度字典'!$E$2:$E$200)),COUNTA('维度字典'!$A$2:$A$200))+1)) | D22: =IF($B22="","",INDEX('维度字典'!$E$2:$E$200,MOD(18,COUNTA('维度字典'!$E$2:$E$200))+1)) | E22: =IF($B22="","",SUMPRODUCT(('系统实绩导入'!$B$4:$B$1500=$B22)*('系统实绩导入'!$C$4:$C$1500=$C22)*('系统实绩导入'!$D$4:$D$1500=$D22)*('系统实绩导入'!$F$4:$F$1500="实绩销售额")*('系统实绩导入'!$G$3:$R$3=$F$1)*'系统实绩导入'!$G$4:$R$1500)) | F22: =IF($B22="","",SUMPRODUCT(('系统实绩导入'!$B$4:$B$1500=$B22)*('系统实绩导入'!$C$4:$C$1500=$C22)*('系统实绩导入'!$D$4:$D$1500=$D22)*('系统实绩导入'!$F$4:$F$1500="实绩毛利")*('系统实绩导入'!$G$3:$R$3=$F$1)*'系统实绩导入'!$G$4:$R$1500)) | G22: =IF($B22="","",IFERROR(F22/E22,"")) | H22: =IF($B22="","",SUMPRODUCT(('目标填报'!$B$4:$B$1500=$B22)*('目标填报'!$C$4:$C$1500=$C22)*('目标填报'!$D$4:$D$1500=$D22)*('目标填报'!$F$4:$F$1500="销售目标额")*('目标填报'!$G$3:$R$3=$F$1)*'目标填报'!$G$4:$R$1500)) | I22: =IF($B22="","",IFERROR(E22/H22,"")) | J22: =IF($B22="","",SUMPRODUCT(('系统实绩导入'!$B$4:$B$1500=$B22)*('系统实绩导入'!$C$4:$C$1500=$C22)*('系统实绩导入'!$D$4:$D$1500=$D22)*('系统实绩导入'!$F$4:$F$1500="实绩销售额")*('系统实绩导入'!$G$3:$R$3<=$F$1)*'系统实绩导入'!$G$4:$R$1500)) | K22: =IF($B22="","",SUMPRODUCT(('系统实绩导入'!$B$4:$B$1500=$B22)*('系统实绩导入'!$C$4:$C$1500=$C22)*('系统实绩导入'!$D$4:$D$1500=$D22)*('系统实绩导入'!$F$4:$F$1500="实绩毛利")*('系统实绩导入'!$G$3:$R$3<=$F$1)*'系统实绩导入'!$G$4:$R$1500)) | L22: =IF($B22="","",IFERROR(K22/J22,"")) | M22: =IF($B22="","",SUMIFS('目标填报'!$S$4:$S$1500,'目标填报'!$B$4:$B$1500,$B22,'目标填报'!$C$4:$C$1500,$C22,'目标填报'!$D$4:$D$1500,$D22,'目标填报'!$F$4:$F$1500,"销售目标额")) | N22: =IF($B22="","",IFERROR(J22/M22,"")) | O22: =IF($B22="","",J22-M22) | P22: =IF($B22="","",SUMPRODUCT(('目标填报'!$B$4:$B$1500=$B22)*('目标填报'!$C$4:$C$1500=$C22)*('目标填报'!$D$4:$D$1500=$D22)*('目标填报'!$F$4:$F$1500="在手订单")*('目标填报'!$G$3:$R$3=$F$1)*'目标填报'!$G$4:$R$1500)) | Q22: =IF($B22="","",SUMPRODUCT(('目标填报'!$B$4:$B$1500=$B22)*('目标填报'!$C$4:$C$1500=$C22)*('目标填报'!$D$4:$D$1500=$D22)*('目标填报'!$F$4:$F$1500="在手订单目标")*('目标填报'!$G$3:$R$3=$F$1)*'目标填报'!$G$4:$R$1500)) | R22: =IF($B22="","",IFERROR(P22/Q22,"")) | S22: =IF($B22="","",SUMPRODUCT(('目标填报'!$B$4:$B$1500=$B22)*('目标填报'!$C$4:$C$1500=$C22)*('目标填报'!$D$4:$D$1500=$D22)*('目标填报'!$F$4:$F$1500="目标客户机会")*('目标填报'!$G$3:$R$3=$F$1)*'目标填报'!$G$4:$R$1500)) | T22: =IF($B22="","",SUMPRODUCT(('目标填报'!$B$4:$B$1500=$B22)*('目标填报'!$C$4:$C$1500=$C22)*('目标填报'!$D$4:$D$1500=$D22)*('目标填报'!$F$4:$F$1500="目标客户机会目标")*('目标填报'!$G$3:$R$3=$F$1)*'目标填报'!$G$4:$R$1500)) | U22: =IF($B22="","",IFERROR(S22/T22,"")) | V22: =IF($B22="","",P22+S22) | W22: =IF($B22="","",M22-J22) | X22: =IF($B22="","",IFERROR(V22/W22,"")) | Y22: =IF($B22="","",V22-W22)
A23: =IF($B23="","",ROW()-3) | B23: =IF(19+1>COUNTA('维度字典'!$C$2:$C$200)*COUNTA('维度字典'!$A$2:$A$200)*COUNTA('维度字典'!$E$2:$E$200),"",INDEX('维度字典'!$C$2:$C$200,MOD(INT(19/(COUNTA('维度字典'!$E$2:$E$200)*COUNTA('维度字典'!$A$2:$A$200))),COUNTA('维度字典'!$C$2:$C$200))+1)) | C23: =IF($B23="","",INDEX('维度字典'!$A$2:$A$200,MOD(INT(19/COUNTA('维度字典'!$E$2:$E$200)),COUNTA('维度字典'!$A$2:$A$200))+1)) | D23: =IF($B23="","",INDEX('维度字典'!$E$2:$E$200,MOD(19,COUNTA('维度字典'!$E$2:$E$200))+1)) | E23: =IF($B23="","",SUMPRODUCT(('系统实绩导入'!$B$4:$B$1500=$B23)*('系统实绩导入'!$C$4:$C$1500=$C23)*('系统实绩导入'!$D$4:$D$1500=$D23)*('系统实绩导入'!$F$4:$F$1500="实绩销售额")*('系统实绩导入'!$G$3:$R$3=$F$1)*'系统实绩导入'!$G$4:$R$1500)) | F23: =IF($B23="","",SUMPRODUCT(('系统实绩导入'!$B$4:$B$1500=$B23)*('系统实绩导入'!$C$4:$C$1500=$C23)*('系统实绩导入'!$D$4:$D$1500=$D23)*('系统实绩导入'!$F$4:$F$1500="实绩毛利")*('系统实绩导入'!$G$3:$R$3=$F$1)*'系统实绩导入'!$G$4:$R$1500)) | G23: =IF($B23="","",IFERROR(F23/E23,"")) | H23: =IF($B23="","",SUMPRODUCT(('目标填报'!$B$4:$B$1500=$B23)*('目标填报'!$C$4:$C$1500=$C23)*('目标填报'!$D$4:$D$1500=$D23)*('目标填报'!$F$4:$F$1500="销售目标额")*('目标填报'!$G$3:$R$3=$F$1)*'目标填报'!$G$4:$R$1500)) | I23: =IF($B23="","",IFERROR(E23/H23,"")) | J23: =IF($B23="","",SUMPRODUCT(('系统实绩导入'!$B$4:$B$1500=$B23)*('系统实绩导入'!$C$4:$C$1500=$C23)*('系统实绩导入'!$D$4:$D$1500=$D23)*('系统实绩导入'!$F$4:$F$1500="实绩销售额")*('系统实绩导入'!$G$3:$R$3<=$F$1)*'系统实绩导入'!$G$4:$R$1500)) | K23: =IF($B23="","",SUMPRODUCT(('系统实绩导入'!$B$4:$B$1500=$B23)*('系统实绩导入'!$C$4:$C$1500=$C23)*('系统实绩导入'!$D$4:$D$1500=$D23)*('系统实绩导入'!$F$4:$F$1500="实绩毛利")*('系统实绩导入'!$G$3:$R$3<=$F$1)*'系统实绩导入'!$G$4:$R$1500)) | L23: =IF($B23="","",IFERROR(K23/J23,"")) | M23: =IF($B23="","",SUMIFS('目标填报'!$S$4:$S$1500,'目标填报'!$B$4:$B$1500,$B23,'目标填报'!$C$4:$C$1500,$C23,'目标填报'!$D$4:$D$1500,$D23,'目标填报'!$F$4:$F$1500,"销售目标额")) | N23: =IF($B23="","",IFERROR(J23/M23,"")) | O23: =IF($B23="","",J23-M23) | P23: =IF($B23="","",SUMPRODUCT(('目标填报'!$B$4:$B$1500=$B23)*('目标填报'!$C$4:$C$1500=$C23)*('目标填报'!$D$4:$D$1500=$D23)*('目标填报'!$F$4:$F$1500="在手订单")*('目标填报'!$G$3:$R$3=$F$1)*'目标填报'!$G$4:$R$1500)) | Q23: =IF($B23="","",SUMPRODUCT(('目标填报'!$B$4:$B$1500=$B23)*('目标填报'!$C$4:$C$1500=$C23)*('目标填报'!$D$4:$D$1500=$D23)*('目标填报'!$F$4:$F$1500="在手订单目标")*('目标填报'!$G$3:$R$3=$F$1)*'目标填报'!$G$4:$R$1500)) | R23: =IF($B23="","",IFERROR(P23/Q23,"")) | S23: =IF($B23="","",SUMPRODUCT(('目标填报'!$B$4:$B$1500=$B23)*('目标填报'!$C$4:$C$1500=$C23)*('目标填报'!$D$4:$D$1500=$D23)*('目标填报'!$F$4:$F$1500="目标客户机会")*('目标填报'!$G$3:$R$3=$F$1)*'目标填报'!$G$4:$R$1500)) | T23: =IF($B23="","",SUMPRODUCT(('目标填报'!$B$4:$B$1500=$B23)*('目标填报'!$C$4:$C$1500=$C23)*('目标填报'!$D$4:$D$1500=$D23)*('目标填报'!$F$4:$F$1500="目标客户机会目标")*('目标填报'!$G$3:$R$3=$F$1)*'目标填报'!$G$4:$R$1500)) | U23: =IF($B23="","",IFERROR(S23/T23,"")) | V23: =IF($B23="","",P23+S23) | W23: =IF($B23="","",M23-J23) | X23: =IF($B23="","",IFERROR(V23/W23,"")) | Y23: =IF($B23="","",V23-W23)
A24: =IF($B24="","",ROW()-3) | B24: =IF(20+1>COUNTA('维度字典'!$C$2:$C$200)*COUNTA('维度字典'!$A$2:$A$200)*COUNTA('维度字典'!$E$2:$E$200),"",INDEX('维度字典'!$C$2:$C$200,MOD(INT(20/(COUNTA('维度字典'!$E$2:$E$200)*COUNTA('维度字典'!$A$2:$A$200))),COUNTA('维度字典'!$C$2:$C$200))+1)) | C24: =IF($B24="","",INDEX('维度字典'!$A$2:$A$200,MOD(INT(20/COUNTA('维度字典'!$E$2:$E$200)),COUNTA('维度字典'!$A$2:$A$200))+1)) | D24: =IF($B24="","",INDEX('维度字典'!$E$2:$E$200,MOD(20,COUNTA('维度字典'!$E$2:$E$200))+1)) | E24: =IF($B24="","",SUMPRODUCT(('系统实绩导入'!$B$4:$B$1500=$B24)*('系统实绩导入'!$C$4:$C$1500=$C24)*('系统实绩导入'!$D$4:$D$1500=$D24)*('系统实绩导入'!$F$4:$F$1500="实绩销售额")*('系统实绩导入'!$G$3:$R$3=$F$1)*'系统实绩导入'!$G$4:$R$1500)) | F24: =IF($B24="","",SUMPRODUCT(('系统实绩导入'!$B$4:$B$1500=$B24)*('系统实绩导入'!$C$4:$C$1500=$C24)*('系统实绩导入'!$D$4:$D$1500=$D24)*('系统实绩导入'!$F$4:$F$1500="实绩毛利")*('系统实绩导入'!$G$3:$R$3=$F$1)*'系统实绩导入'!$G$4:$R$1500)) | G24: =IF($B24="","",IFERROR(F24/E24,"")) | H24: =IF($B24="","",SUMPRODUCT(('目标填报'!$B$4:$B$1500=$B24)*('目标填报'!$C$4:$C$1500=$C24)*('目标填报'!$D$4:$D$1500=$D24)*('目标填报'!$F$4:$F$1500="销售目标额")*('目标填报'!$G$3:$R$3=$F$1)*'目标填报'!$G$4:$R$1500)) | I24: =IF($B24="","",IFERROR(E24/H24,"")) | J24: =IF($B24="","",SUMPRODUCT(('系统实绩导入'!$B$4:$B$1500=$B24)*('系统实绩导入'!$C$4:$C$1500=$C24)*('系统实绩导入'!$D$4:$D$1500=$D24)*('系统实绩导入'!$F$4:$F$1500="实绩销售额")*('系统实绩导入'!$G$3:$R$3<=$F$1)*'系统实绩导入'!$G$4:$R$1500)) | K24: =IF($B24="","",SUMPRODUCT(('系统实绩导入'!$B$4:$B$1500=$B24)*('系统实绩导入'!$C$4:$C$1500=$C24)*('系统实绩导入'!$D$4:$D$1500=$D24)*('系统实绩导入'!$F$4:$F$1500="实绩毛利")*('系统实绩导入'!$G$3:$R$3<=$F$1)*'系统实绩导入'!$G$4:$R$1500)) | L24: =IF($B24="","",IFERROR(K24/J24,"")) | M24: =IF($B24="","",SUMIFS('目标填报'!$S$4:$S$1500,'目标填报'!$B$4:$B$1500,$B24,'目标填报'!$C$4:$C$1500,$C24,'目标填报'!$D$4:$D$1500,$D24,'目标填报'!$F$4:$F$1500,"销售目标额")) | N24: =IF($B24="","",IFERROR(J24/M24,"")) | O24: =IF($B24="","",J24-M24) | P24: =IF($B24="","",SUMPRODUCT(('目标填报'!$B$4:$B$1500=$B24)*('目标填报'!$C$4:$C$1500=$C24)*('目标填报'!$D$4:$D$1500=$D24)*('目标填报'!$F$4:$F$1500="在手订单")*('目标填报'!$G$3:$R$3=$F$1)*'目标填报'!$G$4:$R$1500)) | Q24: =IF($B24="","",SUMPRODUCT(('目标填报'!$B$4:$B$1500=$B24)*('目标填报'!$C$4:$C$1500=$C24)*('目标填报'!$D$4:$D$1500=$D24)*('目标填报'!$F$4:$F$1500="在手订单目标")*('目标填报'!$G$3:$R$3=$F$1)*'目标填报'!$G$4:$R$1500)) | R24: =IF($B24="","",IFERROR(P24/Q24,"")) | S24: =IF($B24="","",SUMPRODUCT(('目标填报'!$B$4:$B$1500=$B24)*('目标填报'!$C$4:$C$1500=$C24)*('目标填报'!$D$4:$D$1500=$D24)*('目标填报'!$F$4:$F$1500="目标客户机会")*('目标填报'!$G$3:$R$3=$F$1)*'目标填报'!$G$4:$R$1500)) | T24: =IF($B24="","",SUMPRODUCT(('目标填报'!$B$4:$B$1500=$B24)*('目标填报'!$C$4:$C$1500=$C24)*('目标填报'!$D$4:$D$1500=$D24)*('目标填报'!$F$4:$F$1500="目标客户机会目标")*('目标填报'!$G$3:$R$3=$F$1)*'目标填报'!$G$4:$R$1500)) | U24: =IF($B24="","",IFERROR(S24/T24,"")) | V24: =IF($B24="","",P24+S24) | W24: =IF($B24="","",M24-J24) | X24: =IF($B24="","",IFERROR(V24/W24,"")) | Y24: =IF($B24="","",V24-W24)
A25: =IF($B25="","",ROW()-3) | B25: =IF(21+1>COUNTA('维度字典'!$C$2:$C$200)*COUNTA('维度字典'!$A$2:$A$200)*COUNTA('维度字典'!$E$2:$E$200),"",INDEX('维度字典'!$C$2:$C$200,MOD(INT(21/(COUNTA('维度字典'!$E$2:$E$200)*COUNTA('维度字典'!$A$2:$A$200))),COUNTA('维度字典'!$C$2:$C$200))+1)) | C25: =IF($B25="","",INDEX('维度字典'!$A$2:$A$200,MOD(INT(21/COUNTA('维度字典'!$E$2:$E$200)),COUNTA('维度字典'!$A$2:$A$200))+1)) | D25: =IF($B25="","",INDEX('维度字典'!$E$2:$E$200,MOD(21,COUNTA('维度字典'!$E$2:$E$200))+1)) | E25: =IF($B25="","",SUMPRODUCT(('系统实绩导入'!$B$4:$B$1500=$B25)*('系统实绩导入'!$C$4:$C$1500=$C25)*('系统实绩导入'!$D$4:$D$1500=$D25)*('系统实绩导入'!$F$4:$F$1500="实绩销售额")*('系统实绩导入'!$G$3:$R$3=$F$1)*'系统实绩导入'!$G$4:$R$1500)) | F25: =IF($B25="","",SUMPRODUCT(('系统实绩导入'!$B$4:$B$1500=$B25)*('系统实绩导入'!$C$4:$C$1500=$C25)*('系统实绩导入'!$D$4:$D$1500=$D25)*('系统实绩导入'!$F$4:$F$1500="实绩毛利")*('系统实绩导入'!$G$3:$R$3=$F$1)*'系统实绩导入'!$G$4:$R$1500)) | G25: =IF($B25="","",IFERROR(F25/E25,"")) | H25: =IF($B25="","",SUMPRODUCT(('目标填报'!$B$4:$B$1500=$B25)*('目标填报'!$C$4:$C$1500=$C25)*('目标填报'!$D$4:$D$1500=$D25)*('目标填报'!$F$4:$F$1500="销售目标额")*('目标填报'!$G$3:$R$3=$F$1)*'目标填报'!$G$4:$R$1500)) | I25: =IF($B25="","",IFERROR(E25/H25,"")) | J25: =IF($B25="","",SUMPRODUCT(('系统实绩导入'!$B$4:$B$1500=$B25)*('系统实绩导入'!$C$4:$C$1500=$C25)*('系统实绩导入'!$D$4:$D$1500=$D25)*('系统实绩导入'!$F$4:$F$1500="实绩销售额")*('系统实绩导入'!$G$3:$R$3<=$F$1)*'系统实绩导入'!$G$4:$R$1500)) | K25: =IF($B25="","",SUMPRODUCT(('系统实绩导入'!$B$4:$B$1500=$B25)*('系统实绩导入'!$C$4:$C$1500=$C25)*('系统实绩导入'!$D$4:$D$1500=$D25)*('系统实绩导入'!$F$4:$F$1500="实绩毛利")*('系统实绩导入'!$G$3:$R$3<=$F$1)*'系统实绩导入'!$G$4:$R$1500)) | L25: =IF($B25="","",IFERROR(K25/J25,"")) | M25: =IF($B25="","",SUMIFS('目标填报'!$S$4:$S$1500,'目标填报'!$B$4:$B$1500,$B25,'目标填报'!$C$4:$C$1500,$C25,'目标填报'!$D$4:$D$1500,$D25,'目标填报'!$F$4:$F$1500,"销售目标额")) | N25: =IF($B25="","",IFERROR(J25/M25,"")) | O25: =IF($B25="","",J25-M25) | P25: =IF($B25="","",SUMPRODUCT(('目标填报'!$B$4:$B$1500=$B25)*('目标填报'!$C$4:$C$1500=$C25)*('目标填报'!$D$4:$D$1500=$D25)*('目标填报'!$F$4:$F$1500="在手订单")*('目标填报'!$G$3:$R$3=$F$1)*'目标填报'!$G$4:$R$1500)) | Q25: =IF($B25="","",SUMPRODUCT(('目标填报'!$B$4:$B$1500=$B25)*('目标填报'!$C$4:$C$1500=$C25)*('目标填报'!$D$4:$D$1500=$D25)*('目标填报'!$F$4:$F$1500="在手订单目标")*('目标填报'!$G$3:$R$3=$F$1)*'目标填报'!$G$4:$R$1500)) | R25: =IF($B25="","",IFERROR(P25/Q25,"")) | S25: =IF($B25="","",SUMPRODUCT(('目标填报'!$B$4:$B$1500=$B25)*('目标填报'!$C$4:$C$1500=$C25)*('目标填报'!$D$4:$D$1500=$D25)*('目标填报'!$F$4:$F$1500="目标客户机会")*('目标填报'!$G$3:$R$3=$F$1)*'目标填报'!$G$4:$R$1500)) | T25: =IF($B25="","",SUMPRODUCT(('目标填报'!$B$4:$B$1500=$B25)*('目标填报'!$C$4:$C$1500=$C25)*('目标填报'!$D$4:$D$1500=$D25)*('目标填报'!$F$4:$F$1500="目标客户机会目标")*('目标填报'!$G$3:$R$3=$F$1)*'目标填报'!$G$4:$R$1500)) | U25: =IF($B25="","",IFERROR(S25/T25,"")) | V25: =IF($B25="","",P25+S25) | W25: =IF($B25="","",M25-J25) | X25: =IF($B25="","",IFERROR(V25/W25,"")) | Y25: =IF($B25="","",V25-W25)
A26: =IF($B26="","",ROW()-3) | B26: =IF(22+1>COUNTA('维度字典'!$C$2:$C$200)*COUNTA('维度字典'!$A$2:$A$200)*COUNTA('维度字典'!$E$2:$E$200),"",INDEX('维度字典'!$C$2:$C$200,MOD(INT(22/(COUNTA('维度字典'!$E$2:$E$200)*COUNTA('维度字典'!$A$2:$A$200))),COUNTA('维度字典'!$C$2:$C$200))+1)) | C26: =IF($B26="","",INDEX('维度字典'!$A$2:$A$200,MOD(INT(22/COUNTA('维度字典'!$E$2:$E$200)),COUNTA('维度字典'!$A$2:$A$200))+1)) | D26: =IF($B26="","",INDEX('维度字典'!$E$2:$E$200,MOD(22,COUNTA('维度字典'!$E$2:$E$200))+1)) | E26: =IF($B26="","",SUMPRODUCT(('系统实绩导入'!$B$4:$B$1500=$B26)*('系统实绩导入'!$C$4:$C$1500=$C26)*('系统实绩导入'!$D$4:$D$1500=$D26)*('系统实绩导入'!$F$4:$F$1500="实绩销售额")*('系统实绩导入'!$G$3:$R$3=$F$1)*'系统实绩导入'!$G$4:$R$1500)) | F26: =IF($B26="","",SUMPRODUCT(('系统实绩导入'!$B$4:$B$1500=$B26)*('系统实绩导入'!$C$4:$C$1500=$C26)*('系统实绩导入'!$D$4:$D$1500=$D26)*('系统实绩导入'!$F$4:$F$1500="实绩毛利")*('系统实绩导入'!$G$3:$R$3=$F$1)*'系统实绩导入'!$G$4:$R$1500)) | G26: =IF($B26="","",IFERROR(F26/E26,"")) | H26: =IF($B26="","",SUMPRODUCT(('目标填报'!$B$4:$B$1500=$B26)*('目标填报'!$C$4:$C$1500=$C26)*('目标填报'!$D$4:$D$1500=$D26)*('目标填报'!$F$4:$F$1500="销售目标额")*('目标填报'!$G$3:$R$3=$F$1)*'目标填报'!$G$4:$R$1500)) | I26: =IF($B26="","",IFERROR(E26/H26,"")) | J26: =IF($B26="","",SUMPRODUCT(('系统实绩导入'!$B$4:$B$1500=$B26)*('系统实绩导入'!$C$4:$C$1500=$C26)*('系统实绩导入'!$D$4:$D$1500=$D26)*('系统实绩导入'!$F$4:$F$1500="实绩销售额")*('系统实绩导入'!$G$3:$R$3<=$F$1)*'系统实绩导入'!$G$4:$R$1500)) | K26: =IF($B26="","",SUMPRODUCT(('系统实绩导入'!$B$4:$B$1500=$B26)*('系统实绩导入'!$C$4:$C$1500=$C26)*('系统实绩导入'!$D$4:$D$1500=$D26)*('系统实绩导入'!$F$4:$F$1500="实绩毛利")*('系统实绩导入'!$G$3:$R$3<=$F$1)*'系统实绩导入'!$G$4:$R$1500)) | L26: =IF($B26="","",IFERROR(K26/J26,"")) | M26: =IF($B26="","",SUMIFS('目标填报'!$S$4:$S$1500,'目标填报'!$B$4:$B$1500,$B26,'目标填报'!$C$4:$C$1500,$C26,'目标填报'!$D$4:$D$1500,$D26,'目标填报'!$F$4:$F$1500,"销售目标额")) | N26: =IF($B26="","",IFERROR(J26/M26,"")) | O26: =IF($B26="","",J26-M26) | P26: =IF($B26="","",SUMPRODUCT(('目标填报'!$B$4:$B$1500=$B26)*('目标填报'!$C$4:$C$1500=$C26)*('目标填报'!$D$4:$D$1500=$D26)*('目标填报'!$F$4:$F$1500="在手订单")*('目标填报'!$G$3:$R$3=$F$1)*'目标填报'!$G$4:$R$1500)) | Q26: =IF($B26="","",SUMPRODUCT(('目标填报'!$B$4:$B$1500=$B26)*('目标填报'!$C$4:$C$1500=$C26)*('目标填报'!$D$4:$D$1500=$D26)*('目标填报'!$F$4:$F$1500="在手订单目标")*('目标填报'!$G$3:$R$3=$F$1)*'目标填报'!$G$4:$R$1500)) | R26: =IF($B26="","",IFERROR(P26/Q26,"")) | S26: =IF($B26="","",SUMPRODUCT(('目标填报'!$B$4:$B$1500=$B26)*('目标填报'!$C$4:$C$1500=$C26)*('目标填报'!$D$4:$D$1500=$D26)*('目标填报'!$F$4:$F$1500="目标客户机会")*('目标填报'!$G$3:$R$3=$F$1)*'目标填报'!$G$4:$R$1500)) | T26: =IF($B26="","",SUMPRODUCT(('目标填报'!$B$4:$B$1500=$B26)*('目标填报'!$C$4:$C$1500=$C26)*('目标填报'!$D$4:$D$1500=$D26)*('目标填报'!$F$4:$F$1500="目标客户机会目标")*('目标填报'!$G$3:$R$3=$F$1)*'目标填报'!$G$4:$R$1500)) | U26: =IF($B26="","",IFERROR(S26/T26,"")) | V26: =IF($B26="","",P26+S26) | W26: =IF($B26="","",M26-J26) | X26: =IF($B26="","",IFERROR(V26/W26,"")) | Y26: =IF($B26="","",V26-W26)
A27: =IF($B27="","",ROW()-3) | B27: =IF(23+1>COUNTA('维度字典'!$C$2:$C$200)*COUNTA('维度字典'!$A$2:$A$200)*COUNTA('维度字典'!$E$2:$E$200),"",INDEX('维度字典'!$C$2:$C$200,MOD(INT(23/(COUNTA('维度字典'!$E$2:$E$200)*COUNTA('维度字典'!$A$2:$A$200))),COUNTA('维度字典'!$C$2:$C$200))+1)) | C27: =IF($B27="","",INDEX('维度字典'!$A$2:$A$200,MOD(INT(23/COUNTA('维度字典'!$E$2:$E$200)),COUNTA('维度字典'!$A$2:$A$200))+1)) | D27: =IF($B27="","",INDEX('维度字典'!$E$2:$E$200,MOD(23,COUNTA('维度字典'!$E$2:$E$200))+1)) | E27: =IF($B27="","",SUMPRODUCT(('系统实绩导入'!$B$4:$B$1500=$B27)*('系统实绩导入'!$C$4:$C$1500=$C27)*('系统实绩导入'!$D$4:$D$1500=$D27)*('系统实绩导入'!$F$4:$F$1500="实绩销售额")*('系统实绩导入'!$G$3:$R$3=$F$1)*'系统实绩导入'!$G$4:$R$1500)) | F27: =IF($B27="","",SUMPRODUCT(('系统实绩导入'!$B$4:$B$1500=$B27)*('系统实绩导入'!$C$4:$C$1500=$C27)*('系统实绩导入'!$D$4:$D$1500=$D27)*('系统实绩导入'!$F$4:$F$1500="实绩毛利")*('系统实绩导入'!$G$3:$R$3=$F$1)*'系统实绩导入'!$G$4:$R$1500)) | G27: =IF($B27="","",IFERROR(F27/E27,"")) | H27: =IF($B27="","",SUMPRODUCT(('目标填报'!$B$4:$B$1500=$B27)*('目标填报'!$C$4:$C$1500=$C27)*('目标填报'!$D$4:$D$1500=$D27)*('目标填报'!$F$4:$F$1500="销售目标额")*('目标填报'!$G$3:$R$3=$F$1)*'目标填报'!$G$4:$R$1500)) | I27: =IF($B27="","",IFERROR(E27/H27,"")) | J27: =IF($B27="","",SUMPRODUCT(('系统实绩导入'!$B$4:$B$1500=$B27)*('系统实绩导入'!$C$4:$C$1500=$C27)*('系统实绩导入'!$D$4:$D$1500=$D27)*('系统实绩导入'!$F$4:$F$1500="实绩销售额")*('系统实绩导入'!$G$3:$R$3<=$F$1)*'系统实绩导入'!$G$4:$R$1500)) | K27: =IF($B27="","",SUMPRODUCT(('系统实绩导入'!$B$4:$B$1500=$B27)*('系统实绩导入'!$C$4:$C$1500=$C27)*('系统实绩导入'!$D$4:$D$1500=$D27)*('系统实绩导入'!$F$4:$F$1500="实绩毛利")*('系统实绩导入'!$G$3:$R$3<=$F$1)*'系统实绩导入'!$G$4:$R$1500)) | L27: =IF($B27="","",IFERROR(K27/J27,"")) | M27: =IF($B27="","",SUMIFS('目标填报'!$S$4:$S$1500,'目标填报'!$B$4:$B$1500,$B27,'目标填报'!$C$4:$C$1500,$C27,'目标填报'!$D$4:$D$1500,$D27,'目标填报'!$F$4:$F$1500,"销售目标额")) | N27: =IF($B27="","",IFERROR(J27/M27,"")) | O27: =IF($B27="","",J27-M27) | P27: =IF($B27="","",SUMPRODUCT(('目标填报'!$B$4:$B$1500=$B27)*('目标填报'!$C$4:$C$1500=$C27)*('目标填报'!$D$4:$D$1500=$D27)*('目标填报'!$F$4:$F$1500="在手订单")*('目标填报'!$G$3:$R$3=$F$1)*'目标填报'!$G$4:$R$1500)) | Q27: =IF($B27="","",SUMPRODUCT(('目标填报'!$B$4:$B$1500=$B27)*('目标填报'!$C$4:$C$1500=$C27)*('目标填报'!$D$4:$D$1500=$D27)*('目标填报'!$F$4:$F$1500="在手订单目标")*('目标填报'!$G$3:$R$3=$F$1)*'目标填报'!$G$4:$R$1500)) | R27: =IF($B27="","",IFERROR(P27/Q27,"")) | S27: =IF($B27="","",SUMPRODUCT(('目标填报'!$B$4:$B$1500=$B27)*('目标填报'!$C$4:$C$1500=$C27)*('目标填报'!$D$4:$D$1500=$D27)*('目标填报'!$F$4:$F$1500="目标客户机会")*('目标填报'!$G$3:$R$3=$F$1)*'目标填报'!$G$4:$R$1500)) | T27: =IF($B27="","",SUMPRODUCT(('目标填报'!$B$4:$B$1500=$B27)*('目标填报'!$C$4:$C$1500=$C27)*('目标填报'!$D$4:$D$1500=$D27)*('目标填报'!$F$4:$F$1500="目标客户机会目标")*('目标填报'!$G$3:$R$3=$F$1)*'目标填报'!$G$4:$R$1500)) | U27: =IF($B27="","",IFERROR(S27/T27,"")) | V27: =IF($B27="","",P27+S27) | W27: =IF($B27="","",M27-J27) | X27: =IF($B27="","",IFERROR(V27/W27,"")) | Y27: =IF($B27="","",V27-W27)
A28: =IF($B28="","",ROW()-3) | B28: =IF(24+1>COUNTA('维度字典'!$C$2:$C$200)*COUNTA('维度字典'!$A$2:$A$200)*COUNTA('维度字典'!$E$2:$E$200),"",INDEX('维度字典'!$C$2:$C$200,MOD(INT(24/(COUNTA('维度字典'!$E$2:$E$200)*COUNTA('维度字典'!$A$2:$A$200))),COUNTA('维度字典'!$C$2:$C$200))+1)) | C28: =IF($B28="","",INDEX('维度字典'!$A$2:$A$200,MOD(INT(24/COUNTA('维度字典'!$E$2:$E$200)),COUNTA('维度字典'!$A$2:$A$200))+1)) | D28: =IF($B28="","",INDEX('维度字典'!$E$2:$E$200,MOD(24,COUNTA('维度字典'!$E$2:$E$200))+1)) | E28: =IF($B28="","",SUMPRODUCT(('系统实绩导入'!$B$4:$B$1500=$B28)*('系统实绩导入'!$C$4:$C$1500=$C28)*('系统实绩导入'!$D$4:$D$1500=$D28)*('系统实绩导入'!$F$4:$F$1500="实绩销售额")*('系统实绩导入'!$G$3:$R$3=$F$1)*'系统实绩导入'!$G$4:$R$1500)) | F28: =IF($B28="","",SUMPRODUCT(('系统实绩导入'!$B$4:$B$1500=$B28)*('系统实绩导入'!$C$4:$C$1500=$C28)*('系统实绩导入'!$D$4:$D$1500=$D28)*('系统实绩导入'!$F$4:$F$1500="实绩毛利")*('系统实绩导入'!$G$3:$R$3=$F$1)*'系统实绩导入'!$G$4:$R$1500)) | G28: =IF($B28="","",IFERROR(F28/E28,"")) | H28: =IF($B28="","",SUMPRODUCT(('目标填报'!$B$4:$B$1500=$B28)*('目标填报'!$C$4:$C$1500=$C28)*('目标填报'!$D$4:$D$1500=$D28)*('目标填报'!$F$4:$F$1500="销售目标额")*('目标填报'!$G$3:$R$3=$F$1)*'目标填报'!$G$4:$R$1500)) | I28: =IF($B28="","",IFERROR(E28/H28,"")) | J28: =IF($B28="","",SUMPRODUCT(('系统实绩导入'!$B$4:$B$1500=$B28)*('系统实绩导入'!$C$4:$C$1500=$C28)*('系统实绩导入'!$D$4:$D$1500=$D28)*('系统实绩导入'!$F$4:$F$1500="实绩销售额")*('系统实绩导入'!$G$3:$R$3<=$F$1)*'系统实绩导入'!$G$4:$R$1500)) | K28: =IF($B28="","",SUMPRODUCT(('系统实绩导入'!$B$4:$B$1500=$B28)*('系统实绩导入'!$C$4:$C$1500=$C28)*('系统实绩导入'!$D$4:$D$1500=$D28)*('系统实绩导入'!$F$4:$F$1500="实绩毛利")*('系统实绩导入'!$G$3:$R$3<=$F$1)*'系统实绩导入'!$G$4:$R$1500)) | L28: =IF($B28="","",IFERROR(K28/J28,"")) | M28: =IF($B28="","",SUMIFS('目标填报'!$S$4:$S$1500,'目标填报'!$B$4:$B$1500,$B28,'目标填报'!$C$4:$C$1500,$C28,'目标填报'!$D$4:$D$1500,$D28,'目标填报'!$F$4:$F$1500,"销售目标额")) | N28: =IF($B28="","",IFERROR(J28/M28,"")) | O28: =IF($B28="","",J28-M28) | P28: =IF($B28="","",SUMPRODUCT(('目标填报'!$B$4:$B$1500=$B28)*('目标填报'!$C$4:$C$1500=$C28)*('目标填报'!$D$4:$D$1500=$D28)*('目标填报'!$F$4:$F$1500="在手订单")*('目标填报'!$G$3:$R$3=$F$1)*'目标填报'!$G$4:$R$1500)) | Q28: =IF($B28="","",SUMPRODUCT(('目标填报'!$B$4:$B$1500=$B28)*('目标填报'!$C$4:$C$1500=$C28)*('目标填报'!$D$4:$D$1500=$D28)*('目标填报'!$F$4:$F$1500="在手订单目标")*('目标填报'!$G$3:$R$3=$F$1)*'目标填报'!$G$4:$R$1500)) | R28: =IF($B28="","",IFERROR(P28/Q28,"")) | S28: =IF($B28="","",SUMPRODUCT(('目标填报'!$B$4:$B$1500=$B28)*('目标填报'!$C$4:$C$1500=$C28)*('目标填报'!$D$4:$D$1500=$D28)*('目标填报'!$F$4:$F$1500="目标客户机会")*('目标填报'!$G$3:$R$3=$F$1)*'目标填报'!$G$4:$R$1500)) | T28: =IF($B28="","",SUMPRODUCT(('目标填报'!$B$4:$B$1500=$B28)*('目标填报'!$C$4:$C$1500=$C28)*('目标填报'!$D$4:$D$1500=$D28)*('目标填报'!$F$4:$F$1500="目标客户机会目标")*('目标填报'!$G$3:$R$3=$F$1)*'目标填报'!$G$4:$R$1500)) | U28: =IF($B28="","",IFERROR(S28/T28,"")) | V28: =IF($B28="","",P28+S28) | W28: =IF($B28="","",M28-J28) | X28: =IF($B28="","",IFERROR(V28/W28,"")) | Y28: =IF($B28="","",V28-W28)
A29: =IF($B29="","",ROW()-3) | B29: =IF(25+1>COUNTA('维度字典'!$C$2:$C$200)*COUNTA('维度字典'!$A$2:$A$200)*COUNTA('维度字典'!$E$2:$E$200),"",INDEX('维度字典'!$C$2:$C$200,MOD(INT(25/(COUNTA('维度字典'!$E$2:$E$200)*COUNTA('维度字典'!$A$2:$A$200))),COUNTA('维度字典'!$C$2:$C$200))+1)) | C29: =IF($B29="","",INDEX('维度字典'!$A$2:$A$200,MOD(INT(25/COUNTA('维度字典'!$E$2:$E$200)),COUNTA('维度字典'!$A$2:$A$200))+1)) | D29: =IF($B29="","",INDEX('维度字典'!$E$2:$E$200,MOD(25,COUNTA('维度字典'!$E$2:$E$200))+1)) | E29: =IF($B29="","",SUMPRODUCT(('系统实绩导入'!$B$4:$B$1500=$B29)*('系统实绩导入'!$C$4:$C$1500=$C29)*('系统实绩导入'!$D$4:$D$1500=$D29)*('系统实绩导入'!$F$4:$F$1500="实绩销售额")*('系统实绩导入'!$G$3:$R$3=$F$1)*'系统实绩导入'!$G$4:$R$1500)) | F29: =IF($B29="","",SUMPRODUCT(('系统实绩导入'!$B$4:$B$1500=$B29)*('系统实绩导入'!$C$4:$C$1500=$C29)*('系统实绩导入'!$D$4:$D$1500=$D29)*('系统实绩导入'!$F$4:$F$1500="实绩毛利")*('系统实绩导入'!$G$3:$R$3=$F$1)*'系统实绩导入'!$G$4:$R$1500)) | G29: =IF($B29="","",IFERROR(F29/E29,"")) | H29: =IF($B29="","",SUMPRODUCT(('目标填报'!$B$4:$B$1500=$B29)*('目标填报'!$C$4:$C$1500=$C29)*('目标填报'!$D$4:$D$1500=$D29)*('目标填报'!$F$4:$F$1500="销售目标额")*('目标填报'!$G$3:$R$3=$F$1)*'目标填报'!$G$4:$R$1500)) | I29: =IF($B29="","",IFERROR(E29/H29,"")) | J29: =IF($B29="","",SUMPRODUCT(('系统实绩导入'!$B$4:$B$1500=$B29)*('系统实绩导入'!$C$4:$C$1500=$C29)*('系统实绩导入'!$D$4:$D$1500=$D29)*('系统实绩导入'!$F$4:$F$1500="实绩销售额")*('系统实绩导入'!$G$3:$R$3<=$F$1)*'系统实绩导入'!$G$4:$R$1500)) | K29: =IF($B29="","",SUMPRODUCT(('系统实绩导入'!$B$4:$B$1500=$B29)*('系统实绩导入'!$C$4:$C$1500=$C29)*('系统实绩导入'!$D$4:$D$1500=$D29)*('系统实绩导入'!$F$4:$F$1500="实绩毛利")*('系统实绩导入'!$G$3:$R$3<=$F$1)*'系统实绩导入'!$G$4:$R$1500)) | L29: =IF($B29="","",IFERROR(K29/J29,"")) | M29: =IF($B29="","",SUMIFS('目标填报'!$S$4:$S$1500,'目标填报'!$B$4:$B$1500,$B29,'目标填报'!$C$4:$C$1500,$C29,'目标填报'!$D$4:$D$1500,$D29,'目标填报'!$F$4:$F$1500,"销售目标额")) | N29: =IF($B29="","",IFERROR(J29/M29,"")) | O29: =IF($B29="","",J29-M29) | P29: =IF($B29="","",SUMPRODUCT(('目标填报'!$B$4:$B$1500=$B29)*('目标填报'!$C$4:$C$1500=$C29)*('目标填报'!$D$4:$D$1500=$D29)*('目标填报'!$F$4:$F$1500="在手订单")*('目标填报'!$G$3:$R$3=$F$1)*'目标填报'!$G$4:$R$1500)) | Q29: =IF($B29="","",SUMPRODUCT(('目标填报'!$B$4:$B$1500=$B29)*('目标填报'!$C$4:$C$1500=$C29)*('目标填报'!$D$4:$D$1500=$D29)*('目标填报'!$F$4:$F$1500="在手订单目标")*('目标填报'!$G$3:$R$3=$F$1)*'目标填报'!$G$4:$R$1500)) | R29: =IF($B29="","",IFERROR(P29/Q29,"")) | S29: =IF($B29="","",SUMPRODUCT(('目标填报'!$B$4:$B$1500=$B29)*('目标填报'!$C$4:$C$1500=$C29)*('目标填报'!$D$4:$D$1500=$D29)*('目标填报'!$F$4:$F$1500="目标客户机会")*('目标填报'!$G$3:$R$3=$F$1)*'目标填报'!$G$4:$R$1500)) | T29: =IF($B29="","",SUMPRODUCT(('目标填报'!$B$4:$B$1500=$B29)*('目标填报'!$C$4:$C$1500=$C29)*('目标填报'!$D$4:$D$1500=$D29)*('目标填报'!$F$4:$F$1500="目标客户机会目标")*('目标填报'!$G$3:$R$3=$F$1)*'目标填报'!$G$4:$R$1500)) | U29: =IF($B29="","",IFERROR(S29/T29,"")) | V29: =IF($B29="","",P29+S29) | W29: =IF($B29="","",M29-J29) | X29: =IF($B29="","",IFERROR(V29/W29,"")) | Y29: =IF($B29="","",V29-W29)
A30: =IF($B30="","",ROW()-3) | B30: =IF(26+1>COUNTA('维度字典'!$C$2:$C$200)*COUNTA('维度字典'!$A$2:$A$200)*COUNTA('维度字典'!$E$2:$E$200),"",INDEX('维度字典'!$C$2:$C$200,MOD(INT(26/(COUNTA('维度字典'!$E$2:$E$200)*COUNTA('维度字典'!$A$2:$A$200))),COUNTA('维度字典'!$C$2:$C$200))+1)) | C30: =IF($B30="","",INDEX('维度字典'!$A$2:$A$200,MOD(INT(26/COUNTA('维度字典'!$E$2:$E$200)),COUNTA('维度字典'!$A$2:$A$200))+1)) | D30: =IF($B30="","",INDEX('维度字典'!$E$2:$E$200,MOD(26,COUNTA('维度字典'!$E$2:$E$200))+1)) | E30: =IF($B30="","",SUMPRODUCT(('系统实绩导入'!$B$4:$B$1500=$B30)*('系统实绩导入'!$C$4:$C$1500=$C30)*('系统实绩导入'!$D$4:$D$1500=$D30)*('系统实绩导入'!$F$4:$F$1500="实绩销售额")*('系统实绩导入'!$G$3:$R$3=$F$1)*'系统实绩导入'!$G$4:$R$1500)) | F30: =IF($B30="","",SUMPRODUCT(('系统实绩导入'!$B$4:$B$1500=$B30)*('系统实绩导入'!$C$4:$C$1500=$C30)*('系统实绩导入'!$D$4:$D$1500=$D30)*('系统实绩导入'!$F$4:$F$1500="实绩毛利")*('系统实绩导入'!$G$3:$R$3=$F$1)*'系统实绩导入'!$G$4:$R$1500)) | G30: =IF($B30="","",IFERROR(F30/E30,"")) | H30: =IF($B30="","",SUMPRODUCT(('目标填报'!$B$4:$B$1500=$B30)*('目标填报'!$C$4:$C$1500=$C30)*('目标填报'!$D$4:$D$1500=$D30)*('目标填报'!$F$4:$F$1500="销售目标额")*('目标填报'!$G$3:$R$3=$F$1)*'目标填报'!$G$4:$R$1500)) | I30: =IF($B30="","",IFERROR(E30/H30,"")) | J30: =IF($B30="","",SUMPRODUCT(('系统实绩导入'!$B$4:$B$1500=$B30)*('系统实绩导入'!$C$4:$C$1500=$C30)*('系统实绩导入'!$D$4:$D$1500=$D30)*('系统实绩导入'!$F$4:$F$1500="实绩销售额")*('系统实绩导入'!$G$3:$R$3<=$F$1)*'系统实绩导入'!$G$4:$R$1500)) | K30: =IF($B30="","",SUMPRODUCT(('系统实绩导入'!$B$4:$B$1500=$B30)*('系统实绩导入'!$C$4:$C$1500=$C30)*('系统实绩导入'!$D$4:$D$1500=$D30)*('系统实绩导入'!$F$4:$F$1500="实绩毛利")*('系统实绩导入'!$G$3:$R$3<=$F$1)*'系统实绩导入'!$G$4:$R$1500)) | L30: =IF($B30="","",IFERROR(K30/J30,"")) | M30: =IF($B30="","",SUMIFS('目标填报'!$S$4:$S$1500,'目标填报'!$B$4:$B$1500,$B30,'目标填报'!$C$4:$C$1500,$C30,'目标填报'!$D$4:$D$1500,$D30,'目标填报'!$F$4:$F$1500,"销售目标额")) | N30: =IF($B30="","",IFERROR(J30/M30,"")) | O30: =IF($B30="","",J30-M30) | P30: =IF($B30="","",SUMPRODUCT(('目标填报'!$B$4:$B$1500=$B30)*('目标填报'!$C$4:$C$1500=$C30)*('目标填报'!$D$4:$D$1500=$D30)*('目标填报'!$F$4:$F$1500="在手订单")*('目标填报'!$G$3:$R$3=$F$1)*'目标填报'!$G$4:$R$1500)) | Q30: =IF($B30="","",SUMPRODUCT(('目标填报'!$B$4:$B$1500=$B30)*('目标填报'!$C$4:$C$1500=$C30)*('目标填报'!$D$4:$D$1500=$D30)*('目标填报'!$F$4:$F$1500="在手订单目标")*('目标填报'!$G$3:$R$3=$F$1)*'目标填报'!$G$4:$R$1500)) | R30: =IF($B30="","",IFERROR(P30/Q30,"")) | S30: =IF($B30="","",SUMPRODUCT(('目标填报'!$B$4:$B$1500=$B30)*('目标填报'!$C$4:$C$1500=$C30)*('目标填报'!$D$4:$D$1500=$D30)*('目标填报'!$F$4:$F$1500="目标客户机会")*('目标填报'!$G$3:$R$3=$F$1)*'目标填报'!$G$4:$R$1500)) | T30: =IF($B30="","",SUMPRODUCT(('目标填报'!$B$4:$B$1500=$B30)*('目标填报'!$C$4:$C$1500=$C30)*('目标填报'!$D$4:$D$1500=$D30)*('目标填报'!$F$4:$F$1500="目标客户机会目标")*('目标填报'!$G$3:$R$3=$F$1)*'目标填报'!$G$4:$R$1500)) | U30: =IF($B30="","",IFERROR(S30/T30,"")) | V30: =IF($B30="","",P30+S30) | W30: =IF($B30="","",M30-J30) | X30: =IF($B30="","",IFERROR(V30/W30,"")) | Y30: =IF($B30="","",V30-W30)
A31: =IF($B31="","",ROW()-3) | B31: =IF(27+1>COUNTA('维度字典'!$C$2:$C$200)*COUNTA('维度字典'!$A$2:$A$200)*COUNTA('维度字典'!$E$2:$E$200),"",INDEX('维度字典'!$C$2:$C$200,MOD(INT(27/(COUNTA('维度字典'!$E$2:$E$200)*COUNTA('维度字典'!$A$2:$A$200))),COUNTA('维度字典'!$C$2:$C$200))+1)) | C31: =IF($B31="","",INDEX('维度字典'!$A$2:$A$200,MOD(INT(27/COUNTA('维度字典'!$E$2:$E$200)),COUNTA('维度字典'!$A$2:$A$200))+1)) | D31: =IF($B31="","",INDEX('维度字典'!$E$2:$E$200,MOD(27,COUNTA('维度字典'!$E$2:$E$200))+1)) | E31: =IF($B31="","",SUMPRODUCT(('系统实绩导入'!$B$4:$B$1500=$B31)*('系统实绩导入'!$C$4:$C$1500=$C31)*('系统实绩导入'!$D$4:$D$1500=$D31)*('系统实绩导入'!$F$4:$F$1500="实绩销售额")*('系统实绩导入'!$G$3:$R$3=$F$1)*'系统实绩导入'!$G$4:$R$1500)) | F31: =IF($B31="","",SUMPRODUCT(('系统实绩导入'!$B$4:$B$1500=$B31)*('系统实绩导入'!$C$4:$C$1500=$C31)*('系统实绩导入'!$D$4:$D$1500=$D31)*('系统实绩导入'!$F$4:$F$1500="实绩毛利")*('系统实绩导入'!$G$3:$R$3=$F$1)*'系统实绩导入'!$G$4:$R$1500)) | G31: =IF($B31="","",IFERROR(F31/E31,"")) | H31: =IF($B31="","",SUMPRODUCT(('目标填报'!$B$4:$B$1500=$B31)*('目标填报'!$C$4:$C$1500=$C31)*('目标填报'!$D$4:$D$1500=$D31)*('目标填报'!$F$4:$F$1500="销售目标额")*('目标填报'!$G$3:$R$3=$F$1)*'目标填报'!$G$4:$R$1500)) | I31: =IF($B31="","",IFERROR(E31/H31,"")) | J31: =IF($B31="","",SUMPRODUCT(('系统实绩导入'!$B$4:$B$1500=$B31)*('系统实绩导入'!$C$4:$C$1500=$C31)*('系统实绩导入'!$D$4:$D$1500=$D31)*('系统实绩导入'!$F$4:$F$1500="实绩销售额")*('系统实绩导入'!$G$3:$R$3<=$F$1)*'系统实绩导入'!$G$4:$R$1500)) | K31: =IF($B31="","",SUMPRODUCT(('系统实绩导入'!$B$4:$B$1500=$B31)*('系统实绩导入'!$C$4:$C$1500=$C31)*('系统实绩导入'!$D$4:$D$1500=$D31)*('系统实绩导入'!$F$4:$F$1500="实绩毛利")*('系统实绩导入'!$G$3:$R$3<=$F$1)*'系统实绩导入'!$G$4:$R$1500)) | L31: =IF($B31="","",IFERROR(K31/J31,"")) | M31: =IF($B31="","",SUMIFS('目标填报'!$S$4:$S$1500,'目标填报'!$B$4:$B$1500,$B31,'目标填报'!$C$4:$C$1500,$C31,'目标填报'!$D$4:$D$1500,$D31,'目标填报'!$F$4:$F$1500,"销售目标额")) | N31: =IF($B31="","",IFERROR(J31/M31,"")) | O31: =IF($B31="","",J31-M31) | P31: =IF($B31="","",SUMPRODUCT(('目标填报'!$B$4:$B$1500=$B31)*('目标填报'!$C$4:$C$1500=$C31)*('目标填报'!$D$4:$D$1500=$D31)*('目标填报'!$F$4:$F$1500="在手订单")*('目标填报'!$G$3:$R$3=$F$1)*'目标填报'!$G$4:$R$1500)) | Q31: =IF($B31="","",SUMPRODUCT(('目标填报'!$B$4:$B$1500=$B31)*('目标填报'!$C$4:$C$1500=$C31)*('目标填报'!$D$4:$D$1500=$D31)*('目标填报'!$F$4:$F$1500="在手订单目标")*('目标填报'!$G$3:$R$3=$F$1)*'目标填报'!$G$4:$R$1500)) | R31: =IF($B31="","",IFERROR(P31/Q31,"")) | S31: =IF($B31="","",SUMPRODUCT(('目标填报'!$B$4:$B$1500=$B31)*('目标填报'!$C$4:$C$1500=$C31)*('目标填报'!$D$4:$D$1500=$D31)*('目标填报'!$F$4:$F$1500="目标客户机会")*('目标填报'!$G$3:$R$3=$F$1)*'目标填报'!$G$4:$R$1500)) | T31: =IF($B31="","",SUMPRODUCT(('目标填报'!$B$4:$B$1500=$B31)*('目标填报'!$C$4:$C$1500=$C31)*('目标填报'!$D$4:$D$1500=$D31)*('目标填报'!$F$4:$F$1500="目标客户机会目标")*('目标填报'!$G$3:$R$3=$F$1)*'目标填报'!$G$4:$R$1500)) | U31: =IF($B31="","",IFERROR(S31/T31,"")) | V31: =IF($B31="","",P31+S31) | W31: =IF($B31="","",M31-J31) | X31: =IF($B31="","",IFERROR(V31/W31,"")) | Y31: =IF($B31="","",V31-W31)
A32: =IF($B32="","",ROW()-3) | B32: =IF(28+1>COUNTA('维度字典'!$C$2:$C$200)*COUNTA('维度字典'!$A$2:$A$200)*COUNTA('维度字典'!$E$2:$E$200),"",INDEX('维度字典'!$C$2:$C$200,MOD(INT(28/(COUNTA('维度字典'!$E$2:$E$200)*COUNTA('维度字典'!$A$2:$A$200))),COUNTA('维度字典'!$C$2:$C$200))+1)) | C32: =IF($B32="","",INDEX('维度字典'!$A$2:$A$200,MOD(INT(28/COUNTA('维度字典'!$E$2:$E$200)),COUNTA('维度字典'!$A$2:$A$200))+1)) | D32: =IF($B32="","",INDEX('维度字典'!$E$2:$E$200,MOD(28,COUNTA('维度字典'!$E$2:$E$200))+1)) | E32: =IF($B32="","",SUMPRODUCT(('系统实绩导入'!$B$4:$B$1500=$B32)*('系统实绩导入'!$C$4:$C$1500=$C32)*('系统实绩导入'!$D$4:$D$1500=$D32)*('系统实绩导入'!$F$4:$F$1500="实绩销售额")*('系统实绩导入'!$G$3:$R$3=$F$1)*'系统实绩导入'!$G$4:$R$1500)) | F32: =IF($B32="","",SUMPRODUCT(('系统实绩导入'!$B$4:$B$1500=$B32)*('系统实绩导入'!$C$4:$C$1500=$C32)*('系统实绩导入'!$D$4:$D$1500=$D32)*('系统实绩导入'!$F$4:$F$1500="实绩毛利")*('系统实绩导入'!$G$3:$R$3=$F$1)*'系统实绩导入'!$G$4:$R$1500)) | G32: =IF($B32="","",IFERROR(F32/E32,"")) | H32: =IF($B32="","",SUMPRODUCT(('目标填报'!$B$4:$B$1500=$B32)*('目标填报'!$C$4:$C$1500=$C32)*('目标填报'!$D$4:$D$1500=$D32)*('目标填报'!$F$4:$F$1500="销售目标额")*('目标填报'!$G$3:$R$3=$F$1)*'目标填报'!$G$4:$R$1500)) | I32: =IF($B32="","",IFERROR(E32/H32,"")) | J32: =IF($B32="","",SUMPRODUCT(('系统实绩导入'!$B$4:$B$1500=$B32)*('系统实绩导入'!$C$4:$C$1500=$C32)*('系统实绩导入'!$D$4:$D$1500=$D32)*('系统实绩导入'!$F$4:$F$1500="实绩销售额")*('系统实绩导入'!$G$3:$R$3<=$F$1)*'系统实绩导入'!$G$4:$R$1500)) | K32: =IF($B32="","",SUMPRODUCT(('系统实绩导入'!$B$4:$B$1500=$B32)*('系统实绩导入'!$C$4:$C$1500=$C32)*('系统实绩导入'!$D$4:$D$1500=$D32)*('系统实绩导入'!$F$4:$F$1500="实绩毛利")*('系统实绩导入'!$G$3:$R$3<=$F$1)*'系统实绩导入'!$G$4:$R$1500)) | L32: =IF($B32="","",IFERROR(K32/J32,"")) | M32: =IF($B32="","",SUMIFS('目标填报'!$S$4:$S$1500,'目标填报'!$B$4:$B$1500,$B32,'目标填报'!$C$4:$C$1500,$C32,'目标填报'!$D$4:$D$1500,$D32,'目标填报'!$F$4:$F$1500,"销售目标额")) | N32: =IF($B32="","",IFERROR(J32/M32,"")) | O32: =IF($B32="","",J32-M32) | P32: =IF($B32="","",SUMPRODUCT(('目标填报'!$B$4:$B$1500=$B32)*('目标填报'!$C$4:$C$1500=$C32)*('目标填报'!$D$4:$D$1500=$D32)*('目标填报'!$F$4:$F$1500="在手订单")*('目标填报'!$G$3:$R$3=$F$1)*'目标填报'!$G$4:$R$1500)) | Q32: =IF($B32="","",SUMPRODUCT(('目标填报'!$B$4:$B$1500=$B32)*('目标填报'!$C$4:$C$1500=$C32)*('目标填报'!$D$4:$D$1500=$D32)*('目标填报'!$F$4:$F$1500="在手订单目标")*('目标填报'!$G$3:$R$3=$F$1)*'目标填报'!$G$4:$R$1500)) | R32: =IF($B32="","",IFERROR(P32/Q32,"")) | S32: =IF($B32="","",SUMPRODUCT(('目标填报'!$B$4:$B$1500=$B32)*('目标填报'!$C$4:$C$1500=$C32)*('目标填报'!$D$4:$D$1500=$D32)*('目标填报'!$F$4:$F$1500="目标客户机会")*('目标填报'!$G$3:$R$3=$F$1)*'目标填报'!$G$4:$R$1500)) | T32: =IF($B32="","",SUMPRODUCT(('目标填报'!$B$4:$B$1500=$B32)*('目标填报'!$C$4:$C$1500=$C32)*('目标填报'!$D$4:$D$1500=$D32)*('目标填报'!$F$4:$F$1500="目标客户机会目标")*('目标填报'!$G$3:$R$3=$F$1)*'目标填报'!$G$4:$R$1500)) | U32: =IF($B32="","",IFERROR(S32/T32,"")) | V32: =IF($B32="","",P32+S32) | W32: =IF($B32="","",M32-J32) | X32: =IF($B32="","",IFERROR(V32/W32,"")) | Y32: =IF($B32="","",V32-W32)
A33: =IF($B33="","",ROW()-3) | B33: =IF(29+1>COUNTA('维度字典'!$C$2:$C$200)*COUNTA('维度字典'!$A$2:$A$200)*COUNTA('维度字典'!$E$2:$E$200),"",INDEX('维度字典'!$C$2:$C$200,MOD(INT(29/(COUNTA('维度字典'!$E$2:$E$200)*COUNTA('维度字典'!$A$2:$A$200))),COUNTA('维度字典'!$C$2:$C$200))+1)) | C33: =IF($B33="","",INDEX('维度字典'!$A$2:$A$200,MOD(INT(29/COUNTA('维度字典'!$E$2:$E$200)),COUNTA('维度字典'!$A$2:$A$200))+1)) | D33: =IF($B33="","",INDEX('维度字典'!$E$2:$E$200,MOD(29,COUNTA('维度字典'!$E$2:$E$200))+1)) | E33: =IF($B33="","",SUMPRODUCT(('系统实绩导入'!$B$4:$B$1500=$B33)*('系统实绩导入'!$C$4:$C$1500=$C33)*('系统实绩导入'!$D$4:$D$1500=$D33)*('系统实绩导入'!$F$4:$F$1500="实绩销售额")*('系统实绩导入'!$G$3:$R$3=$F$1)*'系统实绩导入'!$G$4:$R$1500)) | F33: =IF($B33="","",SUMPRODUCT(('系统实绩导入'!$B$4:$B$1500=$B33)*('系统实绩导入'!$C$4:$C$1500=$C33)*('系统实绩导入'!$D$4:$D$1500=$D33)*('系统实绩导入'!$F$4:$F$1500="实绩毛利")*('系统实绩导入'!$G$3:$R$3=$F$1)*'系统实绩导入'!$G$4:$R$1500)) | G33: =IF($B33="","",IFERROR(F33/E33,"")) | H33: =IF($B33="","",SUMPRODUCT(('目标填报'!$B$4:$B$1500=$B33)*('目标填报'!$C$4:$C$1500=$C33)*('目标填报'!$D$4:$D$1500=$D33)*('目标填报'!$F$4:$F$1500="销售目标额")*('目标填报'!$G$3:$R$3=$F$1)*'目标填报'!$G$4:$R$1500)) | I33: =IF($B33="","",IFERROR(E33/H33,"")) | J33: =IF($B33="","",SUMPRODUCT(('系统实绩导入'!$B$4:$B$1500=$B33)*('系统实绩导入'!$C$4:$C$1500=$C33)*('系统实绩导入'!$D$4:$D$1500=$D33)*('系统实绩导入'!$F$4:$F$1500="实绩销售额")*('系统实绩导入'!$G$3:$R$3<=$F$1)*'系统实绩导入'!$G$4:$R$1500)) | K33: =IF($B33="","",SUMPRODUCT(('系统实绩导入'!$B$4:$B$1500=$B33)*('系统实绩导入'!$C$4:$C$1500=$C33)*('系统实绩导入'!$D$4:$D$1500=$D33)*('系统实绩导入'!$F$4:$F$1500="实绩毛利")*('系统实绩导入'!$G$3:$R$3<=$F$1)*'系统实绩导入'!$G$4:$R$1500)) | L33: =IF($B33="","",IFERROR(K33/J33,"")) | M33: =IF($B33="","",SUMIFS('目标填报'!$S$4:$S$1500,'目标填报'!$B$4:$B$1500,$B33,'目标填报'!$C$4:$C$1500,$C33,'目标填报'!$D$4:$D$1500,$D33,'目标填报'!$F$4:$F$1500,"销售目标额")) | N33: =IF($B33="","",IFERROR(J33/M33,"")) | O33: =IF($B33="","",J33-M33) | P33: =IF($B33="","",SUMPRODUCT(('目标填报'!$B$4:$B$1500=$B33)*('目标填报'!$C$4:$C$1500=$C33)*('目标填报'!$D$4:$D$1500=$D33)*('目标填报'!$F$4:$F$1500="在手订单")*('目标填报'!$G$3:$R$3=$F$1)*'目标填报'!$G$4:$R$1500)) | Q33: =IF($B33="","",SUMPRODUCT(('目标填报'!$B$4:$B$1500=$B33)*('目标填报'!$C$4:$C$1500=$C33)*('目标填报'!$D$4:$D$1500=$D33)*('目标填报'!$F$4:$F$1500="在手订单目标")*('目标填报'!$G$3:$R$3=$F$1)*'目标填报'!$G$4:$R$1500)) | R33: =IF($B33="","",IFERROR(P33/Q33,"")) | S33: =IF($B33="","",SUMPRODUCT(('目标填报'!$B$4:$B$1500=$B33)*('目标填报'!$C$4:$C$1500=$C33)*('目标填报'!$D$4:$D$1500=$D33)*('目标填报'!$F$4:$F$1500="目标客户机会")*('目标填报'!$G$3:$R$3=$F$1)*'目标填报'!$G$4:$R$1500)) | T33: =IF($B33="","",SUMPRODUCT(('目标填报'!$B$4:$B$1500=$B33)*('目标填报'!$C$4:$C$1500=$C33)*('目标填报'!$D$4:$D$1500=$D33)*('目标填报'!$F$4:$F$1500="目标客户机会目标")*('目标填报'!$G$3:$R$3=$F$1)*'目标填报'!$G$4:$R$1500)) | U33: =IF($B33="","",IFERROR(S33/T33,"")) | V33: =IF($B33="","",P33+S33) | W33: =IF($B33="","",M33-J33) | X33: =IF($B33="","",IFERROR(V33/W33,"")) | Y33: =IF($B33="","",V33-W33)
A34: =IF($B34="","",ROW()-3) | B34: =IF(30+1>COUNTA('维度字典'!$C$2:$C$200)*COUNTA('维度字典'!$A$2:$A$200)*COUNTA('维度字典'!$E$2:$E$200),"",INDEX('维度字典'!$C$2:$C$200,MOD(INT(30/(COUNTA('维度字典'!$E$2:$E$200)*COUNTA('维度字典'!$A$2:$A$200))),COUNTA('维度字典'!$C$2:$C$200))+1)) | C34: =IF($B34="","",INDEX('维度字典'!$A$2:$A$200,MOD(INT(30/COUNTA('维度字典'!$E$2:$E$200)),COUNTA('维度字典'!$A$2:$A$200))+1)) | D34: =IF($B34="","",INDEX('维度字典'!$E$2:$E$200,MOD(30,COUNTA('维度字典'!$E$2:$E$200))+1)) | E34: =IF($B34="","",SUMPRODUCT(('系统实绩导入'!$B$4:$B$1500=$B34)*('系统实绩导入'!$C$4:$C$1500=$C34)*('系统实绩导入'!$D$4:$D$1500=$D34)*('系统实绩导入'!$F$4:$F$1500="实绩销售额")*('系统实绩导入'!$G$3:$R$3=$F$1)*'系统实绩导入'!$G$4:$R$1500)) | F34: =IF($B34="","",SUMPRODUCT(('系统实绩导入'!$B$4:$B$1500=$B34)*('系统实绩导入'!$C$4:$C$1500=$C34)*('系统实绩导入'!$D$4:$D$1500=$D34)*('系统实绩导入'!$F$4:$F$1500="实绩毛利")*('系统实绩导入'!$G$3:$R$3=$F$1)*'系统实绩导入'!$G$4:$R$1500)) | G34: =IF($B34="","",IFERROR(F34/E34,"")) | H34: =IF($B34="","",SUMPRODUCT(('目标填报'!$B$4:$B$1500=$B34)*('目标填报'!$C$4:$C$1500=$C34)*('目标填报'!$D$4:$D$1500=$D34)*('目标填报'!$F$4:$F$1500="销售目标额")*('目标填报'!$G$3:$R$3=$F$1)*'目标填报'!$G$4:$R$1500)) | I34: =IF($B34="","",IFERROR(E34/H34,"")) | J34: =IF($B34="","",SUMPRODUCT(('系统实绩导入'!$B$4:$B$1500=$B34)*('系统实绩导入'!$C$4:$C$1500=$C34)*('系统实绩导入'!$D$4:$D$1500=$D34)*('系统实绩导入'!$F$4:$F$1500="实绩销售额")*('系统实绩导入'!$G$3:$R$3<=$F$1)*'系统实绩导入'!$G$4:$R$1500)) | K34: =IF($B34="","",SUMPRODUCT(('系统实绩导入'!$B$4:$B$1500=$B34)*('系统实绩导入'!$C$4:$C$1500=$C34)*('系统实绩导入'!$D$4:$D$1500=$D34)*('系统实绩导入'!$F$4:$F$1500="实绩毛利")*('系统实绩导入'!$G$3:$R$3<=$F$1)*'系统实绩导入'!$G$4:$R$1500)) | L34: =IF($B34="","",IFERROR(K34/J34,"")) | M34: =IF($B34="","",SUMIFS('目标填报'!$S$4:$S$1500,'目标填报'!$B$4:$B$1500,$B34,'目标填报'!$C$4:$C$1500,$C34,'目标填报'!$D$4:$D$1500,$D34,'目标填报'!$F$4:$F$1500,"销售目标额")) | N34: =IF($B34="","",IFERROR(J34/M34,"")) | O34: =IF($B34="","",J34-M34) | P34: =IF($B34="","",SUMPRODUCT(('目标填报'!$B$4:$B$1500=$B34)*('目标填报'!$C$4:$C$1500=$C34)*('目标填报'!$D$4:$D$1500=$D34)*('目标填报'!$F$4:$F$1500="在手订单")*('目标填报'!$G$3:$R$3=$F$1)*'目标填报'!$G$4:$R$1500)) | Q34: =IF($B34="","",SUMPRODUCT(('目标填报'!$B$4:$B$1500=$B34)*('目标填报'!$C$4:$C$1500=$C34)*('目标填报'!$D$4:$D$1500=$D34)*('目标填报'!$F$4:$F$1500="在手订单目标")*('目标填报'!$G$3:$R$3=$F$1)*'目标填报'!$G$4:$R$1500)) | R34: =IF($B34="","",IFERROR(P34/Q34,"")) | S34: =IF($B34="","",SUMPRODUCT(('目标填报'!$B$4:$B$1500=$B34)*('目标填报'!$C$4:$C$1500=$C34)*('目标填报'!$D$4:$D$1500=$D34)*('目标填报'!$F$4:$F$1500="目标客户机会")*('目标填报'!$G$3:$R$3=$F$1)*'目标填报'!$G$4:$R$1500)) | T34: =IF($B34="","",SUMPRODUCT(('目标填报'!$B$4:$B$1500=$B34)*('目标填报'!$C$4:$C$1500=$C34)*('目标填报'!$D$4:$D$1500=$D34)*('目标填报'!$F$4:$F$1500="目标客户机会目标")*('目标填报'!$G$3:$R$3=$F$1)*'目标填报'!$G$4:$R$1500)) | U34: =IF($B34="","",IFERROR(S34/T34,"")) | V34: =IF($B34="","",P34+S34) | W34: =IF($B34="","",M34-J34) | X34: =IF($B34="","",IFERROR(V34/W34,"")) | Y34: =IF($B34="","",V34-W34)
A35: =IF($B35="","",ROW()-3) | B35: =IF(31+1>COUNTA('维度字典'!$C$2:$C$200)*COUNTA('维度字典'!$A$2:$A$200)*COUNTA('维度字典'!$E$2:$E$200),"",INDEX('维度字典'!$C$2:$C$200,MOD(INT(31/(COUNTA('维度字典'!$E$2:$E$200)*COUNTA('维度字典'!$A$2:$A$200))),COUNTA('维度字典'!$C$2:$C$200))+1)) | C35: =IF($B35="","",INDEX('维度字典'!$A$2:$A$200,MOD(INT(31/COUNTA('维度字典'!$E$2:$E$200)),COUNTA('维度字典'!$A$2:$A$200))+1)) | D35: =IF($B35="","",INDEX('维度字典'!$E$2:$E$200,MOD(31,COUNTA('维度字典'!$E$2:$E$200))+1)) | E35: =IF($B35="","",SUMPRODUCT(('系统实绩导入'!$B$4:$B$1500=$B35)*('系统实绩导入'!$C$4:$C$1500=$C35)*('系统实绩导入'!$D$4:$D$1500=$D35)*('系统实绩导入'!$F$4:$F$1500="实绩销售额")*('系统实绩导入'!$G$3:$R$3=$F$1)*'系统实绩导入'!$G$4:$R$1500)) | F35: =IF($B35="","",SUMPRODUCT(('系统实绩导入'!$B$4:$B$1500=$B35)*('系统实绩导入'!$C$4:$C$1500=$C35)*('系统实绩导入'!$D$4:$D$1500=$D35)*('系统实绩导入'!$F$4:$F$1500="实绩毛利")*('系统实绩导入'!$G$3:$R$3=$F$1)*'系统实绩导入'!$G$4:$R$1500)) | G35: =IF($B35="","",IFERROR(F35/E35,"")) | H35: =IF($B35="","",SUMPRODUCT(('目标填报'!$B$4:$B$1500=$B35)*('目标填报'!$C$4:$C$1500=$C35)*('目标填报'!$D$4:$D$1500=$D35)*('目标填报'!$F$4:$F$1500="销售目标额")*('目标填报'!$G$3:$R$3=$F$1)*'目标填报'!$G$4:$R$1500)) | I35: =IF($B35="","",IFERROR(E35/H35,"")) | J35: =IF($B35="","",SUMPRODUCT(('系统实绩导入'!$B$4:$B$1500=$B35)*('系统实绩导入'!$C$4:$C$1500=$C35)*('系统实绩导入'!$D$4:$D$1500=$D35)*('系统实绩导入'!$F$4:$F$1500="实绩销售额")*('系统实绩导入'!$G$3:$R$3<=$F$1)*'系统实绩导入'!$G$4:$R$1500)) | K35: =IF($B35="","",SUMPRODUCT(('系统实绩导入'!$B$4:$B$1500=$B35)*('系统实绩导入'!$C$4:$C$1500=$C35)*('系统实绩导入'!$D$4:$D$1500=$D35)*('系统实绩导入'!$F$4:$F$1500="实绩毛利")*('系统实绩导入'!$G$3:$R$3<=$F$1)*'系统实绩导入'!$G$4:$R$1500)) | L35: =IF($B35="","",IFERROR(K35/J35,"")) | M35: =IF($B35="","",SUMIFS('目标填报'!$S$4:$S$1500,'目标填报'!$B$4:$B$1500,$B35,'目标填报'!$C$4:$C$1500,$C35,'目标填报'!$D$4:$D$1500,$D35,'目标填报'!$F$4:$F$1500,"销售目标额")) | N35: =IF($B35="","",IFERROR(J35/M35,"")) | O35: =IF($B35="","",J35-M35) | P35: =IF($B35="","",SUMPRODUCT(('目标填报'!$B$4:$B$1500=$B35)*('目标填报'!$C$4:$C$1500=$C35)*('目标填报'!$D$4:$D$1500=$D35)*('目标填报'!$F$4:$F$1500="在手订单")*('目标填报'!$G$3:$R$3=$F$1)*'目标填报'!$G$4:$R$1500)) | Q35: =IF($B35="","",SUMPRODUCT(('目标填报'!$B$4:$B$1500=$B35)*('目标填报'!$C$4:$C$1500=$C35)*('目标填报'!$D$4:$D$1500=$D35)*('目标填报'!$F$4:$F$1500="在手订单目标")*('目标填报'!$G$3:$R$3=$F$1)*'目标填报'!$G$4:$R$1500)) | R35: =IF($B35="","",IFERROR(P35/Q35,"")) | S35: =IF($B35="","",SUMPRODUCT(('目标填报'!$B$4:$B$1500=$B35)*('目标填报'!$C$4:$C$1500=$C35)*('目标填报'!$D$4:$D$1500=$D35)*('目标填报'!$F$4:$F$1500="目标客户机会")*('目标填报'!$G$3:$R$3=$F$1)*'目标填报'!$G$4:$R$1500)) | T35: =IF($B35="","",SUMPRODUCT(('目标填报'!$B$4:$B$1500=$B35)*('目标填报'!$C$4:$C$1500=$C35)*('目标填报'!$D$4:$D$1500=$D35)*('目标填报'!$F$4:$F$1500="目标客户机会目标")*('目标填报'!$G$3:$R$3=$F$1)*'目标填报'!$G$4:$R$1500)) | U35: =IF($B35="","",IFERROR(S35/T35,"")) | V35: =IF($B35="","",P35+S35) | W35: =IF($B35="","",M35-J35) | X35: =IF($B35="","",IFERROR(V35/W35,"")) | Y35: =IF($B35="","",V35-W35)
A36: =IF($B36="","",ROW()-3) | B36: =IF(32+1>COUNTA('维度字典'!$C$2:$C$200)*COUNTA('维度字典'!$A$2:$A$200)*COUNTA('维度字典'!$E$2:$E$200),"",INDEX('维度字典'!$C$2:$C$200,MOD(INT(32/(COUNTA('维度字典'!$E$2:$E$200)*COUNTA('维度字典'!$A$2:$A$200))),COUNTA('维度字典'!$C$2:$C$200))+1)) | C36: =IF($B36="","",INDEX('维度字典'!$A$2:$A$200,MOD(INT(32/COUNTA('维度字典'!$E$2:$E$200)),COUNTA('维度字典'!$A$2:$A$200))+1)) | D36: =IF($B36="","",INDEX('维度字典'!$E$2:$E$200,MOD(32,COUNTA('维度字典'!$E$2:$E$200))+1)) | E36: =IF($B36="","",SUMPRODUCT(('系统实绩导入'!$B$4:$B$1500=$B36)*('系统实绩导入'!$C$4:$C$1500=$C36)*('系统实绩导入'!$D$4:$D$1500=$D36)*('系统实绩导入'!$F$4:$F$1500="实绩销售额")*('系统实绩导入'!$G$3:$R$3=$F$1)*'系统实绩导入'!$G$4:$R$1500)) | F36: =IF($B36="","",SUMPRODUCT(('系统实绩导入'!$B$4:$B$1500=$B36)*('系统实绩导入'!$C$4:$C$1500=$C36)*('系统实绩导入'!$D$4:$D$1500=$D36)*('系统实绩导入'!$F$4:$F$1500="实绩毛利")*('系统实绩导入'!$G$3:$R$3=$F$1)*'系统实绩导入'!$G$4:$R$1500)) | G36: =IF($B36="","",IFERROR(F36/E36,"")) | H36: =IF($B36="","",SUMPRODUCT(('目标填报'!$B$4:$B$1500=$B36)*('目标填报'!$C$4:$C$1500=$C36)*('目标填报'!$D$4:$D$1500=$D36)*('目标填报'!$F$4:$F$1500="销售目标额")*('目标填报'!$G$3:$R$3=$F$1)*'目标填报'!$G$4:$R$1500)) | I36: =IF($B36="","",IFERROR(E36/H36,"")) | J36: =IF($B36="","",SUMPRODUCT(('系统实绩导入'!$B$4:$B$1500=$B36)*('系统实绩导入'!$C$4:$C$1500=$C36)*('系统实绩导入'!$D$4:$D$1500=$D36)*('系统实绩导入'!$F$4:$F$1500="实绩销售额")*('系统实绩导入'!$G$3:$R$3<=$F$1)*'系统实绩导入'!$G$4:$R$1500)) | K36: =IF($B36="","",SUMPRODUCT(('系统实绩导入'!$B$4:$B$1500=$B36)*('系统实绩导入'!$C$4:$C$1500=$C36)*('系统实绩导入'!$D$4:$D$1500=$D36)*('系统实绩导入'!$F$4:$F$1500="实绩毛利")*('系统实绩导入'!$G$3:$R$3<=$F$1)*'系统实绩导入'!$G$4:$R$1500)) | L36: =IF($B36="","",IFERROR(K36/J36,"")) | M36: =IF($B36="","",SUMIFS('目标填报'!$S$4:$S$1500,'目标填报'!$B$4:$B$1500,$B36,'目标填报'!$C$4:$C$1500,$C36,'目标填报'!$D$4:$D$1500,$D36,'目标填报'!$F$4:$F$1500,"销售目标额")) | N36: =IF($B36="","",IFERROR(J36/M36,"")) | O36: =IF($B36="","",J36-M36) | P36: =IF($B36="","",SUMPRODUCT(('目标填报'!$B$4:$B$1500=$B36)*('目标填报'!$C$4:$C$1500=$C36)*('目标填报'!$D$4:$D$1500=$D36)*('目标填报'!$F$4:$F$1500="在手订单")*('目标填报'!$G$3:$R$3=$F$1)*'目标填报'!$G$4:$R$1500)) | Q36: =IF($B36="","",SUMPRODUCT(('目标填报'!$B$4:$B$1500=$B36)*('目标填报'!$C$4:$C$1500=$C36)*('目标填报'!$D$4:$D$1500=$D36)*('目标填报'!$F$4:$F$1500="在手订单目标")*('目标填报'!$G$3:$R$3=$F$1)*'目标填报'!$G$4:$R$1500)) | R36: =IF($B36="","",IFERROR(P36/Q36,"")) | S36: =IF($B36="","",SUMPRODUCT(('目标填报'!$B$4:$B$1500=$B36)*('目标填报'!$C$4:$C$1500=$C36)*('目标填报'!$D$4:$D$1500=$D36)*('目标填报'!$F$4:$F$1500="目标客户机会")*('目标填报'!$G$3:$R$3=$F$1)*'目标填报'!$G$4:$R$1500)) | T36: =IF($B36="","",SUMPRODUCT(('目标填报'!$B$4:$B$1500=$B36)*('目标填报'!$C$4:$C$1500=$C36)*('目标填报'!$D$4:$D$1500=$D36)*('目标填报'!$F$4:$F$1500="目标客户机会目标")*('目标填报'!$G$3:$R$3=$F$1)*'目标填报'!$G$4:$R$1500)) | U36: =IF($B36="","",IFERROR(S36/T36,"")) | V36: =IF($B36="","",P36+S36) | W36: =IF($B36="","",M36-J36) | X36: =IF($B36="","",IFERROR(V36/W36,"")) | Y36: =IF($B36="","",V36-W36)
A37: =IF($B37="","",ROW()-3) | B37: =IF(33+1>COUNTA('维度字典'!$C$2:$C$200)*COUNTA('维度字典'!$A$2:$A$200)*COUNTA('维度字典'!$E$2:$E$200),"",INDEX('维度字典'!$C$2:$C$200,MOD(INT(33/(COUNTA('维度字典'!$E$2:$E$200)*COUNTA('维度字典'!$A$2:$A$200))),COUNTA('维度字典'!$C$2:$C$200))+1)) | C37: =IF($B37="","",INDEX('维度字典'!$A$2:$A$200,MOD(INT(33/COUNTA('维度字典'!$E$2:$E$200)),COUNTA('维度字典'!$A$2:$A$200))+1)) | D37: =IF($B37="","",INDEX('维度字典'!$E$2:$E$200,MOD(33,COUNTA('维度字典'!$E$2:$E$200))+1)) | E37: =IF($B37="","",SUMPRODUCT(('系统实绩导入'!$B$4:$B$1500=$B37)*('系统实绩导入'!$C$4:$C$1500=$C37)*('系统实绩导入'!$D$4:$D$1500=$D37)*('系统实绩导入'!$F$4:$F$1500="实绩销售额")*('系统实绩导入'!$G$3:$R$3=$F$1)*'系统实绩导入'!$G$4:$R$1500)) | F37: =IF($B37="","",SUMPRODUCT(('系统实绩导入'!$B$4:$B$1500=$B37)*('系统实绩导入'!$C$4:$C$1500=$C37)*('系统实绩导入'!$D$4:$D$1500=$D37)*('系统实绩导入'!$F$4:$F$1500="实绩毛利")*('系统实绩导入'!$G$3:$R$3=$F$1)*'系统实绩导入'!$G$4:$R$1500)) | G37: =IF($B37="","",IFERROR(F37/E37,"")) | H37: =IF($B37="","",SUMPRODUCT(('目标填报'!$B$4:$B$1500=$B37)*('目标填报'!$C$4:$C$1500=$C37)*('目标填报'!$D$4:$D$1500=$D37)*('目标填报'!$F$4:$F$1500="销售目标额")*('目标填报'!$G$3:$R$3=$F$1)*'目标填报'!$G$4:$R$1500)) | I37: =IF($B37="","",IFERROR(E37/H37,"")) | J37: =IF($B37="","",SUMPRODUCT(('系统实绩导入'!$B$4:$B$1500=$B37)*('系统实绩导入'!$C$4:$C$1500=$C37)*('系统实绩导入'!$D$4:$D$1500=$D37)*('系统实绩导入'!$F$4:$F$1500="实绩销售额")*('系统实绩导入'!$G$3:$R$3<=$F$1)*'系统实绩导入'!$G$4:$R$1500)) | K37: =IF($B37="","",SUMPRODUCT(('系统实绩导入'!$B$4:$B$1500=$B37)*('系统实绩导入'!$C$4:$C$1500=$C37)*('系统实绩导入'!$D$4:$D$1500=$D37)*('系统实绩导入'!$F$4:$F$1500="实绩毛利")*('系统实绩导入'!$G$3:$R$3<=$F$1)*'系统实绩导入'!$G$4:$R$1500)) | L37: =IF($B37="","",IFERROR(K37/J37,"")) | M37: =IF($B37="","",SUMIFS('目标填报'!$S$4:$S$1500,'目标填报'!$B$4:$B$1500,$B37,'目标填报'!$C$4:$C$1500,$C37,'目标填报'!$D$4:$D$1500,$D37,'目标填报'!$F$4:$F$1500,"销售目标额")) | N37: =IF($B37="","",IFERROR(J37/M37,"")) | O37: =IF($B37="","",J37-M37) | P37: =IF($B37="","",SUMPRODUCT(('目标填报'!$B$4:$B$1500=$B37)*('目标填报'!$C$4:$C$1500=$C37)*('目标填报'!$D$4:$D$1500=$D37)*('目标填报'!$F$4:$F$1500="在手订单")*('目标填报'!$G$3:$R$3=$F$1)*'目标填报'!$G$4:$R$1500)) | Q37: =IF($B37="","",SUMPRODUCT(('目标填报'!$B$4:$B$1500=$B37)*('目标填报'!$C$4:$C$1500=$C37)*('目标填报'!$D$4:$D$1500=$D37)*('目标填报'!$F$4:$F$1500="在手订单目标")*('目标填报'!$G$3:$R$3=$F$1)*'目标填报'!$G$4:$R$1500)) | R37: =IF($B37="","",IFERROR(P37/Q37,"")) | S37: =IF($B37="","",SUMPRODUCT(('目标填报'!$B$4:$B$1500=$B37)*('目标填报'!$C$4:$C$1500=$C37)*('目标填报'!$D$4:$D$1500=$D37)*('目标填报'!$F$4:$F$1500="目标客户机会")*('目标填报'!$G$3:$R$3=$F$1)*'目标填报'!$G$4:$R$1500)) | T37: =IF($B37="","",SUMPRODUCT(('目标填报'!$B$4:$B$1500=$B37)*('目标填报'!$C$4:$C$1500=$C37)*('目标填报'!$D$4:$D$1500=$D37)*('目标填报'!$F$4:$F$1500="目标客户机会目标")*('目标填报'!$G$3:$R$3=$F$1)*'目标填报'!$G$4:$R$1500)) | U37: =IF($B37="","",IFERROR(S37/T37,"")) | V37: =IF($B37="","",P37+S37) | W37: =IF($B37="","",M37-J37) | X37: =IF($B37="","",IFERROR(V37/W37,"")) | Y37: =IF($B37="","",V37-W37)
A38: =IF($B38="","",ROW()-3) | B38: =IF(34+1>COUNTA('维度字典'!$C$2:$C$200)*COUNTA('维度字典'!$A$2:$A$200)*COUNTA('维度字典'!$E$2:$E$200),"",INDEX('维度字典'!$C$2:$C$200,MOD(INT(34/(COUNTA('维度字典'!$E$2:$E$200)*COUNTA('维度字典'!$A$2:$A$200))),COUNTA('维度字典'!$C$2:$C$200))+1)) | C38: =IF($B38="","",INDEX('维度字典'!$A$2:$A$200,MOD(INT(34/COUNTA('维度字典'!$E$2:$E$200)),COUNTA('维度字典'!$A$2:$A$200))+1)) | D38: =IF($B38="","",INDEX('维度字典'!$E$2:$E$200,MOD(34,COUNTA('维度字典'!$E$2:$E$200))+1)) | E38: =IF($B38="","",SUMPRODUCT(('系统实绩导入'!$B$4:$B$1500=$B38)*('系统实绩导入'!$C$4:$C$1500=$C38)*('系统实绩导入'!$D$4:$D$1500=$D38)*('系统实绩导入'!$F$4:$F$1500="实绩销售额")*('系统实绩导入'!$G$3:$R$3=$F$1)*'系统实绩导入'!$G$4:$R$1500)) | F38: =IF($B38="","",SUMPRODUCT(('系统实绩导入'!$B$4:$B$1500=$B38)*('系统实绩导入'!$C$4:$C$1500=$C38)*('系统实绩导入'!$D$4:$D$1500=$D38)*('系统实绩导入'!$F$4:$F$1500="实绩毛利")*('系统实绩导入'!$G$3:$R$3=$F$1)*'系统实绩导入'!$G$4:$R$1500)) | G38: =IF($B38="","",IFERROR(F38/E38,"")) | H38: =IF($B38="","",SUMPRODUCT(('目标填报'!$B$4:$B$1500=$B38)*('目标填报'!$C$4:$C$1500=$C38)*('目标填报'!$D$4:$D$1500=$D38)*('目标填报'!$F$4:$F$1500="销售目标额")*('目标填报'!$G$3:$R$3=$F$1)*'目标填报'!$G$4:$R$1500)) | I38: =IF($B38="","",IFERROR(E38/H38,"")) | J38: =IF($B38="","",SUMPRODUCT(('系统实绩导入'!$B$4:$B$1500=$B38)*('系统实绩导入'!$C$4:$C$1500=$C38)*('系统实绩导入'!$D$4:$D$1500=$D38)*('系统实绩导入'!$F$4:$F$1500="实绩销售额")*('系统实绩导入'!$G$3:$R$3<=$F$1)*'系统实绩导入'!$G$4:$R$1500)) | K38: =IF($B38="","",SUMPRODUCT(('系统实绩导入'!$B$4:$B$1500=$B38)*('系统实绩导入'!$C$4:$C$1500=$C38)*('系统实绩导入'!$D$4:$D$1500=$D38)*('系统实绩导入'!$F$4:$F$1500="实绩毛利")*('系统实绩导入'!$G$3:$R$3<=$F$1)*'系统实绩导入'!$G$4:$R$1500)) | L38: =IF($B38="","",IFERROR(K38/J38,"")) | M38: =IF($B38="","",SUMIFS('目标填报'!$S$4:$S$1500,'目标填报'!$B$4:$B$1500,$B38,'目标填报'!$C$4:$C$1500,$C38,'目标填报'!$D$4:$D$1500,$D38,'目标填报'!$F$4:$F$1500,"销售目标额")) | N38: =IF($B38="","",IFERROR(J38/M38,"")) | O38: =IF($B38="","",J38-M38) | P38: =IF($B38="","",SUMPRODUCT(('目标填报'!$B$4:$B$1500=$B38)*('目标填报'!$C$4:$C$1500=$C38)*('目标填报'!$D$4:$D$1500=$D38)*('目标填报'!$F$4:$F$1500="在手订单")*('目标填报'!$G$3:$R$3=$F$1)*'目标填报'!$G$4:$R$1500)) | Q38: =IF($B38="","",SUMPRODUCT(('目标填报'!$B$4:$B$1500=$B38)*('目标填报'!$C$4:$C$1500=$C38)*('目标填报'!$D$4:$D$1500=$D38)*('目标填报'!$F$4:$F$1500="在手订单目标")*('目标填报'!$G$3:$R$3=$F$1)*'目标填报'!$G$4:$R$1500)) | R38: =IF($B38="","",IFERROR(P38/Q38,"")) | S38: =IF($B38="","",SUMPRODUCT(('目标填报'!$B$4:$B$1500=$B38)*('目标填报'!$C$4:$C$1500=$C38)*('目标填报'!$D$4:$D$1500=$D38)*('目标填报'!$F$4:$F$1500="目标客户机会")*('目标填报'!$G$3:$R$3=$F$1)*'目标填报'!$G$4:$R$1500)) | T38: =IF($B38="","",SUMPRODUCT(('目标填报'!$B$4:$B$1500=$B38)*('目标填报'!$C$4:$C$1500=$C38)*('目标填报'!$D$4:$D$1500=$D38)*('目标填报'!$F$4:$F$1500="目标客户机会目标")*('目标填报'!$G$3:$R$3=$F$1)*'目标填报'!$G$4:$R$1500)) | U38: =IF($B38="","",IFERROR(S38/T38,"")) | V38: =IF($B38="","",P38+S38) | W38: =IF($B38="","",M38-J38) | X38: =IF($B38="","",IFERROR(V38/W38,"")) | Y38: =IF($B38="","",V38-W38)
A39: =IF($B39="","",ROW()-3) | B39: =IF(35+1>COUNTA('维度字典'!$C$2:$C$200)*COUNTA('维度字典'!$A$2:$A$200)*COUNTA('维度字典'!$E$2:$E$200),"",INDEX('维度字典'!$C$2:$C$200,MOD(INT(35/(COUNTA('维度字典'!$E$2:$E$200)*COUNTA('维度字典'!$A$2:$A$200))),COUNTA('维度字典'!$C$2:$C$200))+1)) | C39: =IF($B39="","",INDEX('维度字典'!$A$2:$A$200,MOD(INT(35/COUNTA('维度字典'!$E$2:$E$200)),COUNTA('维度字典'!$A$2:$A$200))+1)) | D39: =IF($B39="","",INDEX('维度字典'!$E$2:$E$200,MOD(35,COUNTA('维度字典'!$E$2:$E$200))+1)) | E39: =IF($B39="","",SUMPRODUCT(('系统实绩导入'!$B$4:$B$1500=$B39)*('系统实绩导入'!$C$4:$C$1500=$C39)*('系统实绩导入'!$D$4:$D$1500=$D39)*('系统实绩导入'!$F$4:$F$1500="实绩销售额")*('系统实绩导入'!$G$3:$R$3=$F$1)*'系统实绩导入'!$G$4:$R$1500)) | F39: =IF($B39="","",SUMPRODUCT(('系统实绩导入'!$B$4:$B$1500=$B39)*('系统实绩导入'!$C$4:$C$1500=$C39)*('系统实绩导入'!$D$4:$D$1500=$D39)*('系统实绩导入'!$F$4:$F$1500="实绩毛利")*('系统实绩导入'!$G$3:$R$3=$F$1)*'系统实绩导入'!$G$4:$R$1500)) | G39: =IF($B39="","",IFERROR(F39/E39,"")) | H39: =IF($B39="","",SUMPRODUCT(('目标填报'!$B$4:$B$1500=$B39)*('目标填报'!$C$4:$C$1500=$C39)*('目标填报'!$D$4:$D$1500=$D39)*('目标填报'!$F$4:$F$1500="销售目标额")*('目标填报'!$G$3:$R$3=$F$1)*'目标填报'!$G$4:$R$1500)) | I39: =IF($B39="","",IFERROR(E39/H39,"")) | J39: =IF($B39="","",SUMPRODUCT(('系统实绩导入'!$B$4:$B$1500=$B39)*('系统实绩导入'!$C$4:$C$1500=$C39)*('系统实绩导入'!$D$4:$D$1500=$D39)*('系统实绩导入'!$F$4:$F$1500="实绩销售额")*('系统实绩导入'!$G$3:$R$3<=$F$1)*'系统实绩导入'!$G$4:$R$1500)) | K39: =IF($B39="","",SUMPRODUCT(('系统实绩导入'!$B$4:$B$1500=$B39)*('系统实绩导入'!$C$4:$C$1500=$C39)*('系统实绩导入'!$D$4:$D$1500=$D39)*('系统实绩导入'!$F$4:$F$1500="实绩毛利")*('系统实绩导入'!$G$3:$R$3<=$F$1)*'系统实绩导入'!$G$4:$R$1500)) | L39: =IF($B39="","",IFERROR(K39/J39,"")) | M39: =IF($B39="","",SUMIFS('目标填报'!$S$4:$S$1500,'目标填报'!$B$4:$B$1500,$B39,'目标填报'!$C$4:$C$1500,$C39,'目标填报'!$D$4:$D$1500,$D39,'目标填报'!$F$4:$F$1500,"销售目标额")) | N39: =IF($B39="","",IFERROR(J39/M39,"")) | O39: =IF($B39="","",J39-M39) | P39: =IF($B39="","",SUMPRODUCT(('目标填报'!$B$4:$B$1500=$B39)*('目标填报'!$C$4:$C$1500=$C39)*('目标填报'!$D$4:$D$1500=$D39)*('目标填报'!$F$4:$F$1500="在手订单")*('目标填报'!$G$3:$R$3=$F$1)*'目标填报'!$G$4:$R$1500)) | Q39: =IF($B39="","",SUMPRODUCT(('目标填报'!$B$4:$B$1500=$B39)*('目标填报'!$C$4:$C$1500=$C39)*('目标填报'!$D$4:$D$1500=$D39)*('目标填报'!$F$4:$F$1500="在手订单目标")*('目标填报'!$G$3:$R$3=$F$1)*'目标填报'!$G$4:$R$1500)) | R39: =IF($B39="","",IFERROR(P39/Q39,"")) | S39: =IF($B39="","",SUMPRODUCT(('目标填报'!$B$4:$B$1500=$B39)*('目标填报'!$C$4:$C$1500=$C39)*('目标填报'!$D$4:$D$1500=$D39)*('目标填报'!$F$4:$F$1500="目标客户机会")*('目标填报'!$G$3:$R$3=$F$1)*'目标填报'!$G$4:$R$1500)) | T39: =IF($B39="","",SUMPRODUCT(('目标填报'!$B$4:$B$1500=$B39)*('目标填报'!$C$4:$C$1500=$C39)*('目标填报'!$D$4:$D$1500=$D39)*('目标填报'!$F$4:$F$1500="目标客户机会目标")*('目标填报'!$G$3:$R$3=$F$1)*'目标填报'!$G$4:$R$1500)) | U39: =IF($B39="","",IFERROR(S39/T39,"")) | V39: =IF($B39="","",P39+S39) | W39: =IF($B39="","",M39-J39) | X39: =IF($B39="","",IFERROR(V39/W39,"")) | Y39: =IF($B39="","",V39-W39)
A40: =IF($B40="","",ROW()-3) | B40: =IF(36+1>COUNTA('维度字典'!$C$2:$C$200)*COUNTA('维度字典'!$A$2:$A$200)*COUNTA('维度字典'!$E$2:$E$200),"",INDEX('维度字典'!$C$2:$C$200,MOD(INT(36/(COUNTA('维度字典'!$E$2:$E$200)*COUNTA('维度字典'!$A$2:$A$200))),COUNTA('维度字典'!$C$2:$C$200))+1)) | C40: =IF($B40="","",INDEX('维度字典'!$A$2:$A$200,MOD(INT(36/COUNTA('维度字典'!$E$2:$E$200)),COUNTA('维度字典'!$A$2:$A$200))+1)) | D40: =IF($B40="","",INDEX('维度字典'!$E$2:$E$200,MOD(36,COUNTA('维度字典'!$E$2:$E$200))+1)) | E40: =IF($B40="","",SUMPRODUCT(('系统实绩导入'!$B$4:$B$1500=$B40)*('系统实绩导入'!$C$4:$C$1500=$C40)*('系统实绩导入'!$D$4:$D$1500=$D40)*('系统实绩导入'!$F$4:$F$1500="实绩销售额")*('系统实绩导入'!$G$3:$R$3=$F$1)*'系统实绩导入'!$G$4:$R$1500)) | F40: =IF($B40="","",SUMPRODUCT(('系统实绩导入'!$B$4:$B$1500=$B40)*('系统实绩导入'!$C$4:$C$1500=$C40)*('系统实绩导入'!$D$4:$D$1500=$D40)*('系统实绩导入'!$F$4:$F$1500="实绩毛利")*('系统实绩导入'!$G$3:$R$3=$F$1)*'系统实绩导入'!$G$4:$R$1500)) | G40: =IF($B40="","",IFERROR(F40/E40,"")) | H40: =IF($B40="","",SUMPRODUCT(('目标填报'!$B$4:$B$1500=$B40)*('目标填报'!$C$4:$C$1500=$C40)*('目标填报'!$D$4:$D$1500=$D40)*('目标填报'!$F$4:$F$1500="销售目标额")*('目标填报'!$G$3:$R$3=$F$1)*'目标填报'!$G$4:$R$1500)) | I40: =IF($B40="","",IFERROR(E40/H40,"")) | J40: =IF($B40="","",SUMPRODUCT(('系统实绩导入'!$B$4:$B$1500=$B40)*('系统实绩导入'!$C$4:$C$1500=$C40)*('系统实绩导入'!$D$4:$D$1500=$D40)*('系统实绩导入'!$F$4:$F$1500="实绩销售额")*('系统实绩导入'!$G$3:$R$3<=$F$1)*'系统实绩导入'!$G$4:$R$1500)) | K40: =IF($B40="","",SUMPRODUCT(('系统实绩导入'!$B$4:$B$1500=$B40)*('系统实绩导入'!$C$4:$C$1500=$C40)*('系统实绩导入'!$D$4:$D$1500=$D40)*('系统实绩导入'!$F$4:$F$1500="实绩毛利")*('系统实绩导入'!$G$3:$R$3<=$F$1)*'系统实绩导入'!$G$4:$R$1500)) | L40: =IF($B40="","",IFERROR(K40/J40,"")) | M40: =IF($B40="","",SUMIFS('目标填报'!$S$4:$S$1500,'目标填报'!$B$4:$B$1500,$B40,'目标填报'!$C$4:$C$1500,$C40,'目标填报'!$D$4:$D$1500,$D40,'目标填报'!$F$4:$F$1500,"销售目标额")) | N40: =IF($B40="","",IFERROR(J40/M40,"")) | O40: =IF($B40="","",J40-M40) | P40: =IF($B40="","",SUMPRODUCT(('目标填报'!$B$4:$B$1500=$B40)*('目标填报'!$C$4:$C$1500=$C40)*('目标填报'!$D$4:$D$1500=$D40)*('目标填报'!$F$4:$F$1500="在手订单")*('目标填报'!$G$3:$R$3=$F$1)*'目标填报'!$G$4:$R$1500)) | Q40: =IF($B40="","",SUMPRODUCT(('目标填报'!$B$4:$B$1500=$B40)*('目标填报'!$C$4:$C$1500=$C40)*('目标填报'!$D$4:$D$1500=$D40)*('目标填报'!$F$4:$F$1500="在手订单目标")*('目标填报'!$G$3:$R$3=$F$1)*'目标填报'!$G$4:$R$1500)) | R40: =IF($B40="","",IFERROR(P40/Q40,"")) | S40: =IF($B40="","",SUMPRODUCT(('目标填报'!$B$4:$B$1500=$B40)*('目标填报'!$C$4:$C$1500=$C40)*('目标填报'!$D$4:$D$1500=$D40)*('目标填报'!$F$4:$F$1500="目标客户机会")*('目标填报'!$G$3:$R$3=$F$1)*'目标填报'!$G$4:$R$1500)) | T40: =IF($B40="","",SUMPRODUCT(('目标填报'!$B$4:$B$1500=$B40)*('目标填报'!$C$4:$C$1500=$C40)*('目标填报'!$D$4:$D$1500=$D40)*('目标填报'!$F$4:$F$1500="目标客户机会目标")*('目标填报'!$G$3:$R$3=$F$1)*'目标填报'!$G$4:$R$1500)) | U40: =IF($B40="","",IFERROR(S40/T40,"")) | V40: =IF($B40="","",P40+S40) | W40: =IF($B40="","",M40-J40) | X40: =IF($B40="","",IFERROR(V40/W40,"")) | Y40: =IF($B40="","",V40-W40)
A41: =IF($B41="","",ROW()-3) | B41: =IF(37+1>COUNTA('维度字典'!$C$2:$C$200)*COUNTA('维度字典'!$A$2:$A$200)*COUNTA('维度字典'!$E$2:$E$200),"",INDEX('维度字典'!$C$2:$C$200,MOD(INT(37/(COUNTA('维度字典'!$E$2:$E$200)*COUNTA('维度字典'!$A$2:$A$200))),COUNTA('维度字典'!$C$2:$C$200))+1)) | C41: =IF($B41="","",INDEX('维度字典'!$A$2:$A$200,MOD(INT(37/COUNTA('维度字典'!$E$2:$E$200)),COUNTA('维度字典'!$A$2:$A$200))+1)) | D41: =IF($B41="","",INDEX('维度字典'!$E$2:$E$200,MOD(37,COUNTA('维度字典'!$E$2:$E$200))+1)) | E41: =IF($B41="","",SUMPRODUCT(('系统实绩导入'!$B$4:$B$1500=$B41)*('系统实绩导入'!$C$4:$C$1500=$C41)*('系统实绩导入'!$D$4:$D$1500=$D41)*('系统实绩导入'!$F$4:$F$1500="实绩销售额")*('系统实绩导入'!$G$3:$R$3=$F$1)*'系统实绩导入'!$G$4:$R$1500)) | F41: =IF($B41="","",SUMPRODUCT(('系统实绩导入'!$B$4:$B$1500=$B41)*('系统实绩导入'!$C$4:$C$1500=$C41)*('系统实绩导入'!$D$4:$D$1500=$D41)*('系统实绩导入'!$F$4:$F$1500="实绩毛利")*('系统实绩导入'!$G$3:$R$3=$F$1)*'系统实绩导入'!$G$4:$R$1500)) | G41: =IF($B41="","",IFERROR(F41/E41,"")) | H41: =IF($B41="","",SUMPRODUCT(('目标填报'!$B$4:$B$1500=$B41)*('目标填报'!$C$4:$C$1500=$C41)*('目标填报'!$D$4:$D$1500=$D41)*('目标填报'!$F$4:$F$1500="销售目标额")*('目标填报'!$G$3:$R$3=$F$1)*'目标填报'!$G$4:$R$1500)) | I41: =IF($B41="","",IFERROR(E41/H41,"")) | J41: =IF($B41="","",SUMPRODUCT(('系统实绩导入'!$B$4:$B$1500=$B41)*('系统实绩导入'!$C$4:$C$1500=$C41)*('系统实绩导入'!$D$4:$D$1500=$D41)*('系统实绩导入'!$F$4:$F$1500="实绩销售额")*('系统实绩导入'!$G$3:$R$3<=$F$1)*'系统实绩导入'!$G$4:$R$1500)) | K41: =IF($B41="","",SUMPRODUCT(('系统实绩导入'!$B$4:$B$1500=$B41)*('系统实绩导入'!$C$4:$C$1500=$C41)*('系统实绩导入'!$D$4:$D$1500=$D41)*('系统实绩导入'!$F$4:$F$1500="实绩毛利")*('系统实绩导入'!$G$3:$R$3<=$F$1)*'系统实绩导入'!$G$4:$R$1500)) | L41: =IF($B41="","",IFERROR(K41/J41,"")) | M41: =IF($B41="","",SUMIFS('目标填报'!$S$4:$S$1500,'目标填报'!$B$4:$B$1500,$B41,'目标填报'!$C$4:$C$1500,$C41,'目标填报'!$D$4:$D$1500,$D41,'目标填报'!$F$4:$F$1500,"销售目标额")) | N41: =IF($B41="","",IFERROR(J41/M41,"")) | O41: =IF($B41="","",J41-M41) | P41: =IF($B41="","",SUMPRODUCT(('目标填报'!$B$4:$B$1500=$B41)*('目标填报'!$C$4:$C$1500=$C41)*('目标填报'!$D$4:$D$1500=$D41)*('目标填报'!$F$4:$F$1500="在手订单")*('目标填报'!$G$3:$R$3=$F$1)*'目标填报'!$G$4:$R$1500)) | Q41: =IF($B41="","",SUMPRODUCT(('目标填报'!$B$4:$B$1500=$B41)*('目标填报'!$C$4:$C$1500=$C41)*('目标填报'!$D$4:$D$1500=$D41)*('目标填报'!$F$4:$F$1500="在手订单目标")*('目标填报'!$G$3:$R$3=$F$1)*'目标填报'!$G$4:$R$1500)) | R41: =IF($B41="","",IFERROR(P41/Q41,"")) | S41: =IF($B41="","",SUMPRODUCT(('目标填报'!$B$4:$B$1500=$B41)*('目标填报'!$C$4:$C$1500=$C41)*('目标填报'!$D$4:$D$1500=$D41)*('目标填报'!$F$4:$F$1500="目标客户机会")*('目标填报'!$G$3:$R$3=$F$1)*'目标填报'!$G$4:$R$1500)) | T41: =IF($B41="","",SUMPRODUCT(('目标填报'!$B$4:$B$1500=$B41)*('目标填报'!$C$4:$C$1500=$C41)*('目标填报'!$D$4:$D$1500=$D41)*('目标填报'!$F$4:$F$1500="目标客户机会目标")*('目标填报'!$G$3:$R$3=$F$1)*'目标填报'!$G$4:$R$1500)) | U41: =IF($B41="","",IFERROR(S41/T41,"")) | V41: =IF($B41="","",P41+S41) | W41: =IF($B41="","",M41-J41) | X41: =IF($B41="","",IFERROR(V41/W41,"")) | Y41: =IF($B41="","",V41-W41)
A42: =IF($B42="","",ROW()-3) | B42: =IF(38+1>COUNTA('维度字典'!$C$2:$C$200)*COUNTA('维度字典'!$A$2:$A$200)*COUNTA('维度字典'!$E$2:$E$200),"",INDEX('维度字典'!$C$2:$C$200,MOD(INT(38/(COUNTA('维度字典'!$E$2:$E$200)*COUNTA('维度字典'!$A$2:$A$200))),COUNTA('维度字典'!$C$2:$C$200))+1)) | C42: =IF($B42="","",INDEX('维度字典'!$A$2:$A$200,MOD(INT(38/COUNTA('维度字典'!$E$2:$E$200)),COUNTA('维度字典'!$A$2:$A$200))+1)) | D42: =IF($B42="","",INDEX('维度字典'!$E$2:$E$200,MOD(38,COUNTA('维度字典'!$E$2:$E$200))+1)) | E42: =IF($B42="","",SUMPRODUCT(('系统实绩导入'!$B$4:$B$1500=$B42)*('系统实绩导入'!$C$4:$C$1500=$C42)*('系统实绩导入'!$D$4:$D$1500=$D42)*('系统实绩导入'!$F$4:$F$1500="实绩销售额")*('系统实绩导入'!$G$3:$R$3=$F$1)*'系统实绩导入'!$G$4:$R$1500)) | F42: =IF($B42="","",SUMPRODUCT(('系统实绩导入'!$B$4:$B$1500=$B42)*('系统实绩导入'!$C$4:$C$1500=$C42)*('系统实绩导入'!$D$4:$D$1500=$D42)*('系统实绩导入'!$F$4:$F$1500="实绩毛利")*('系统实绩导入'!$G$3:$R$3=$F$1)*'系统实绩导入'!$G$4:$R$1500)) | G42: =IF($B42="","",IFERROR(F42/E42,"")) | H42: =IF($B42="","",SUMPRODUCT(('目标填报'!$B$4:$B$1500=$B42)*('目标填报'!$C$4:$C$1500=$C42)*('目标填报'!$D$4:$D$1500=$D42)*('目标填报'!$F$4:$F$1500="销售目标额")*('目标填报'!$G$3:$R$3=$F$1)*'目标填报'!$G$4:$R$1500)) | I42: =IF($B42="","",IFERROR(E42/H42,"")) | J42: =IF($B42="","",SUMPRODUCT(('系统实绩导入'!$B$4:$B$1500=$B42)*('系统实绩导入'!$C$4:$C$1500=$C42)*('系统实绩导入'!$D$4:$D$1500=$D42)*('系统实绩导入'!$F$4:$F$1500="实绩销售额")*('系统实绩导入'!$G$3:$R$3<=$F$1)*'系统实绩导入'!$G$4:$R$1500)) | K42: =IF($B42="","",SUMPRODUCT(('系统实绩导入'!$B$4:$B$1500=$B42)*('系统实绩导入'!$C$4:$C$1500=$C42)*('系统实绩导入'!$D$4:$D$1500=$D42)*('系统实绩导入'!$F$4:$F$1500="实绩毛利")*('系统实绩导入'!$G$3:$R$3<=$F$1)*'系统实绩导入'!$G$4:$R$1500)) | L42: =IF($B42="","",IFERROR(K42/J42,"")) | M42: =IF($B42="","",SUMIFS('目标填报'!$S$4:$S$1500,'目标填报'!$B$4:$B$1500,$B42,'目标填报'!$C$4:$C$1500,$C42,'目标填报'!$D$4:$D$1500,$D42,'目标填报'!$F$4:$F$1500,"销售目标额")) | N42: =IF($B42="","",IFERROR(J42/M42,"")) | O42: =IF($B42="","",J42-M42) | P42: =IF($B42="","",SUMPRODUCT(('目标填报'!$B$4:$B$1500=$B42)*('目标填报'!$C$4:$C$1500=$C42)*('目标填报'!$D$4:$D$1500=$D42)*('目标填报'!$F$4:$F$1500="在手订单")*('目标填报'!$G$3:$R$3=$F$1)*'目标填报'!$G$4:$R$1500)) | Q42: =IF($B42="","",SUMPRODUCT(('目标填报'!$B$4:$B$1500=$B42)*('目标填报'!$C$4:$C$1500=$C42)*('目标填报'!$D$4:$D$1500=$D42)*('目标填报'!$F$4:$F$1500="在手订单目标")*('目标填报'!$G$3:$R$3=$F$1)*'目标填报'!$G$4:$R$1500)) | R42: =IF($B42="","",IFERROR(P42/Q42,"")) | S42: =IF($B42="","",SUMPRODUCT(('目标填报'!$B$4:$B$1500=$B42)*('目标填报'!$C$4:$C$1500=$C42)*('目标填报'!$D$4:$D$1500=$D42)*('目标填报'!$F$4:$F$1500="目标客户机会")*('目标填报'!$G$3:$R$3=$F$1)*'目标填报'!$G$4:$R$1500)) | T42: =IF($B42="","",SUMPRODUCT(('目标填报'!$B$4:$B$1500=$B42)*('目标填报'!$C$4:$C$1500=$C42)*('目标填报'!$D$4:$D$1500=$D42)*('目标填报'!$F$4:$F$1500="目标客户机会目标")*('目标填报'!$G$3:$R$3=$F$1)*'目标填报'!$G$4:$R$1500)) | U42: =IF($B42="","",IFERROR(S42/T42,"")) | V42: =IF($B42="","",P42+S42) | W42: =IF($B42="","",M42-J42) | X42: =IF($B42="","",IFERROR(V42/W42,"")) | Y42: =IF($B42="","",V42-W42)
A43: =IF($B43="","",ROW()-3) | B43: =IF(39+1>COUNTA('维度字典'!$C$2:$C$200)*COUNTA('维度字典'!$A$2:$A$200)*COUNTA('维度字典'!$E$2:$E$200),"",INDEX('维度字典'!$C$2:$C$200,MOD(INT(39/(COUNTA('维度字典'!$E$2:$E$200)*COUNTA('维度字典'!$A$2:$A$200))),COUNTA('维度字典'!$C$2:$C$200))+1)) | C43: =IF($B43="","",INDEX('维度字典'!$A$2:$A$200,MOD(INT(39/COUNTA('维度字典'!$E$2:$E$200)),COUNTA('维度字典'!$A$2:$A$200))+1)) | D43: =IF($B43="","",INDEX('维度字典'!$E$2:$E$200,MOD(39,COUNTA('维度字典'!$E$2:$E$200))+1)) | E43: =IF($B43="","",SUMPRODUCT(('系统实绩导入'!$B$4:$B$1500=$B43)*('系统实绩导入'!$C$4:$C$1500=$C43)*('系统实绩导入'!$D$4:$D$1500=$D43)*('系统实绩导入'!$F$4:$F$1500="实绩销售额")*('系统实绩导入'!$G$3:$R$3=$F$1)*'系统实绩导入'!$G$4:$R$1500)) | F43: =IF($B43="","",SUMPRODUCT(('系统实绩导入'!$B$4:$B$1500=$B43)*('系统实绩导入'!$C$4:$C$1500=$C43)*('系统实绩导入'!$D$4:$D$1500=$D43)*('系统实绩导入'!$F$4:$F$1500="实绩毛利")*('系统实绩导入'!$G$3:$R$3=$F$1)*'系统实绩导入'!$G$4:$R$1500)) | G43: =IF($B43="","",IFERROR(F43/E43,"")) | H43: =IF($B43="","",SUMPRODUCT(('目标填报'!$B$4:$B$1500=$B43)*('目标填报'!$C$4:$C$1500=$C43)*('目标填报'!$D$4:$D$1500=$D43)*('目标填报'!$F$4:$F$1500="销售目标额")*('目标填报'!$G$3:$R$3=$F$1)*'目标填报'!$G$4:$R$1500)) | I43: =IF($B43="","",IFERROR(E43/H43,"")) | J43: =IF($B43="","",SUMPRODUCT(('系统实绩导入'!$B$4:$B$1500=$B43)*('系统实绩导入'!$C$4:$C$1500=$C43)*('系统实绩导入'!$D$4:$D$1500=$D43)*('系统实绩导入'!$F$4:$F$1500="实绩销售额")*('系统实绩导入'!$G$3:$R$3<=$F$1)*'系统实绩导入'!$G$4:$R$1500)) | K43: =IF($B43="","",SUMPRODUCT(('系统实绩导入'!$B$4:$B$1500=$B43)*('系统实绩导入'!$C$4:$C$1500=$C43)*('系统实绩导入'!$D$4:$D$1500=$D43)*('系统实绩导入'!$F$4:$F$1500="实绩毛利")*('系统实绩导入'!$G$3:$R$3<=$F$1)*'系统实绩导入'!$G$4:$R$1500)) | L43: =IF($B43="","",IFERROR(K43/J43,"")) | M43: =IF($B43="","",SUMIFS('目标填报'!$S$4:$S$1500,'目标填报'!$B$4:$B$1500,$B43,'目标填报'!$C$4:$C$1500,$C43,'目标填报'!$D$4:$D$1500,$D43,'目标填报'!$F$4:$F$1500,"销售目标额")) | N43: =IF($B43="","",IFERROR(J43/M43,"")) | O43: =IF($B43="","",J43-M43) | P43: =IF($B43="","",SUMPRODUCT(('目标填报'!$B$4:$B$1500=$B43)*('目标填报'!$C$4:$C$1500=$C43)*('目标填报'!$D$4:$D$1500=$D43)*('目标填报'!$F$4:$F$1500="在手订单")*('目标填报'!$G$3:$R$3=$F$1)*'目标填报'!$G$4:$R$1500)) | Q43: =IF($B43="","",SUMPRODUCT(('目标填报'!$B$4:$B$1500=$B43)*('目标填报'!$C$4:$C$1500=$C43)*('目标填报'!$D$4:$D$1500=$D43)*('目标填报'!$F$4:$F$1500="在手订单目标")*('目标填报'!$G$3:$R$3=$F$1)*'目标填报'!$G$4:$R$1500)) | R43: =IF($B43="","",IFERROR(P43/Q43,"")) | S43: =IF($B43="","",SUMPRODUCT(('目标填报'!$B$4:$B$1500=$B43)*('目标填报'!$C$4:$C$1500=$C43)*('目标填报'!$D$4:$D$1500=$D43)*('目标填报'!$F$4:$F$1500="目标客户机会")*('目标填报'!$G$3:$R$3=$F$1)*'目标填报'!$G$4:$R$1500)) | T43: =IF($B43="","",SUMPRODUCT(('目标填报'!$B$4:$B$1500=$B43)*('目标填报'!$C$4:$C$1500=$C43)*('目标填报'!$D$4:$D$1500=$D43)*('目标填报'!$F$4:$F$1500="目标客户机会目标")*('目标填报'!$G$3:$R$3=$F$1)*'目标填报'!$G$4:$R$1500)) | U43: =IF($B43="","",IFERROR(S43/T43,"")) | V43: =IF($B43="","",P43+S43) | W43: =IF($B43="","",M43-J43) | X43: =IF($B43="","",IFERROR(V43/W43,"")) | Y43: =IF($B43="","",V43-W43)
A44: =IF($B44="","",ROW()-3) | B44: =IF(40+1>COUNTA('维度字典'!$C$2:$C$200)*COUNTA('维度字典'!$A$2:$A$200)*COUNTA('维度字典'!$E$2:$E$200),"",INDEX('维度字典'!$C$2:$C$200,MOD(INT(40/(COUNTA('维度字典'!$E$2:$E$200)*COUNTA('维度字典'!$A$2:$A$200))),COUNTA('维度字典'!$C$2:$C$200))+1)) | C44: =IF($B44="","",INDEX('维度字典'!$A$2:$A$200,MOD(INT(40/COUNTA('维度字典'!$E$2:$E$200)),COUNTA('维度字典'!$A$2:$A$200))+1)) | D44: =IF($B44="","",INDEX('维度字典'!$E$2:$E$200,MOD(40,COUNTA('维度字典'!$E$2:$E$200))+1)) | E44: =IF($B44="","",SUMPRODUCT(('系统实绩导入'!$B$4:$B$1500=$B44)*('系统实绩导入'!$C$4:$C$1500=$C44)*('系统实绩导入'!$D$4:$D$1500=$D44)*('系统实绩导入'!$F$4:$F$1500="实绩销售额")*('系统实绩导入'!$G$3:$R$3=$F$1)*'系统实绩导入'!$G$4:$R$1500)) | F44: =IF($B44="","",SUMPRODUCT(('系统实绩导入'!$B$4:$B$1500=$B44)*('系统实绩导入'!$C$4:$C$1500=$C44)*('系统实绩导入'!$D$4:$D$1500=$D44)*('系统实绩导入'!$F$4:$F$1500="实绩毛利")*('系统实绩导入'!$G$3:$R$3=$F$1)*'系统实绩导入'!$G$4:$R$1500)) | G44: =IF($B44="","",IFERROR(F44/E44,"")) | H44: =IF($B44="","",SUMPRODUCT(('目标填报'!$B$4:$B$1500=$B44)*('目标填报'!$C$4:$C$1500=$C44)*('目标填报'!$D$4:$D$1500=$D44)*('目标填报'!$F$4:$F$1500="销售目标额")*('目标填报'!$G$3:$R$3=$F$1)*'目标填报'!$G$4:$R$1500)) | I44: =IF($B44="","",IFERROR(E44/H44,"")) | J44: =IF($B44="","",SUMPRODUCT(('系统实绩导入'!$B$4:$B$1500=$B44)*('系统实绩导入'!$C$4:$C$1500=$C44)*('系统实绩导入'!$D$4:$D$1500=$D44)*('系统实绩导入'!$F$4:$F$1500="实绩销售额")*('系统实绩导入'!$G$3:$R$3<=$F$1)*'系统实绩导入'!$G$4:$R$1500)) | K44: =IF($B44="","",SUMPRODUCT(('系统实绩导入'!$B$4:$B$1500=$B44)*('系统实绩导入'!$C$4:$C$1500=$C44)*('系统实绩导入'!$D$4:$D$1500=$D44)*('系统实绩导入'!$F$4:$F$1500="实绩毛利")*('系统实绩导入'!$G$3:$R$3<=$F$1)*'系统实绩导入'!$G$4:$R$1500)) | L44: =IF($B44="","",IFERROR(K44/J44,"")) | M44: =IF($B44="","",SUMIFS('目标填报'!$S$4:$S$1500,'目标填报'!$B$4:$B$1500,$B44,'目标填报'!$C$4:$C$1500,$C44,'目标填报'!$D$4:$D$1500,$D44,'目标填报'!$F$4:$F$1500,"销售目标额")) | N44: =IF($B44="","",IFERROR(J44/M44,"")) | O44: =IF($B44="","",J44-M44) | P44: =IF($B44="","",SUMPRODUCT(('目标填报'!$B$4:$B$1500=$B44)*('目标填报'!$C$4:$C$1500=$C44)*('目标填报'!$D$4:$D$1500=$D44)*('目标填报'!$F$4:$F$1500="在手订单")*('目标填报'!$G$3:$R$3=$F$1)*'目标填报'!$G$4:$R$1500)) | Q44: =IF($B44="","",SUMPRODUCT(('目标填报'!$B$4:$B$1500=$B44)*('目标填报'!$C$4:$C$1500=$C44)*('目标填报'!$D$4:$D$1500=$D44)*('目标填报'!$F$4:$F$1500="在手订单目标")*('目标填报'!$G$3:$R$3=$F$1)*'目标填报'!$G$4:$R$1500)) | R44: =IF($B44="","",IFERROR(P44/Q44,"")) | S44: =IF($B44="","",SUMPRODUCT(('目标填报'!$B$4:$B$1500=$B44)*('目标填报'!$C$4:$C$1500=$C44)*('目标填报'!$D$4:$D$1500=$D44)*('目标填报'!$F$4:$F$1500="目标客户机会")*('目标填报'!$G$3:$R$3=$F$1)*'目标填报'!$G$4:$R$1500)) | T44: =IF($B44="","",SUMPRODUCT(('目标填报'!$B$4:$B$1500=$B44)*('目标填报'!$C$4:$C$1500=$C44)*('目标填报'!$D$4:$D$1500=$D44)*('目标填报'!$F$4:$F$1500="目标客户机会目标")*('目标填报'!$G$3:$R$3=$F$1)*'目标填报'!$G$4:$R$1500)) | U44: =IF($B44="","",IFERROR(S44/T44,"")) | V44: =IF($B44="","",P44+S44) | W44: =IF($B44="","",M44-J44) | X44: =IF($B44="","",IFERROR(V44/W44,"")) | Y44: =IF($B44="","",V44-W44)
A45: =IF($B45="","",ROW()-3) | B45: =IF(41+1>COUNTA('维度字典'!$C$2:$C$200)*COUNTA('维度字典'!$A$2:$A$200)*COUNTA('维度字典'!$E$2:$E$200),"",INDEX('维度字典'!$C$2:$C$200,MOD(INT(41/(COUNTA('维度字典'!$E$2:$E$200)*COUNTA('维度字典'!$A$2:$A$200))),COUNTA('维度字典'!$C$2:$C$200))+1)) | C45: =IF($B45="","",INDEX('维度字典'!$A$2:$A$200,MOD(INT(41/COUNTA('维度字典'!$E$2:$E$200)),COUNTA('维度字典'!$A$2:$A$200))+1)) | D45: =IF($B45="","",INDEX('维度字典'!$E$2:$E$200,MOD(41,COUNTA('维度字典'!$E$2:$E$200))+1)) | E45: =IF($B45="","",SUMPRODUCT(('系统实绩导入'!$B$4:$B$1500=$B45)*('系统实绩导入'!$C$4:$C$1500=$C45)*('系统实绩导入'!$D$4:$D$1500=$D45)*('系统实绩导入'!$F$4:$F$1500="实绩销售额")*('系统实绩导入'!$G$3:$R$3=$F$1)*'系统实绩导入'!$G$4:$R$1500)) | F45: =IF($B45="","",SUMPRODUCT(('系统实绩导入'!$B$4:$B$1500=$B45)*('系统实绩导入'!$C$4:$C$1500=$C45)*('系统实绩导入'!$D$4:$D$1500=$D45)*('系统实绩导入'!$F$4:$F$1500="实绩毛利")*('系统实绩导入'!$G$3:$R$3=$F$1)*'系统实绩导入'!$G$4:$R$1500)) | G45: =IF($B45="","",IFERROR(F45/E45,"")) | H45: =IF($B45="","",SUMPRODUCT(('目标填报'!$B$4:$B$1500=$B45)*('目标填报'!$C$4:$C$1500=$C45)*('目标填报'!$D$4:$D$1500=$D45)*('目标填报'!$F$4:$F$1500="销售目标额")*('目标填报'!$G$3:$R$3=$F$1)*'目标填报'!$G$4:$R$1500)) | I45: =IF($B45="","",IFERROR(E45/H45,"")) | J45: =IF($B45="","",SUMPRODUCT(('系统实绩导入'!$B$4:$B$1500=$B45)*('系统实绩导入'!$C$4:$C$1500=$C45)*('系统实绩导入'!$D$4:$D$1500=$D45)*('系统实绩导入'!$F$4:$F$1500="实绩销售额")*('系统实绩导入'!$G$3:$R$3<=$F$1)*'系统实绩导入'!$G$4:$R$1500)) | K45: =IF($B45="","",SUMPRODUCT(('系统实绩导入'!$B$4:$B$1500=$B45)*('系统实绩导入'!$C$4:$C$1500=$C45)*('系统实绩导入'!$D$4:$D$1500=$D45)*('系统实绩导入'!$F$4:$F$1500="实绩毛利")*('系统实绩导入'!$G$3:$R$3<=$F$1)*'系统实绩导入'!$G$4:$R$1500)) | L45: =IF($B45="","",IFERROR(K45/J45,"")) | M45: =IF($B45="","",SUMIFS('目标填报'!$S$4:$S$1500,'目标填报'!$B$4:$B$1500,$B45,'目标填报'!$C$4:$C$1500,$C45,'目标填报'!$D$4:$D$1500,$D45,'目标填报'!$F$4:$F$1500,"销售目标额")) | N45: =IF($B45="","",IFERROR(J45/M45,"")) | O45: =IF($B45="","",J45-M45) | P45: =IF($B45="","",SUMPRODUCT(('目标填报'!$B$4:$B$1500=$B45)*('目标填报'!$C$4:$C$1500=$C45)*('目标填报'!$D$4:$D$1500=$D45)*('目标填报'!$F$4:$F$1500="在手订单")*('目标填报'!$G$3:$R$3=$F$1)*'目标填报'!$G$4:$R$1500)) | Q45: =IF($B45="","",SUMPRODUCT(('目标填报'!$B$4:$B$1500=$B45)*('目标填报'!$C$4:$C$1500=$C45)*('目标填报'!$D$4:$D$1500=$D45)*('目标填报'!$F$4:$F$1500="在手订单目标")*('目标填报'!$G$3:$R$3=$F$1)*'目标填报'!$G$4:$R$1500)) | R45: =IF($B45="","",IFERROR(P45/Q45,"")) | S45: =IF($B45="","",SUMPRODUCT(('目标填报'!$B$4:$B$1500=$B45)*('目标填报'!$C$4:$C$1500=$C45)*('目标填报'!$D$4:$D$1500=$D45)*('目标填报'!$F$4:$F$1500="目标客户机会")*('目标填报'!$G$3:$R$3=$F$1)*'目标填报'!$G$4:$R$1500)) | T45: =IF($B45="","",SUMPRODUCT(('目标填报'!$B$4:$B$1500=$B45)*('目标填报'!$C$4:$C$1500=$C45)*('目标填报'!$D$4:$D$1500=$D45)*('目标填报'!$F$4:$F$1500="目标客户机会目标")*('目标填报'!$G$3:$R$3=$F$1)*'目标填报'!$G$4:$R$1500)) | U45: =IF($B45="","",IFERROR(S45/T45,"")) | V45: =IF($B45="","",P45+S45) | W45: =IF($B45="","",M45-J45) | X45: =IF($B45="","",IFERROR(V45/W45,"")) | Y45: =IF($B45="","",V45-W45)
A46: =IF($B46="","",ROW()-3) | B46: =IF(42+1>COUNTA('维度字典'!$C$2:$C$200)*COUNTA('维度字典'!$A$2:$A$200)*COUNTA('维度字典'!$E$2:$E$200),"",INDEX('维度字典'!$C$2:$C$200,MOD(INT(42/(COUNTA('维度字典'!$E$2:$E$200)*COUNTA('维度字典'!$A$2:$A$200))),COUNTA('维度字典'!$C$2:$C$200))+1)) | C46: =IF($B46="","",INDEX('维度字典'!$A$2:$A$200,MOD(INT(42/COUNTA('维度字典'!$E$2:$E$200)),COUNTA('维度字典'!$A$2:$A$200))+1)) | D46: =IF($B46="","",INDEX('维度字典'!$E$2:$E$200,MOD(42,COUNTA('维度字典'!$E$2:$E$200))+1)) | E46: =IF($B46="","",SUMPRODUCT(('系统实绩导入'!$B$4:$B$1500=$B46)*('系统实绩导入'!$C$4:$C$1500=$C46)*('系统实绩导入'!$D$4:$D$1500=$D46)*('系统实绩导入'!$F$4:$F$1500="实绩销售额")*('系统实绩导入'!$G$3:$R$3=$F$1)*'系统实绩导入'!$G$4:$R$1500)) | F46: =IF($B46="","",SUMPRODUCT(('系统实绩导入'!$B$4:$B$1500=$B46)*('系统实绩导入'!$C$4:$C$1500=$C46)*('系统实绩导入'!$D$4:$D$1500=$D46)*('系统实绩导入'!$F$4:$F$1500="实绩毛利")*('系统实绩导入'!$G$3:$R$3=$F$1)*'系统实绩导入'!$G$4:$R$1500)) | G46: =IF($B46="","",IFERROR(F46/E46,"")) | H46: =IF($B46="","",SUMPRODUCT(('目标填报'!$B$4:$B$1500=$B46)*('目标填报'!$C$4:$C$1500=$C46)*('目标填报'!$D$4:$D$1500=$D46)*('目标填报'!$F$4:$F$1500="销售目标额")*('目标填报'!$G$3:$R$3=$F$1)*'目标填报'!$G$4:$R$1500)) | I46: =IF($B46="","",IFERROR(E46/H46,"")) | J46: =IF($B46="","",SUMPRODUCT(('系统实绩导入'!$B$4:$B$1500=$B46)*('系统实绩导入'!$C$4:$C$1500=$C46)*('系统实绩导入'!$D$4:$D$1500=$D46)*('系统实绩导入'!$F$4:$F$1500="实绩销售额")*('系统实绩导入'!$G$3:$R$3<=$F$1)*'系统实绩导入'!$G$4:$R$1500)) | K46: =IF($B46="","",SUMPRODUCT(('系统实绩导入'!$B$4:$B$1500=$B46)*('系统实绩导入'!$C$4:$C$1500=$C46)*('系统实绩导入'!$D$4:$D$1500=$D46)*('系统实绩导入'!$F$4:$F$1500="实绩毛利")*('系统实绩导入'!$G$3:$R$3<=$F$1)*'系统实绩导入'!$G$4:$R$1500)) | L46: =IF($B46="","",IFERROR(K46/J46,"")) | M46: =IF($B46="","",SUMIFS('目标填报'!$S$4:$S$1500,'目标填报'!$B$4:$B$1500,$B46,'目标填报'!$C$4:$C$1500,$C46,'目标填报'!$D$4:$D$1500,$D46,'目标填报'!$F$4:$F$1500,"销售目标额")) | N46: =IF($B46="","",IFERROR(J46/M46,"")) | O46: =IF($B46="","",J46-M46) | P46: =IF($B46="","",SUMPRODUCT(('目标填报'!$B$4:$B$1500=$B46)*('目标填报'!$C$4:$C$1500=$C46)*('目标填报'!$D$4:$D$1500=$D46)*('目标填报'!$F$4:$F$1500="在手订单")*('目标填报'!$G$3:$R$3=$F$1)*'目标填报'!$G$4:$R$1500)) | Q46: =IF($B46="","",SUMPRODUCT(('目标填报'!$B$4:$B$1500=$B46)*('目标填报'!$C$4:$C$1500=$C46)*('目标填报'!$D$4:$D$1500=$D46)*('目标填报'!$F$4:$F$1500="在手订单目标")*('目标填报'!$G$3:$R$3=$F$1)*'目标填报'!$G$4:$R$1500)) | R46: =IF($B46="","",IFERROR(P46/Q46,"")) | S46: =IF($B46="","",SUMPRODUCT(('目标填报'!$B$4:$B$1500=$B46)*('目标填报'!$C$4:$C$1500=$C46)*('目标填报'!$D$4:$D$1500=$D46)*('目标填报'!$F$4:$F$1500="目标客户机会")*('目标填报'!$G$3:$R$3=$F$1)*'目标填报'!$G$4:$R$1500)) | T46: =IF($B46="","",SUMPRODUCT(('目标填报'!$B$4:$B$1500=$B46)*('目标填报'!$C$4:$C$1500=$C46)*('目标填报'!$D$4:$D$1500=$D46)*('目标填报'!$F$4:$F$1500="目标客户机会目标")*('目标填报'!$G$3:$R$3=$F$1)*'目标填报'!$G$4:$R$1500)) | U46: =IF($B46="","",IFERROR(S46/T46,"")) | V46: =IF($B46="","",P46+S46) | W46: =IF($B46="","",M46-J46) | X46: =IF($B46="","",IFERROR(V46/W46,"")) | Y46: =IF($B46="","",V46-W46)
A47: =IF($B47="","",ROW()-3) | B47: =IF(43+1>COUNTA('维度字典'!$C$2:$C$200)*COUNTA('维度字典'!$A$2:$A$200)*COUNTA('维度字典'!$E$2:$E$200),"",INDEX('维度字典'!$C$2:$C$200,MOD(INT(43/(COUNTA('维度字典'!$E$2:$E$200)*COUNTA('维度字典'!$A$2:$A$200))),COUNTA('维度字典'!$C$2:$C$200))+1)) | C47: =IF($B47="","",INDEX('维度字典'!$A$2:$A$200,MOD(INT(43/COUNTA('维度字典'!$E$2:$E$200)),COUNTA('维度字典'!$A$2:$A$200))+1)) | D47: =IF($B47="","",INDEX('维度字典'!$E$2:$E$200,MOD(43,COUNTA('维度字典'!$E$2:$E$200))+1)) | E47: =IF($B47="","",SUMPRODUCT(('系统实绩导入'!$B$4:$B$1500=$B47)*('系统实绩导入'!$C$4:$C$1500=$C47)*('系统实绩导入'!$D$4:$D$1500=$D47)*('系统实绩导入'!$F$4:$F$1500="实绩销售额")*('系统实绩导入'!$G$3:$R$3=$F$1)*'系统实绩导入'!$G$4:$R$1500)) | F47: =IF($B47="","",SUMPRODUCT(('系统实绩导入'!$B$4:$B$1500=$B47)*('系统实绩导入'!$C$4:$C$1500=$C47)*('系统实绩导入'!$D$4:$D$1500=$D47)*('系统实绩导入'!$F$4:$F$1500="实绩毛利")*('系统实绩导入'!$G$3:$R$3=$F$1)*'系统实绩导入'!$G$4:$R$1500)) | G47: =IF($B47="","",IFERROR(F47/E47,"")) | H47: =IF($B47="","",SUMPRODUCT(('目标填报'!$B$4:$B$1500=$B47)*('目标填报'!$C$4:$C$1500=$C47)*('目标填报'!$D$4:$D$1500=$D47)*('目标填报'!$F$4:$F$1500="销售目标额")*('目标填报'!$G$3:$R$3=$F$1)*'目标填报'!$G$4:$R$1500)) | I47: =IF($B47="","",IFERROR(E47/H47,"")) | J47: =IF($B47="","",SUMPRODUCT(('系统实绩导入'!$B$4:$B$1500=$B47)*('系统实绩导入'!$C$4:$C$1500=$C47)*('系统实绩导入'!$D$4:$D$1500=$D47)*('系统实绩导入'!$F$4:$F$1500="实绩销售额")*('系统实绩导入'!$G$3:$R$3<=$F$1)*'系统实绩导入'!$G$4:$R$1500)) | K47: =IF($B47="","",SUMPRODUCT(('系统实绩导入'!$B$4:$B$1500=$B47)*('系统实绩导入'!$C$4:$C$1500=$C47)*('系统实绩导入'!$D$4:$D$1500=$D47)*('系统实绩导入'!$F$4:$F$1500="实绩毛利")*('系统实绩导入'!$G$3:$R$3<=$F$1)*'系统实绩导入'!$G$4:$R$1500)) | L47: =IF($B47="","",IFERROR(K47/J47,"")) | M47: =IF($B47="","",SUMIFS('目标填报'!$S$4:$S$1500,'目标填报'!$B$4:$B$1500,$B47,'目标填报'!$C$4:$C$1500,$C47,'目标填报'!$D$4:$D$1500,$D47,'目标填报'!$F$4:$F$1500,"销售目标额")) | N47: =IF($B47="","",IFERROR(J47/M47,"")) | O47: =IF($B47="","",J47-M47) | P47: =IF($B47="","",SUMPRODUCT(('目标填报'!$B$4:$B$1500=$B47)*('目标填报'!$C$4:$C$1500=$C47)*('目标填报'!$D$4:$D$1500=$D47)*('目标填报'!$F$4:$F$1500="在手订单")*('目标填报'!$G$3:$R$3=$F$1)*'目标填报'!$G$4:$R$1500)) | Q47: =IF($B47="","",SUMPRODUCT(('目标填报'!$B$4:$B$1500=$B47)*('目标填报'!$C$4:$C$1500=$C47)*('目标填报'!$D$4:$D$1500=$D47)*('目标填报'!$F$4:$F$1500="在手订单目标")*('目标填报'!$G$3:$R$3=$F$1)*'目标填报'!$G$4:$R$1500)) | R47: =IF($B47="","",IFERROR(P47/Q47,"")) | S47: =IF($B47="","",SUMPRODUCT(('目标填报'!$B$4:$B$1500=$B47)*('目标填报'!$C$4:$C$1500=$C47)*('目标填报'!$D$4:$D$1500=$D47)*('目标填报'!$F$4:$F$1500="目标客户机会")*('目标填报'!$G$3:$R$3=$F$1)*'目标填报'!$G$4:$R$1500)) | T47: =IF($B47="","",SUMPRODUCT(('目标填报'!$B$4:$B$1500=$B47)*('目标填报'!$C$4:$C$1500=$C47)*('目标填报'!$D$4:$D$1500=$D47)*('目标填报'!$F$4:$F$1500="目标客户机会目标")*('目标填报'!$G$3:$R$3=$F$1)*'目标填报'!$G$4:$R$1500)) | U47: =IF($B47="","",IFERROR(S47/T47,"")) | V47: =IF($B47="","",P47+S47) | W47: =IF($B47="","",M47-J47) | X47: =IF($B47="","",IFERROR(V47/W47,"")) | Y47: =IF($B47="","",V47-W47)
A48: =IF($B48="","",ROW()-3) | B48: =IF(44+1>COUNTA('维度字典'!$C$2:$C$200)*COUNTA('维度字典'!$A$2:$A$200)*COUNTA('维度字典'!$E$2:$E$200),"",INDEX('维度字典'!$C$2:$C$200,MOD(INT(44/(COUNTA('维度字典'!$E$2:$E$200)*COUNTA('维度字典'!$A$2:$A$200))),COUNTA('维度字典'!$C$2:$C$200))+1)) | C48: =IF($B48="","",INDEX('维度字典'!$A$2:$A$200,MOD(INT(44/COUNTA('维度字典'!$E$2:$E$200)),COUNTA('维度字典'!$A$2:$A$200))+1)) | D48: =IF($B48="","",INDEX('维度字典'!$E$2:$E$200,MOD(44,COUNTA('维度字典'!$E$2:$E$200))+1)) | E48: =IF($B48="","",SUMPRODUCT(('系统实绩导入'!$B$4:$B$1500=$B48)*('系统实绩导入'!$C$4:$C$1500=$C48)*('系统实绩导入'!$D$4:$D$1500=$D48)*('系统实绩导入'!$F$4:$F$1500="实绩销售额")*('系统实绩导入'!$G$3:$R$3=$F$1)*'系统实绩导入'!$G$4:$R$1500)) | F48: =IF($B48="","",SUMPRODUCT(('系统实绩导入'!$B$4:$B$1500=$B48)*('系统实绩导入'!$C$4:$C$1500=$C48)*('系统实绩导入'!$D$4:$D$1500=$D48)*('系统实绩导入'!$F$4:$F$1500="实绩毛利")*('系统实绩导入'!$G$3:$R$3=$F$1)*'系统实绩导入'!$G$4:$R$1500)) | G48: =IF($B48="","",IFERROR(F48/E48,"")) | H48: =IF($B48="","",SUMPRODUCT(('目标填报'!$B$4:$B$1500=$B48)*('目标填报'!$C$4:$C$1500=$C48)*('目标填报'!$D$4:$D$1500=$D48)*('目标填报'!$F$4:$F$1500="销售目标额")*('目标填报'!$G$3:$R$3=$F$1)*'目标填报'!$G$4:$R$1500)) | I48: =IF($B48="","",IFERROR(E48/H48,"")) | J48: =IF($B48="","",SUMPRODUCT(('系统实绩导入'!$B$4:$B$1500=$B48)*('系统实绩导入'!$C$4:$C$1500=$C48)*('系统实绩导入'!$D$4:$D$1500=$D48)*('系统实绩导入'!$F$4:$F$1500="实绩销售额")*('系统实绩导入'!$G$3:$R$3<=$F$1)*'系统实绩导入'!$G$4:$R$1500)) | K48: =IF($B48="","",SUMPRODUCT(('系统实绩导入'!$B$4:$B$1500=$B48)*('系统实绩导入'!$C$4:$C$1500=$C48)*('系统实绩导入'!$D$4:$D$1500=$D48)*('系统实绩导入'!$F$4:$F$1500="实绩毛利")*('系统实绩导入'!$G$3:$R$3<=$F$1)*'系统实绩导入'!$G$4:$R$1500)) | L48: =IF($B48="","",IFERROR(K48/J48,"")) | M48: =IF($B48="","",SUMIFS('目标填报'!$S$4:$S$1500,'目标填报'!$B$4:$B$1500,$B48,'目标填报'!$C$4:$C$1500,$C48,'目标填报'!$D$4:$D$1500,$D48,'目标填报'!$F$4:$F$1500,"销售目标额")) | N48: =IF($B48="","",IFERROR(J48/M48,"")) | O48: =IF($B48="","",J48-M48) | P48: =IF($B48="","",SUMPRODUCT(('目标填报'!$B$4:$B$1500=$B48)*('目标填报'!$C$4:$C$1500=$C48)*('目标填报'!$D$4:$D$1500=$D48)*('目标填报'!$F$4:$F$1500="在手订单")*('目标填报'!$G$3:$R$3=$F$1)*'目标填报'!$G$4:$R$1500)) | Q48: =IF($B48="","",SUMPRODUCT(('目标填报'!$B$4:$B$1500=$B48)*('目标填报'!$C$4:$C$1500=$C48)*('目标填报'!$D$4:$D$1500=$D48)*('目标填报'!$F$4:$F$1500="在手订单目标")*('目标填报'!$G$3:$R$3=$F$1)*'目标填报'!$G$4:$R$1500)) | R48: =IF($B48="","",IFERROR(P48/Q48,"")) | S48: =IF($B48="","",SUMPRODUCT(('目标填报'!$B$4:$B$1500=$B48)*('目标填报'!$C$4:$C$1500=$C48)*('目标填报'!$D$4:$D$1500=$D48)*('目标填报'!$F$4:$F$1500="目标客户机会")*('目标填报'!$G$3:$R$3=$F$1)*'目标填报'!$G$4:$R$1500)) | T48: =IF($B48="","",SUMPRODUCT(('目标填报'!$B$4:$B$1500=$B48)*('目标填报'!$C$4:$C$1500=$C48)*('目标填报'!$D$4:$D$1500=$D48)*('目标填报'!$F$4:$F$1500="目标客户机会目标")*('目标填报'!$G$3:$R$3=$F$1)*'目标填报'!$G$4:$R$1500)) | U48: =IF($B48="","",IFERROR(S48/T48,"")) | V48: =IF($B48="","",P48+S48) | W48: =IF($B48="","",M48-J48) | X48: =IF($B48="","",IFERROR(V48/W48,"")) | Y48: =IF($B48="","",V48-W48)
A49: =IF($B49="","",ROW()-3) | B49: =IF(45+1>COUNTA('维度字典'!$C$2:$C$200)*COUNTA('维度字典'!$A$2:$A$200)*COUNTA('维度字典'!$E$2:$E$200),"",INDEX('维度字典'!$C$2:$C$200,MOD(INT(45/(COUNTA('维度字典'!$E$2:$E$200)*COUNTA('维度字典'!$A$2:$A$200))),COUNTA('维度字典'!$C$2:$C$200))+1)) | C49: =IF($B49="","",INDEX('维度字典'!$A$2:$A$200,MOD(INT(45/COUNTA('维度字典'!$E$2:$E$200)),COUNTA('维度字典'!$A$2:$A$200))+1)) | D49: =IF($B49="","",INDEX('维度字典'!$E$2:$E$200,MOD(45,COUNTA('维度字典'!$E$2:$E$200))+1)) | E49: =IF($B49="","",SUMPRODUCT(('系统实绩导入'!$B$4:$B$1500=$B49)*('系统实绩导入'!$C$4:$C$1500=$C49)*('系统实绩导入'!$D$4:$D$1500=$D49)*('系统实绩导入'!$F$4:$F$1500="实绩销售额")*('系统实绩导入'!$G$3:$R$3=$F$1)*'系统实绩导入'!$G$4:$R$1500)) | F49: =IF($B49="","",SUMPRODUCT(('系统实绩导入'!$B$4:$B$1500=$B49)*('系统实绩导入'!$C$4:$C$1500=$C49)*('系统实绩导入'!$D$4:$D$1500=$D49)*('系统实绩导入'!$F$4:$F$1500="实绩毛利")*('系统实绩导入'!$G$3:$R$3=$F$1)*'系统实绩导入'!$G$4:$R$1500)) | G49: =IF($B49="","",IFERROR(F49/E49,"")) | H49: =IF($B49="","",SUMPRODUCT(('目标填报'!$B$4:$B$1500=$B49)*('目标填报'!$C$4:$C$1500=$C49)*('目标填报'!$D$4:$D$1500=$D49)*('目标填报'!$F$4:$F$1500="销售目标额")*('目标填报'!$G$3:$R$3=$F$1)*'目标填报'!$G$4:$R$1500)) | I49: =IF($B49="","",IFERROR(E49/H49,"")) | J49: =IF($B49="","",SUMPRODUCT(('系统实绩导入'!$B$4:$B$1500=$B49)*('系统实绩导入'!$C$4:$C$1500=$C49)*('系统实绩导入'!$D$4:$D$1500=$D49)*('系统实绩导入'!$F$4:$F$1500="实绩销售额")*('系统实绩导入'!$G$3:$R$3<=$F$1)*'系统实绩导入'!$G$4:$R$1500)) | K49: =IF($B49="","",SUMPRODUCT(('系统实绩导入'!$B$4:$B$1500=$B49)*('系统实绩导入'!$C$4:$C$1500=$C49)*('系统实绩导入'!$D$4:$D$1500=$D49)*('系统实绩导入'!$F$4:$F$1500="实绩毛利")*('系统实绩导入'!$G$3:$R$3<=$F$1)*'系统实绩导入'!$G$4:$R$1500)) | L49: =IF($B49="","",IFERROR(K49/J49,"")) | M49: =IF($B49="","",SUMIFS('目标填报'!$S$4:$S$1500,'目标填报'!$B$4:$B$1500,$B49,'目标填报'!$C$4:$C$1500,$C49,'目标填报'!$D$4:$D$1500,$D49,'目标填报'!$F$4:$F$1500,"销售目标额")) | N49: =IF($B49="","",IFERROR(J49/M49,"")) | O49: =IF($B49="","",J49-M49) | P49: =IF($B49="","",SUMPRODUCT(('目标填报'!$B$4:$B$1500=$B49)*('目标填报'!$C$4:$C$1500=$C49)*('目标填报'!$D$4:$D$1500=$D49)*('目标填报'!$F$4:$F$1500="在手订单")*('目标填报'!$G$3:$R$3=$F$1)*'目标填报'!$G$4:$R$1500)) | Q49: =IF($B49="","",SUMPRODUCT(('目标填报'!$B$4:$B$1500=$B49)*('目标填报'!$C$4:$C$1500=$C49)*('目标填报'!$D$4:$D$1500=$D49)*('目标填报'!$F$4:$F$1500="在手订单目标")*('目标填报'!$G$3:$R$3=$F$1)*'目标填报'!$G$4:$R$1500)) | R49: =IF($B49="","",IFERROR(P49/Q49,"")) | S49: =IF($B49="","",SUMPRODUCT(('目标填报'!$B$4:$B$1500=$B49)*('目标填报'!$C$4:$C$1500=$C49)*('目标填报'!$D$4:$D$1500=$D49)*('目标填报'!$F$4:$F$1500="目标客户机会")*('目标填报'!$G$3:$R$3=$F$1)*'目标填报'!$G$4:$R$1500)) | T49: =IF($B49="","",SUMPRODUCT(('目标填报'!$B$4:$B$1500=$B49)*('目标填报'!$C$4:$C$1500=$C49)*('目标填报'!$D$4:$D$1500=$D49)*('目标填报'!$F$4:$F$1500="目标客户机会目标")*('目标填报'!$G$3:$R$3=$F$1)*'目标填报'!$G$4:$R$1500)) | U49: =IF($B49="","",IFERROR(S49/T49,"")) | V49: =IF($B49="","",P49+S49) | W49: =IF($B49="","",M49-J49) | X49: =IF($B49="","",IFERROR(V49/W49,"")) | Y49: =IF($B49="","",V49-W49)
A50: =IF($B50="","",ROW()-3) | B50: =IF(46+1>COUNTA('维度字典'!$C$2:$C$200)*COUNTA('维度字典'!$A$2:$A$200)*COUNTA('维度字典'!$E$2:$E$200),"",INDEX('维度字典'!$C$2:$C$200,MOD(INT(46/(COUNTA('维度字典'!$E$2:$E$200)*COUNTA('维度字典'!$A$2:$A$200))),COUNTA('维度字典'!$C$2:$C$200))+1)) | C50: =IF($B50="","",INDEX('维度字典'!$A$2:$A$200,MOD(INT(46/COUNTA('维度字典'!$E$2:$E$200)),COUNTA('维度字典'!$A$2:$A$200))+1)) | D50: =IF($B50="","",INDEX('维度字典'!$E$2:$E$200,MOD(46,COUNTA('维度字典'!$E$2:$E$200))+1)) | E50: =IF($B50="","",SUMPRODUCT(('系统实绩导入'!$B$4:$B$1500=$B50)*('系统实绩导入'!$C$4:$C$1500=$C50)*('系统实绩导入'!$D$4:$D$1500=$D50)*('系统实绩导入'!$F$4:$F$1500="实绩销售额")*('系统实绩导入'!$G$3:$R$3=$F$1)*'系统实绩导入'!$G$4:$R$1500)) | F50: =IF($B50="","",SUMPRODUCT(('系统实绩导入'!$B$4:$B$1500=$B50)*('系统实绩导入'!$C$4:$C$1500=$C50)*('系统实绩导入'!$D$4:$D$1500=$D50)*('系统实绩导入'!$F$4:$F$1500="实绩毛利")*('系统实绩导入'!$G$3:$R$3=$F$1)*'系统实绩导入'!$G$4:$R$1500)) | G50: =IF($B50="","",IFERROR(F50/E50,"")) | H50: =IF($B50="","",SUMPRODUCT(('目标填报'!$B$4:$B$1500=$B50)*('目标填报'!$C$4:$C$1500=$C50)*('目标填报'!$D$4:$D$1500=$D50)*('目标填报'!$F$4:$F$1500="销售目标额")*('目标填报'!$G$3:$R$3=$F$1)*'目标填报'!$G$4:$R$1500)) | I50: =IF($B50="","",IFERROR(E50/H50,"")) | J50: =IF($B50="","",SUMPRODUCT(('系统实绩导入'!$B$4:$B$1500=$B50)*('系统实绩导入'!$C$4:$C$1500=$C50)*('系统实绩导入'!$D$4:$D$1500=$D50)*('系统实绩导入'!$F$4:$F$1500="实绩销售额")*('系统实绩导入'!$G$3:$R$3<=$F$1)*'系统实绩导入'!$G$4:$R$1500)) | K50: =IF($B50="","",SUMPRODUCT(('系统实绩导入'!$B$4:$B$1500=$B50)*('系统实绩导入'!$C$4:$C$1500=$C50)*('系统实绩导入'!$D$4:$D$1500=$D50)*('系统实绩导入'!$F$4:$F$1500="实绩毛利")*('系统实绩导入'!$G$3:$R$3<=$F$1)*'系统实绩导入'!$G$4:$R$1500)) | L50: =IF($B50="","",IFERROR(K50/J50,"")) | M50: =IF($B50="","",SUMIFS('目标填报'!$S$4:$S$1500,'目标填报'!$B$4:$B$1500,$B50,'目标填报'!$C$4:$C$1500,$C50,'目标填报'!$D$4:$D$1500,$D50,'目标填报'!$F$4:$F$1500,"销售目标额")) | N50: =IF($B50="","",IFERROR(J50/M50,"")) | O50: =IF($B50="","",J50-M50) | P50: =IF($B50="","",SUMPRODUCT(('目标填报'!$B$4:$B$1500=$B50)*('目标填报'!$C$4:$C$1500=$C50)*('目标填报'!$D$4:$D$1500=$D50)*('目标填报'!$F$4:$F$1500="在手订单")*('目标填报'!$G$3:$R$3=$F$1)*'目标填报'!$G$4:$R$1500)) | Q50: =IF($B50="","",SUMPRODUCT(('目标填报'!$B$4:$B$1500=$B50)*('目标填报'!$C$4:$C$1500=$C50)*('目标填报'!$D$4:$D$1500=$D50)*('目标填报'!$F$4:$F$1500="在手订单目标")*('目标填报'!$G$3:$R$3=$F$1)*'目标填报'!$G$4:$R$1500)) | R50: =IF($B50="","",IFERROR(P50/Q50,"")) | S50: =IF($B50="","",SUMPRODUCT(('目标填报'!$B$4:$B$1500=$B50)*('目标填报'!$C$4:$C$1500=$C50)*('目标填报'!$D$4:$D$1500=$D50)*('目标填报'!$F$4:$F$1500="目标客户机会")*('目标填报'!$G$3:$R$3=$F$1)*'目标填报'!$G$4:$R$1500)) | T50: =IF($B50="","",SUMPRODUCT(('目标填报'!$B$4:$B$1500=$B50)*('目标填报'!$C$4:$C$1500=$C50)*('目标填报'!$D$4:$D$1500=$D50)*('目标填报'!$F$4:$F$1500="目标客户机会目标")*('目标填报'!$G$3:$R$3=$F$1)*'目标填报'!$G$4:$R$1500)) | U50: =IF($B50="","",IFERROR(S50/T50,"")) | V50: =IF($B50="","",P50+S50) | W50: =IF($B50="","",M50-J50) | X50: =IF($B50="","",IFERROR(V50/W50,"")) | Y50: =IF($B50="","",V50-W50)
A51: =IF($B51="","",ROW()-3) | B51: =IF(47+1>COUNTA('维度字典'!$C$2:$C$200)*COUNTA('维度字典'!$A$2:$A$200)*COUNTA('维度字典'!$E$2:$E$200),"",INDEX('维度字典'!$C$2:$C$200,MOD(INT(47/(COUNTA('维度字典'!$E$2:$E$200)*COUNTA('维度字典'!$A$2:$A$200))),COUNTA('维度字典'!$C$2:$C$200))+1)) | C51: =IF($B51="","",INDEX('维度字典'!$A$2:$A$200,MOD(INT(47/COUNTA('维度字典'!$E$2:$E$200)),COUNTA('维度字典'!$A$2:$A$200))+1)) | D51: =IF($B51="","",INDEX('维度字典'!$E$2:$E$200,MOD(47,COUNTA('维度字典'!$E$2:$E$200))+1)) | E51: =IF($B51="","",SUMPRODUCT(('系统实绩导入'!$B$4:$B$1500=$B51)*('系统实绩导入'!$C$4:$C$1500=$C51)*('系统实绩导入'!$D$4:$D$1500=$D51)*('系统实绩导入'!$F$4:$F$1500="实绩销售额")*('系统实绩导入'!$G$3:$R$3=$F$1)*'系统实绩导入'!$G$4:$R$1500)) | F51: =IF($B51="","",SUMPRODUCT(('系统实绩导入'!$B$4:$B$1500=$B51)*('系统实绩导入'!$C$4:$C$1500=$C51)*('系统实绩导入'!$D$4:$D$1500=$D51)*('系统实绩导入'!$F$4:$F$1500="实绩毛利")*('系统实绩导入'!$G$3:$R$3=$F$1)*'系统实绩导入'!$G$4:$R$1500)) | G51: =IF($B51="","",IFERROR(F51/E51,"")) | H51: =IF($B51="","",SUMPRODUCT(('目标填报'!$B$4:$B$1500=$B51)*('目标填报'!$C$4:$C$1500=$C51)*('目标填报'!$D$4:$D$1500=$D51)*('目标填报'!$F$4:$F$1500="销售目标额")*('目标填报'!$G$3:$R$3=$F$1)*'目标填报'!$G$4:$R$1500)) | I51: =IF($B51="","",IFERROR(E51/H51,"")) | J51: =IF($B51="","",SUMPRODUCT(('系统实绩导入'!$B$4:$B$1500=$B51)*('系统实绩导入'!$C$4:$C$1500=$C51)*('系统实绩导入'!$D$4:$D$1500=$D51)*('系统实绩导入'!$F$4:$F$1500="实绩销售额")*('系统实绩导入'!$G$3:$R$3<=$F$1)*'系统实绩导入'!$G$4:$R$1500)) | K51: =IF($B51="","",SUMPRODUCT(('系统实绩导入'!$B$4:$B$1500=$B51)*('系统实绩导入'!$C$4:$C$1500=$C51)*('系统实绩导入'!$D$4:$D$1500=$D51)*('系统实绩导入'!$F$4:$F$1500="实绩毛利")*('系统实绩导入'!$G$3:$R$3<=$F$1)*'系统实绩导入'!$G$4:$R$1500)) | L51: =IF($B51="","",IFERROR(K51/J51,"")) | M51: =IF($B51="","",SUMIFS('目标填报'!$S$4:$S$1500,'目标填报'!$B$4:$B$1500,$B51,'目标填报'!$C$4:$C$1500,$C51,'目标填报'!$D$4:$D$1500,$D51,'目标填报'!$F$4:$F$1500,"销售目标额")) | N51: =IF($B51="","",IFERROR(J51/M51,"")) | O51: =IF($B51="","",J51-M51) | P51: =IF($B51="","",SUMPRODUCT(('目标填报'!$B$4:$B$1500=$B51)*('目标填报'!$C$4:$C$1500=$C51)*('目标填报'!$D$4:$D$1500=$D51)*('目标填报'!$F$4:$F$1500="在手订单")*('目标填报'!$G$3:$R$3=$F$1)*'目标填报'!$G$4:$R$1500)) | Q51: =IF($B51="","",SUMPRODUCT(('目标填报'!$B$4:$B$1500=$B51)*('目标填报'!$C$4:$C$1500=$C51)*('目标填报'!$D$4:$D$1500=$D51)*('目标填报'!$F$4:$F$1500="在手订单目标")*('目标填报'!$G$3:$R$3=$F$1)*'目标填报'!$G$4:$R$1500)) | R51: =IF($B51="","",IFERROR(P51/Q51,"")) | S51: =IF($B51="","",SUMPRODUCT(('目标填报'!$B$4:$B$1500=$B51)*('目标填报'!$C$4:$C$1500=$C51)*('目标填报'!$D$4:$D$1500=$D51)*('目标填报'!$F$4:$F$1500="目标客户机会")*('目标填报'!$G$3:$R$3=$F$1)*'目标填报'!$G$4:$R$1500)) | T51: =IF($B51="","",SUMPRODUCT(('目标填报'!$B$4:$B$1500=$B51)*('目标填报'!$C$4:$C$1500=$C51)*('目标填报'!$D$4:$D$1500=$D51)*('目标填报'!$F$4:$F$1500="目标客户机会目标")*('目标填报'!$G$3:$R$3=$F$1)*'目标填报'!$G$4:$R$1500)) | U51: =IF($B51="","",IFERROR(S51/T51,"")) | V51: =IF($B51="","",P51+S51) | W51: =IF($B51="","",M51-J51) | X51: =IF($B51="","",IFERROR(V51/W51,"")) | Y51: =IF($B51="","",V51-W51)
A52: =IF($B52="","",ROW()-3) | B52: =IF(48+1>COUNTA('维度字典'!$C$2:$C$200)*COUNTA('维度字典'!$A$2:$A$200)*COUNTA('维度字典'!$E$2:$E$200),"",INDEX('维度字典'!$C$2:$C$200,MOD(INT(48/(COUNTA('维度字典'!$E$2:$E$200)*COUNTA('维度字典'!$A$2:$A$200))),COUNTA('维度字典'!$C$2:$C$200))+1)) | C52: =IF($B52="","",INDEX('维度字典'!$A$2:$A$200,MOD(INT(48/COUNTA('维度字典'!$E$2:$E$200)),COUNTA('维度字典'!$A$2:$A$200))+1)) | D52: =IF($B52="","",INDEX('维度字典'!$E$2:$E$200,MOD(48,COUNTA('维度字典'!$E$2:$E$200))+1)) | E52: =IF($B52="","",SUMPRODUCT(('系统实绩导入'!$B$4:$B$1500=$B52)*('系统实绩导入'!$C$4:$C$1500=$C52)*('系统实绩导入'!$D$4:$D$1500=$D52)*('系统实绩导入'!$F$4:$F$1500="实绩销售额")*('系统实绩导入'!$G$3:$R$3=$F$1)*'系统实绩导入'!$G$4:$R$1500)) | F52: =IF($B52="","",SUMPRODUCT(('系统实绩导入'!$B$4:$B$1500=$B52)*('系统实绩导入'!$C$4:$C$1500=$C52)*('系统实绩导入'!$D$4:$D$1500=$D52)*('系统实绩导入'!$F$4:$F$1500="实绩毛利")*('系统实绩导入'!$G$3:$R$3=$F$1)*'系统实绩导入'!$G$4:$R$1500)) | G52: =IF($B52="","",IFERROR(F52/E52,"")) | H52: =IF($B52="","",SUMPRODUCT(('目标填报'!$B$4:$B$1500=$B52)*('目标填报'!$C$4:$C$1500=$C52)*('目标填报'!$D$4:$D$1500=$D52)*('目标填报'!$F$4:$F$1500="销售目标额")*('目标填报'!$G$3:$R$3=$F$1)*'目标填报'!$G$4:$R$1500)) | I52: =IF($B52="","",IFERROR(E52/H52,"")) | J52: =IF($B52="","",SUMPRODUCT(('系统实绩导入'!$B$4:$B$1500=$B52)*('系统实绩导入'!$C$4:$C$1500=$C52)*('系统实绩导入'!$D$4:$D$1500=$D52)*('系统实绩导入'!$F$4:$F$1500="实绩销售额")*('系统实绩导入'!$G$3:$R$3<=$F$1)*'系统实绩导入'!$G$4:$R$1500)) | K52: =IF($B52="","",SUMPRODUCT(('系统实绩导入'!$B$4:$B$1500=$B52)*('系统实绩导入'!$C$4:$C$1500=$C52)*('系统实绩导入'!$D$4:$D$1500=$D52)*('系统实绩导入'!$F$4:$F$1500="实绩毛利")*('系统实绩导入'!$G$3:$R$3<=$F$1)*'系统实绩导入'!$G$4:$R$1500)) | L52: =IF($B52="","",IFERROR(K52/J52,"")) | M52: =IF($B52="","",SUMIFS('目标填报'!$S$4:$S$1500,'目标填报'!$B$4:$B$1500,$B52,'目标填报'!$C$4:$C$1500,$C52,'目标填报'!$D$4:$D$1500,$D52,'目标填报'!$F$4:$F$1500,"销售目标额")) | N52: =IF($B52="","",IFERROR(J52/M52,"")) | O52: =IF($B52="","",J52-M52) | P52: =IF($B52="","",SUMPRODUCT(('目标填报'!$B$4:$B$1500=$B52)*('目标填报'!$C$4:$C$1500=$C52)*('目标填报'!$D$4:$D$1500=$D52)*('目标填报'!$F$4:$F$1500="在手订单")*('目标填报'!$G$3:$R$3=$F$1)*'目标填报'!$G$4:$R$1500)) | Q52: =IF($B52="","",SUMPRODUCT(('目标填报'!$B$4:$B$1500=$B52)*('目标填报'!$C$4:$C$1500=$C52)*('目标填报'!$D$4:$D$1500=$D52)*('目标填报'!$F$4:$F$1500="在手订单目标")*('目标填报'!$G$3:$R$3=$F$1)*'目标填报'!$G$4:$R$1500)) | R52: =IF($B52="","",IFERROR(P52/Q52,"")) | S52: =IF($B52="","",SUMPRODUCT(('目标填报'!$B$4:$B$1500=$B52)*('目标填报'!$C$4:$C$1500=$C52)*('目标填报'!$D$4:$D$1500=$D52)*('目标填报'!$F$4:$F$1500="目标客户机会")*('目标填报'!$G$3:$R$3=$F$1)*'目标填报'!$G$4:$R$1500)) | T52: =IF($B52="","",SUMPRODUCT(('目标填报'!$B$4:$B$1500=$B52)*('目标填报'!$C$4:$C$1500=$C52)*('目标填报'!$D$4:$D$1500=$D52)*('目标填报'!$F$4:$F$1500="目标客户机会目标")*('目标填报'!$G$3:$R$3=$F$1)*'目标填报'!$G$4:$R$1500)) | U52: =IF($B52="","",IFERROR(S52/T52,"")) | V52: =IF($B52="","",P52+S52) | W52: =IF($B52="","",M52-J52) | X52: =IF($B52="","",IFERROR(V52/W52,"")) | Y52: =IF($B52="","",V52-W52)
A53: =IF($B53="","",ROW()-3) | B53: =IF(49+1>COUNTA('维度字典'!$C$2:$C$200)*COUNTA('维度字典'!$A$2:$A$200)*COUNTA('维度字典'!$E$2:$E$200),"",INDEX('维度字典'!$C$2:$C$200,MOD(INT(49/(COUNTA('维度字典'!$E$2:$E$200)*COUNTA('维度字典'!$A$2:$A$200))),COUNTA('维度字典'!$C$2:$C$200))+1)) | C53: =IF($B53="","",INDEX('维度字典'!$A$2:$A$200,MOD(INT(49/COUNTA('维度字典'!$E$2:$E$200)),COUNTA('维度字典'!$A$2:$A$200))+1)) | D53: =IF($B53="","",INDEX('维度字典'!$E$2:$E$200,MOD(49,COUNTA('维度字典'!$E$2:$E$200))+1)) | E53: =IF($B53="","",SUMPRODUCT(('系统实绩导入'!$B$4:$B$1500=$B53)*('系统实绩导入'!$C$4:$C$1500=$C53)*('系统实绩导入'!$D$4:$D$1500=$D53)*('系统实绩导入'!$F$4:$F$1500="实绩销售额")*('系统实绩导入'!$G$3:$R$3=$F$1)*'系统实绩导入'!$G$4:$R$1500)) | F53: =IF($B53="","",SUMPRODUCT(('系统实绩导入'!$B$4:$B$1500=$B53)*('系统实绩导入'!$C$4:$C$1500=$C53)*('系统实绩导入'!$D$4:$D$1500=$D53)*('系统实绩导入'!$F$4:$F$1500="实绩毛利")*('系统实绩导入'!$G$3:$R$3=$F$1)*'系统实绩导入'!$G$4:$R$1500)) | G53: =IF($B53="","",IFERROR(F53/E53,"")) | H53: =IF($B53="","",SUMPRODUCT(('目标填报'!$B$4:$B$1500=$B53)*('目标填报'!$C$4:$C$1500=$C53)*('目标填报'!$D$4:$D$1500=$D53)*('目标填报'!$F$4:$F$1500="销售目标额")*('目标填报'!$G$3:$R$3=$F$1)*'目标填报'!$G$4:$R$1500)) | I53: =IF($B53="","",IFERROR(E53/H53,"")) | J53: =IF($B53="","",SUMPRODUCT(('系统实绩导入'!$B$4:$B$1500=$B53)*('系统实绩导入'!$C$4:$C$1500=$C53)*('系统实绩导入'!$D$4:$D$1500=$D53)*('系统实绩导入'!$F$4:$F$1500="实绩销售额")*('系统实绩导入'!$G$3:$R$3<=$F$1)*'系统实绩导入'!$G$4:$R$1500)) | K53: =IF($B53="","",SUMPRODUCT(('系统实绩导入'!$B$4:$B$1500=$B53)*('系统实绩导入'!$C$4:$C$1500=$C53)*('系统实绩导入'!$D$4:$D$1500=$D53)*('系统实绩导入'!$F$4:$F$1500="实绩毛利")*('系统实绩导入'!$G$3:$R$3<=$F$1)*'系统实绩导入'!$G$4:$R$1500)) | L53: =IF($B53="","",IFERROR(K53/J53,"")) | M53: =IF($B53="","",SUMIFS('目标填报'!$S$4:$S$1500,'目标填报'!$B$4:$B$1500,$B53,'目标填报'!$C$4:$C$1500,$C53,'目标填报'!$D$4:$D$1500,$D53,'目标填报'!$F$4:$F$1500,"销售目标额")) | N53: =IF($B53="","",IFERROR(J53/M53,"")) | O53: =IF($B53="","",J53-M53) | P53: =IF($B53="","",SUMPRODUCT(('目标填报'!$B$4:$B$1500=$B53)*('目标填报'!$C$4:$C$1500=$C53)*('目标填报'!$D$4:$D$1500=$D53)*('目标填报'!$F$4:$F$1500="在手订单")*('目标填报'!$G$3:$R$3=$F$1)*'目标填报'!$G$4:$R$1500)) | Q53: =IF($B53="","",SUMPRODUCT(('目标填报'!$B$4:$B$1500=$B53)*('目标填报'!$C$4:$C$1500=$C53)*('目标填报'!$D$4:$D$1500=$D53)*('目标填报'!$F$4:$F$1500="在手订单目标")*('目标填报'!$G$3:$R$3=$F$1)*'目标填报'!$G$4:$R$1500)) | R53: =IF($B53="","",IFERROR(P53/Q53,"")) | S53: =IF($B53="","",SUMPRODUCT(('目标填报'!$B$4:$B$1500=$B53)*('目标填报'!$C$4:$C$1500=$C53)*('目标填报'!$D$4:$D$1500=$D53)*('目标填报'!$F$4:$F$1500="目标客户机会")*('目标填报'!$G$3:$R$3=$F$1)*'目标填报'!$G$4:$R$1500)) | T53: =IF($B53="","",SUMPRODUCT(('目标填报'!$B$4:$B$1500=$B53)*('目标填报'!$C$4:$C$1500=$C53)*('目标填报'!$D$4:$D$1500=$D53)*('目标填报'!$F$4:$F$1500="目标客户机会目标")*('目标填报'!$G$3:$R$3=$F$1)*'目标填报'!$G$4:$R$1500)) | U53: =IF($B53="","",IFERROR(S53/T53,"")) | V53: =IF($B53="","",P53+S53) | W53: =IF($B53="","",M53-J53) | X53: =IF($B53="","",IFERROR(V53/W53,"")) | Y53: =IF($B53="","",V53-W53)
A54: =IF($B54="","",ROW()-3) | B54: =IF(50+1>COUNTA('维度字典'!$C$2:$C$200)*COUNTA('维度字典'!$A$2:$A$200)*COUNTA('维度字典'!$E$2:$E$200),"",INDEX('维度字典'!$C$2:$C$200,MOD(INT(50/(COUNTA('维度字典'!$E$2:$E$200)*COUNTA('维度字典'!$A$2:$A$200))),COUNTA('维度字典'!$C$2:$C$200))+1)) | C54: =IF($B54="","",INDEX('维度字典'!$A$2:$A$200,MOD(INT(50/COUNTA('维度字典'!$E$2:$E$200)),COUNTA('维度字典'!$A$2:$A$200))+1)) | D54: =IF($B54="","",INDEX('维度字典'!$E$2:$E$200,MOD(50,COUNTA('维度字典'!$E$2:$E$200))+1)) | E54: =IF($B54="","",SUMPRODUCT(('系统实绩导入'!$B$4:$B$1500=$B54)*('系统实绩导入'!$C$4:$C$1500=$C54)*('系统实绩导入'!$D$4:$D$1500=$D54)*('系统实绩导入'!$F$4:$F$1500="实绩销售额")*('系统实绩导入'!$G$3:$R$3=$F$1)*'系统实绩导入'!$G$4:$R$1500)) | F54: =IF($B54="","",SUMPRODUCT(('系统实绩导入'!$B$4:$B$1500=$B54)*('系统实绩导入'!$C$4:$C$1500=$C54)*('系统实绩导入'!$D$4:$D$1500=$D54)*('系统实绩导入'!$F$4:$F$1500="实绩毛利")*('系统实绩导入'!$G$3:$R$3=$F$1)*'系统实绩导入'!$G$4:$R$1500)) | G54: =IF($B54="","",IFERROR(F54/E54,"")) | H54: =IF($B54="","",SUMPRODUCT(('目标填报'!$B$4:$B$1500=$B54)*('目标填报'!$C$4:$C$1500=$C54)*('目标填报'!$D$4:$D$1500=$D54)*('目标填报'!$F$4:$F$1500="销售目标额")*('目标填报'!$G$3:$R$3=$F$1)*'目标填报'!$G$4:$R$1500)) | I54: =IF($B54="","",IFERROR(E54/H54,"")) | J54: =IF($B54="","",SUMPRODUCT(('系统实绩导入'!$B$4:$B$1500=$B54)*('系统实绩导入'!$C$4:$C$1500=$C54)*('系统实绩导入'!$D$4:$D$1500=$D54)*('系统实绩导入'!$F$4:$F$1500="实绩销售额")*('系统实绩导入'!$G$3:$R$3<=$F$1)*'系统实绩导入'!$G$4:$R$1500)) | K54: =IF($B54="","",SUMPRODUCT(('系统实绩导入'!$B$4:$B$1500=$B54)*('系统实绩导入'!$C$4:$C$1500=$C54)*('系统实绩导入'!$D$4:$D$1500=$D54)*('系统实绩导入'!$F$4:$F$1500="实绩毛利")*('系统实绩导入'!$G$3:$R$3<=$F$1)*'系统实绩导入'!$G$4:$R$1500)) | L54: =IF($B54="","",IFERROR(K54/J54,"")) | M54: =IF($B54="","",SUMIFS('目标填报'!$S$4:$S$1500,'目标填报'!$B$4:$B$1500,$B54,'目标填报'!$C$4:$C$1500,$C54,'目标填报'!$D$4:$D$1500,$D54,'目标填报'!$F$4:$F$1500,"销售目标额")) | N54: =IF($B54="","",IFERROR(J54/M54,"")) | O54: =IF($B54="","",J54-M54) | P54: =IF($B54="","",SUMPRODUCT(('目标填报'!$B$4:$B$1500=$B54)*('目标填报'!$C$4:$C$1500=$C54)*('目标填报'!$D$4:$D$1500=$D54)*('目标填报'!$F$4:$F$1500="在手订单")*('目标填报'!$G$3:$R$3=$F$1)*'目标填报'!$G$4:$R$1500)) | Q54: =IF($B54="","",SUMPRODUCT(('目标填报'!$B$4:$B$1500=$B54)*('目标填报'!$C$4:$C$1500=$C54)*('目标填报'!$D$4:$D$1500=$D54)*('目标填报'!$F$4:$F$1500="在手订单目标")*('目标填报'!$G$3:$R$3=$F$1)*'目标填报'!$G$4:$R$1500)) | R54: =IF($B54="","",IFERROR(P54/Q54,"")) | S54: =IF($B54="","",SUMPRODUCT(('目标填报'!$B$4:$B$1500=$B54)*('目标填报'!$C$4:$C$1500=$C54)*('目标填报'!$D$4:$D$1500=$D54)*('目标填报'!$F$4:$F$1500="目标客户机会")*('目标填报'!$G$3:$R$3=$F$1)*'目标填报'!$G$4:$R$1500)) | T54: =IF($B54="","",SUMPRODUCT(('目标填报'!$B$4:$B$1500=$B54)*('目标填报'!$C$4:$C$1500=$C54)*('目标填报'!$D$4:$D$1500=$D54)*('目标填报'!$F$4:$F$1500="目标客户机会目标")*('目标填报'!$G$3:$R$3=$F$1)*'目标填报'!$G$4:$R$1500)) | U54: =IF($B54="","",IFERROR(S54/T54,"")) | V54: =IF($B54="","",P54+S54) | W54: =IF($B54="","",M54-J54) | X54: =IF($B54="","",IFERROR(V54/W54,"")) | Y54: =IF($B54="","",V54-W54)
A55: =IF($B55="","",ROW()-3) | B55: =IF(51+1>COUNTA('维度字典'!$C$2:$C$200)*COUNTA('维度字典'!$A$2:$A$200)*COUNTA('维度字典'!$E$2:$E$200),"",INDEX('维度字典'!$C$2:$C$200,MOD(INT(51/(COUNTA('维度字典'!$E$2:$E$200)*COUNTA('维度字典'!$A$2:$A$200))),COUNTA('维度字典'!$C$2:$C$200))+1)) | C55: =IF($B55="","",INDEX('维度字典'!$A$2:$A$200,MOD(INT(51/COUNTA('维度字典'!$E$2:$E$200)),COUNTA('维度字典'!$A$2:$A$200))+1)) | D55: =IF($B55="","",INDEX('维度字典'!$E$2:$E$200,MOD(51,COUNTA('维度字典'!$E$2:$E$200))+1)) | E55: =IF($B55="","",SUMPRODUCT(('系统实绩导入'!$B$4:$B$1500=$B55)*('系统实绩导入'!$C$4:$C$1500=$C55)*('系统实绩导入'!$D$4:$D$1500=$D55)*('系统实绩导入'!$F$4:$F$1500="实绩销售额")*('系统实绩导入'!$G$3:$R$3=$F$1)*'系统实绩导入'!$G$4:$R$1500)) | F55: =IF($B55="","",SUMPRODUCT(('系统实绩导入'!$B$4:$B$1500=$B55)*('系统实绩导入'!$C$4:$C$1500=$C55)*('系统实绩导入'!$D$4:$D$1500=$D55)*('系统实绩导入'!$F$4:$F$1500="实绩毛利")*('系统实绩导入'!$G$3:$R$3=$F$1)*'系统实绩导入'!$G$4:$R$1500)) | G55: =IF($B55="","",IFERROR(F55/E55,"")) | H55: =IF($B55="","",SUMPRODUCT(('目标填报'!$B$4:$B$1500=$B55)*('目标填报'!$C$4:$C$1500=$C55)*('目标填报'!$D$4:$D$1500=$D55)*('目标填报'!$F$4:$F$1500="销售目标额")*('目标填报'!$G$3:$R$3=$F$1)*'目标填报'!$G$4:$R$1500)) | I55: =IF($B55="","",IFERROR(E55/H55,"")) | J55: =IF($B55="","",SUMPRODUCT(('系统实绩导入'!$B$4:$B$1500=$B55)*('系统实绩导入'!$C$4:$C$1500=$C55)*('系统实绩导入'!$D$4:$D$1500=$D55)*('系统实绩导入'!$F$4:$F$1500="实绩销售额")*('系统实绩导入'!$G$3:$R$3<=$F$1)*'系统实绩导入'!$G$4:$R$1500)) | K55: =IF($B55="","",SUMPRODUCT(('系统实绩导入'!$B$4:$B$1500=$B55)*('系统实绩导入'!$C$4:$C$1500=$C55)*('系统实绩导入'!$D$4:$D$1500=$D55)*('系统实绩导入'!$F$4:$F$1500="实绩毛利")*('系统实绩导入'!$G$3:$R$3<=$F$1)*'系统实绩导入'!$G$4:$R$1500)) | L55: =IF($B55="","",IFERROR(K55/J55,"")) | M55: =IF($B55="","",SUMIFS('目标填报'!$S$4:$S$1500,'目标填报'!$B$4:$B$1500,$B55,'目标填报'!$C$4:$C$1500,$C55,'目标填报'!$D$4:$D$1500,$D55,'目标填报'!$F$4:$F$1500,"销售目标额")) | N55: =IF($B55="","",IFERROR(J55/M55,"")) | O55: =IF($B55="","",J55-M55) | P55: =IF($B55="","",SUMPRODUCT(('目标填报'!$B$4:$B$1500=$B55)*('目标填报'!$C$4:$C$1500=$C55)*('目标填报'!$D$4:$D$1500=$D55)*('目标填报'!$F$4:$F$1500="在手订单")*('目标填报'!$G$3:$R$3=$F$1)*'目标填报'!$G$4:$R$1500)) | Q55: =IF($B55="","",SUMPRODUCT(('目标填报'!$B$4:$B$1500=$B55)*('目标填报'!$C$4:$C$1500=$C55)*('目标填报'!$D$4:$D$1500=$D55)*('目标填报'!$F$4:$F$1500="在手订单目标")*('目标填报'!$G$3:$R$3=$F$1)*'目标填报'!$G$4:$R$1500)) | R55: =IF($B55="","",IFERROR(P55/Q55,"")) | S55: =IF($B55="","",SUMPRODUCT(('目标填报'!$B$4:$B$1500=$B55)*('目标填报'!$C$4:$C$1500=$C55)*('目标填报'!$D$4:$D$1500=$D55)*('目标填报'!$F$4:$F$1500="目标客户机会")*('目标填报'!$G$3:$R$3=$F$1)*'目标填报'!$G$4:$R$1500)) | T55: =IF($B55="","",SUMPRODUCT(('目标填报'!$B$4:$B$1500=$B55)*('目标填报'!$C$4:$C$1500=$C55)*('目标填报'!$D$4:$D$1500=$D55)*('目标填报'!$F$4:$F$1500="目标客户机会目标")*('目标填报'!$G$3:$R$3=$F$1)*'目标填报'!$G$4:$R$1500)) | U55: =IF($B55="","",IFERROR(S55/T55,"")) | V55: =IF($B55="","",P55+S55) | W55: =IF($B55="","",M55-J55) | X55: =IF($B55="","",IFERROR(V55/W55,"")) | Y55: =IF($B55="","",V55-W55)
A56: =IF($B56="","",ROW()-3) | B56: =IF(52+1>COUNTA('维度字典'!$C$2:$C$200)*COUNTA('维度字典'!$A$2:$A$200)*COUNTA('维度字典'!$E$2:$E$200),"",INDEX('维度字典'!$C$2:$C$200,MOD(INT(52/(COUNTA('维度字典'!$E$2:$E$200)*COUNTA('维度字典'!$A$2:$A$200))),COUNTA('维度字典'!$C$2:$C$200))+1)) | C56: =IF($B56="","",INDEX('维度字典'!$A$2:$A$200,MOD(INT(52/COUNTA('维度字典'!$E$2:$E$200)),COUNTA('维度字典'!$A$2:$A$200))+1)) | D56: =IF($B56="","",INDEX('维度字典'!$E$2:$E$200,MOD(52,COUNTA('维度字典'!$E$2:$E$200))+1)) | E56: =IF($B56="","",SUMPRODUCT(('系统实绩导入'!$B$4:$B$1500=$B56)*('系统实绩导入'!$C$4:$C$1500=$C56)*('系统实绩导入'!$D$4:$D$1500=$D56)*('系统实绩导入'!$F$4:$F$1500="实绩销售额")*('系统实绩导入'!$G$3:$R$3=$F$1)*'系统实绩导入'!$G$4:$R$1500)) | F56: =IF($B56="","",SUMPRODUCT(('系统实绩导入'!$B$4:$B$1500=$B56)*('系统实绩导入'!$C$4:$C$1500=$C56)*('系统实绩导入'!$D$4:$D$1500=$D56)*('系统实绩导入'!$F$4:$F$1500="实绩毛利")*('系统实绩导入'!$G$3:$R$3=$F$1)*'系统实绩导入'!$G$4:$R$1500)) | G56: =IF($B56="","",IFERROR(F56/E56,"")) | H56: =IF($B56="","",SUMPRODUCT(('目标填报'!$B$4:$B$1500=$B56)*('目标填报'!$C$4:$C$1500=$C56)*('目标填报'!$D$4:$D$1500=$D56)*('目标填报'!$F$4:$F$1500="销售目标额")*('目标填报'!$G$3:$R$3=$F$1)*'目标填报'!$G$4:$R$1500)) | I56: =IF($B56="","",IFERROR(E56/H56,"")) | J56: =IF($B56="","",SUMPRODUCT(('系统实绩导入'!$B$4:$B$1500=$B56)*('系统实绩导入'!$C$4:$C$1500=$C56)*('系统实绩导入'!$D$4:$D$1500=$D56)*('系统实绩导入'!$F$4:$F$1500="实绩销售额")*('系统实绩导入'!$G$3:$R$3<=$F$1)*'系统实绩导入'!$G$4:$R$1500)) | K56: =IF($B56="","",SUMPRODUCT(('系统实绩导入'!$B$4:$B$1500=$B56)*('系统实绩导入'!$C$4:$C$1500=$C56)*('系统实绩导入'!$D$4:$D$1500=$D56)*('系统实绩导入'!$F$4:$F$1500="实绩毛利")*('系统实绩导入'!$G$3:$R$3<=$F$1)*'系统实绩导入'!$G$4:$R$1500)) | L56: =IF($B56="","",IFERROR(K56/J56,"")) | M56: =IF($B56="","",SUMIFS('目标填报'!$S$4:$S$1500,'目标填报'!$B$4:$B$1500,$B56,'目标填报'!$C$4:$C$1500,$C56,'目标填报'!$D$4:$D$1500,$D56,'目标填报'!$F$4:$F$1500,"销售目标额")) | N56: =IF($B56="","",IFERROR(J56/M56,"")) | O56: =IF($B56="","",J56-M56) | P56: =IF($B56="","",SUMPRODUCT(('目标填报'!$B$4:$B$1500=$B56)*('目标填报'!$C$4:$C$1500=$C56)*('目标填报'!$D$4:$D$1500=$D56)*('目标填报'!$F$4:$F$1500="在手订单")*('目标填报'!$G$3:$R$3=$F$1)*'目标填报'!$G$4:$R$1500)) | Q56: =IF($B56="","",SUMPRODUCT(('目标填报'!$B$4:$B$1500=$B56)*('目标填报'!$C$4:$C$1500=$C56)*('目标填报'!$D$4:$D$1500=$D56)*('目标填报'!$F$4:$F$1500="在手订单目标")*('目标填报'!$G$3:$R$3=$F$1)*'目标填报'!$G$4:$R$1500)) | R56: =IF($B56="","",IFERROR(P56/Q56,"")) | S56: =IF($B56="","",SUMPRODUCT(('目标填报'!$B$4:$B$1500=$B56)*('目标填报'!$C$4:$C$1500=$C56)*('目标填报'!$D$4:$D$1500=$D56)*('目标填报'!$F$4:$F$1500="目标客户机会")*('目标填报'!$G$3:$R$3=$F$1)*'目标填报'!$G$4:$R$1500)) | T56: =IF($B56="","",SUMPRODUCT(('目标填报'!$B$4:$B$1500=$B56)*('目标填报'!$C$4:$C$1500=$C56)*('目标填报'!$D$4:$D$1500=$D56)*('目标填报'!$F$4:$F$1500="目标客户机会目标")*('目标填报'!$G$3:$R$3=$F$1)*'目标填报'!$G$4:$R$1500)) | U56: =IF($B56="","",IFERROR(S56/T56,"")) | V56: =IF($B56="","",P56+S56) | W56: =IF($B56="","",M56-J56) | X56: =IF($B56="","",IFERROR(V56/W56,"")) | Y56: =IF($B56="","",V56-W56)
A57: =IF($B57="","",ROW()-3) | B57: =IF(53+1>COUNTA('维度字典'!$C$2:$C$200)*COUNTA('维度字典'!$A$2:$A$200)*COUNTA('维度字典'!$E$2:$E$200),"",INDEX('维度字典'!$C$2:$C$200,MOD(INT(53/(COUNTA('维度字典'!$E$2:$E$200)*COUNTA('维度字典'!$A$2:$A$200))),COUNTA('维度字典'!$C$2:$C$200))+1)) | C57: =IF($B57="","",INDEX('维度字典'!$A$2:$A$200,MOD(INT(53/COUNTA('维度字典'!$E$2:$E$200)),COUNTA('维度字典'!$A$2:$A$200))+1)) | D57: =IF($B57="","",INDEX('维度字典'!$E$2:$E$200,MOD(53,COUNTA('维度字典'!$E$2:$E$200))+1)) | E57: =IF($B57="","",SUMPRODUCT(('系统实绩导入'!$B$4:$B$1500=$B57)*('系统实绩导入'!$C$4:$C$1500=$C57)*('系统实绩导入'!$D$4:$D$1500=$D57)*('系统实绩导入'!$F$4:$F$1500="实绩销售额")*('系统实绩导入'!$G$3:$R$3=$F$1)*'系统实绩导入'!$G$4:$R$1500)) | F57: =IF($B57="","",SUMPRODUCT(('系统实绩导入'!$B$4:$B$1500=$B57)*('系统实绩导入'!$C$4:$C$1500=$C57)*('系统实绩导入'!$D$4:$D$1500=$D57)*('系统实绩导入'!$F$4:$F$1500="实绩毛利")*('系统实绩导入'!$G$3:$R$3=$F$1)*'系统实绩导入'!$G$4:$R$1500)) | G57: =IF($B57="","",IFERROR(F57/E57,"")) | H57: =IF($B57="","",SUMPRODUCT(('目标填报'!$B$4:$B$1500=$B57)*('目标填报'!$C$4:$C$1500=$C57)*('目标填报'!$D$4:$D$1500=$D57)*('目标填报'!$F$4:$F$1500="销售目标额")*('目标填报'!$G$3:$R$3=$F$1)*'目标填报'!$G$4:$R$1500)) | I57: =IF($B57="","",IFERROR(E57/H57,"")) | J57: =IF($B57="","",SUMPRODUCT(('系统实绩导入'!$B$4:$B$1500=$B57)*('系统实绩导入'!$C$4:$C$1500=$C57)*('系统实绩导入'!$D$4:$D$1500=$D57)*('系统实绩导入'!$F$4:$F$1500="实绩销售额")*('系统实绩导入'!$G$3:$R$3<=$F$1)*'系统实绩导入'!$G$4:$R$1500)) | K57: =IF($B57="","",SUMPRODUCT(('系统实绩导入'!$B$4:$B$1500=$B57)*('系统实绩导入'!$C$4:$C$1500=$C57)*('系统实绩导入'!$D$4:$D$1500=$D57)*('系统实绩导入'!$F$4:$F$1500="实绩毛利")*('系统实绩导入'!$G$3:$R$3<=$F$1)*'系统实绩导入'!$G$4:$R$1500)) | L57: =IF($B57="","",IFERROR(K57/J57,"")) | M57: =IF($B57="","",SUMIFS('目标填报'!$S$4:$S$1500,'目标填报'!$B$4:$B$1500,$B57,'目标填报'!$C$4:$C$1500,$C57,'目标填报'!$D$4:$D$1500,$D57,'目标填报'!$F$4:$F$1500,"销售目标额")) | N57: =IF($B57="","",IFERROR(J57/M57,"")) | O57: =IF($B57="","",J57-M57) | P57: =IF($B57="","",SUMPRODUCT(('目标填报'!$B$4:$B$1500=$B57)*('目标填报'!$C$4:$C$1500=$C57)*('目标填报'!$D$4:$D$1500=$D57)*('目标填报'!$F$4:$F$1500="在手订单")*('目标填报'!$G$3:$R$3=$F$1)*'目标填报'!$G$4:$R$1500)) | Q57: =IF($B57="","",SUMPRODUCT(('目标填报'!$B$4:$B$1500=$B57)*('目标填报'!$C$4:$C$1500=$C57)*('目标填报'!$D$4:$D$1500=$D57)*('目标填报'!$F$4:$F$1500="在手订单目标")*('目标填报'!$G$3:$R$3=$F$1)*'目标填报'!$G$4:$R$1500)) | R57: =IF($B57="","",IFERROR(P57/Q57,"")) | S57: =IF($B57="","",SUMPRODUCT(('目标填报'!$B$4:$B$1500=$B57)*('目标填报'!$C$4:$C$1500=$C57)*('目标填报'!$D$4:$D$1500=$D57)*('目标填报'!$F$4:$F$1500="目标客户机会")*('目标填报'!$G$3:$R$3=$F$1)*'目标填报'!$G$4:$R$1500)) | T57: =IF($B57="","",SUMPRODUCT(('目标填报'!$B$4:$B$1500=$B57)*('目标填报'!$C$4:$C$1500=$C57)*('目标填报'!$D$4:$D$1500=$D57)*('目标填报'!$F$4:$F$1500="目标客户机会目标")*('目标填报'!$G$3:$R$3=$F$1)*'目标填报'!$G$4:$R$1500)) | U57: =IF($B57="","",IFERROR(S57/T57,"")) | V57: =IF($B57="","",P57+S57) | W57: =IF($B57="","",M57-J57) | X57: =IF($B57="","",IFERROR(V57/W57,"")) | Y57: =IF($B57="","",V57-W57)
